Workbook

Sheet Supuestos y Consideraciones
B2: Supuestos y consideraciones
B4: Posibles variables que definen a un escenario | K4: Parámetros relevantes del Sistema Eléctrico en Chile
B5: 1) Extensión del despliegue (% de consumidores). | K5: Parámetro | Q5: Unidad | R5: Valor | S5: Comentario
B6: 2) Tiempo de plazo para el despliegue. | K6: Variación proyectada del consumo de energía | Q6: %
B7: 3) Número de funcionalidades del Sistema de Medición Inteligente. | K7: Variación proyectada de los precios de la energía | Q7: %
B8: 4) Densidad de clientes en el despliegue (Urbano vs Rural). | K8: Transferencia de carga de punta | Q8: %
K9: Pérdidas eléctricas en niveles de transmisión y distribución | Q9: %
K10: Minutos no suministrados estimados | Q10: Cantidad
B11: Escenario 0 (Caso Base, sin despliegue): | K11: Valor de Energía No Suministrada; valor del suministro | Q11: $/kWh
B12: Variables | H12: Valor | K12: Tasa de descuento | Q12: %
B13: 1) Extensión del despliegue (% de consumidores). | H13: 0 | K13: Costos de hardware (p. ej, medidor inteligente, módem GPRS/PLC, etc.) | Q13: $
B14: 2) Tiempo de plazo para el despliegue. | H14: 2030 | K14: Número de medidores inteligentes a instalar | Q14: Cantidad
B15: 3) Número de funcionalidades del Sistema de Medición Inteligente. | H15: 0 | K15: Costos de instalación del sistema de medición inteligente | Q15: $
K16: Vida útil del sistema de medición inteligente | Q16: Años
K17: Costos de lectura de medidores | Q17: $/año
B18: Escenario 1: | K18: Tasa de éxito de telecomunicación | Q18: %
B19: Variables | H19: Valor | K19: Tasa de inflación | Q19: %
B20: 1) Extensión del despliegue (% de consumidores). | H20: 0.8 | K20: Reducción de costos asociada a la madurez tecnológica | Q20: %
B21: 2) Tiempo de plazo para el despliegue. | H21: 2030 | K21: Calendario de implementación | Q21: Cantidad/año
B22: 3) Número de funcionalidades del Sistema de Medición Inteligente. | H22: 10 | K22: Porcentaje de medidores ubicados en zonas rurales vs urbanas | Q22: %
K23: Costos de carbono | Q23: $/ton

Sheet CB_SMI_Mixto
A1: Concepto | B1: Periodo 0 | C1: Periodo 1 | D1: Periodo 2 | E1: Periodo 3 | F1: Periodo 4 | G1: Periodo 5 | H1: Periodo 6 | I1: Periodo 7 | J1: Periodo 8 | K1: Periodo 9 | L1: Periodo 10 | M1: Periodo 11 | N1: Periodo 12 | O1: Periodo 13 | P1: Periodo 14 | Q1: Periodo 15
A2: Energía facturada anual [MWh/año] | B2: 34765766 | C2: 35815692 | D2: 36897326 | E2: 38011625 | F2: 39159576 | G2: 40342196 | H2: 41560530 | I2: 42815658 | J2: 44108691 | K2: 45440773 | L2: 46813085 | M2: 48226840 | N2: 49683290 | O2: 51183726 | P2: 52729474 | Q2: 54321904
A3: Cantidad UM 1F | B3: 22317 | C3: 58 | D3: 58 | E3: 59 | F3: 59 | G3: 62 | H3: 62 | I3: 62 | J3: 62 | K3: 62 | L3: 62 | M3: 62 | N3: 62 | O3: 63 | P3: 64 | Q3: 64
A4: Cantidad UM 3F Directa | B4: 0 | C4: 0 | D4: 0 | E4: 0 | F4: 0 | G4: 0 | H4: 0 | I4: 0 | J4: 0 | K4: 0 | L4: 0 | M4: 0 | N4: 0 | O4: 0 | P4: 0 | Q4: 0
A5: Cantidad UM 3F Indirecta | B5: 215824 | C5: 734 | D5: 734 | E5: 739 | F5: 741 | G5: 750 | H5: 750 | I5: 755 | J5: 757 | K5: 757 | L5: 757 | M5: 762 | N5: 768 | O5: 774 | P5: 780 | Q5: 788
A6: Cantidad DCU | B6: 0 | C6: 0 | D6: 0 | E6: 0 | F6: 0 | G6: 0 | H6: 0 | I6: 0 | J6: 0 | K6: 0 | L6: 0 | M6: 0 | N6: 0 | O6: 0 | P6: 0 | Q6: 0
A7: Inversión UM 1F [USD/equipo] | B7: 181.40918 | C7: 175.08079 | D7: 175.08079 | E7: 174.30668 | F7: 174.30668 | G7: 173.3395 | H7: 173.3395 | I7: 173.3395 | J7: 173.3395 | K7: 173.3395 | L7: 173.3395 | M7: 173.3395 | N7: 173.3395 | O7: 173.53149 | P7: 173.71748 | Q7: 173.71748
A8: Inversión UM 3F Directa [USD/equipo] | B8: 0 | C8: 0 | D8: 0 | E8: 0 | F8: 0 | G8: 0 | H8: 0 | I8: 0 | J8: 0 | K8: 0 | L8: 0 | M8: 0 | N8: 0 | O8: 0 | P8: 0 | Q8: 0
A9: Inversión UM 3F Indirecta [USD/equipo] | B9: 789.11275 | C9: 747.70341 | D9: 747.70341 | E9: 747.58392 | F9: 747.671 | G9: 747.89109 | H9: 747.89109 | I9: 747.93781 | J9: 747.85763 | K9: 747.85763 | L9: 747.85763 | M9: 747.90414 | N9: 747.99157 | O9: 747.99721 | P9: 747.92295 | Q9: 747.77303
A10: Inversión DCU [USD/equipo] | B10: 0 | C10: 0 | D10: 0 | E10: 0 | F10: 0 | G10: 0 | H10: 0 | I10: 0 | J10: 0 | K10: 0 | L10: 0 | M10: 0 | N10: 0 | O10: 0 | P10: 0 | Q10: 0
A11: Inversión SGO [USD] | B11: 4370125.5 | C11: 14533.992 | D11: 14533.992 | E11: 14644.098 | F11: 14680.8 | G11: 14901.012 | H11: 14901.012 | I11: 14992.767 | J11: 15029.469 | K11: 15029.469 | L11: 15029.469 | M11: 15121.224 | N11: 15231.33 | O11: 15359.787 | P11: 15488.244 | Q11: 15635.052
A12: Inversión MDMS [USD] | B12: 328383.91 | C12: 1092.1263 | D12: 1092.1263 | E12: 1100.4 | F12: 1103.1579 | G12: 1119.7053 | H12: 1119.7053 | I12: 1126.6 | J12: 1129.3579 | K12: 1129.3579 | L12: 1129.3579 | M12: 1136.2526 | N12: 1144.5263 | O12: 1154.1789 | P12: 1163.8316 | Q12: 1174.8632
A13: Operación Comunicaciones [USD/año] | B13: 0 | C13: 0 | D13: 0 | E13: 0 | F13: 0 | G13: 0 | H13: 0 | I13: 0 | J13: 0 | K13: 0 | L13: 0 | M13: 0 | N13: 0 | O13: 0 | P13: 0 | Q13: 0
... A26: Ahorro por inversión evitada [USD/año] | B26: 14938965 | C26: 14949967 | D26: 14961276 | E26: 15126164 | F26: 15161638 | G26: 15184728 | H26: 15201352 | I26: 15217576 | J26: 15343357 | K26: 15375861 | L26: 15401600 | M26: 15427401 | N26: 15457996 | O26: 15503510 | P26: 15549159 | Q26: 15594942

Sheet Flujo SMI_Mixto
B2: Escenario de implementación | G2: Supuestos y Consideraciones
B4: Densidad de clientes | D4: Tecnología | G4: Tasa de descuento | J4: 0.06 | K4: % | R4: Dólar | S4: 959.36 | T4: USD/$ | U4: 45946
B5: Alta | D5: Mixto | G5: Vida útil del proyecto | J5: 15 | K5: años | R5: UF | S5: 39521.26 | T5: UF/$ | U5: 45946
B6: Media | D6: Mixto | G6: Meta de despligue | J6: 3 | K6: años
B7: Baja | D7: Mixto | G7: Objetivo de despligue UM 1F | J7: =(SUMIF($F$12:$U$12,"<="&$J$6,$F$17:$U$17)) / ($J$6) -> 7497.3333 | K7: UM/año | L7: ="Razonable para chile en torno a 1M y 1,5M por año." -> Razonable para chile en torno a 1M y 1,5M por año.
B8: Muy Baja | D8: Mixto | G8: Objetivo de despligue UM 3F Directa | J8: =(SUMIF($F$12:$U$12,"<="&$J$6,$F$18:$U$18)) / ($J$6) -> 0 | K8: UM/año | L8: ="Razonable para chile en torno a 1M y 1,5M por año." -> Razonable para chile en torno a 1M y 1,5M por año.
B9: Extremadamente Baja | D9: Mixto | G9: Objetivo de despligue UM 3F Indirecta | J9: =(SUMIF($F$12:$U$12,"<="&$J$6,$F$19:$U$19)) / ($J$6) -> 72677 | K9: UM/año | L9: ="Razonable para chile en torno a 1M y 1,5M por año." -> Razonable para chile en torno a 1M y 1,5M por año.
B12: Despligue SMI Chile | E12: Periodo | F12: 0 | G12: 1 | H12: 2 | I12: 3 | J12: 4 | K12: 5 | L12: 6 | M12: 7 | N12: 8 | O12: 9 | P12: 10 | Q12: 11 | R12: 12 | S12: 13 | T12: 14 | U12: 15
E13: Año | F13: 2025 | G13: 2026 | H13: 2027 | I13: 2028 | J13: 2029 | K13: 2030 | L13: 2031 | M13: 2032 | N13: 2033 | O13: 2034 | P13: 2035 | Q13: 2036 | R13: 2037 | S13: 2038 | T13: 2039 | U13: 2040
B15: Datos de despliegue | C15: Energía Facturada anual [GWh] | F15: =CB_SMI_Mixto!B2/1000 -> 34765.766 | G15: =CB_SMI_Mixto!C2/1000 -> 35815.692 | H15: =CB_SMI_Mixto!D2/1000 -> 36897.326 | I15: =CB_SMI_Mixto!E2/1000 -> 38011.625 | J15: =CB_SMI_Mixto!F2/1000 -> 39159.576 | K15: =CB_SMI_Mixto!G2/1000 -> 40342.196 | L15: =CB_SMI_Mixto!H2/1000 -> 41560.53 | M15: =CB_SMI_Mixto!I2/1000 -> 42815.658 | ... U15: =CB_SMI_Mixto!Q2/1000 -> 54321.904
C17: UM 1F [N° Equipos] | F17: =CB_SMI_Mixto!B3 -> 22317 | G17: =CB_SMI_Mixto!C3 -> 58 | H17: =CB_SMI_Mixto!D3 -> 58 | I17: =CB_SMI_Mixto!E3 -> 59 | J17: =CB_SMI_Mixto!F3 -> 59 | K17: =CB_SMI_Mixto!G3 -> 62 | L17: =CB_SMI_Mixto!H3 -> 62 | M17: =CB_SMI_Mixto!I3 -> 62 | ... U17: =CB_SMI_Mixto!Q3 -> 64
C18: UM 3F Directa [N° Equipos] | F18: =CB_SMI_Mixto!B4 -> 0 | G18: =CB_SMI_Mixto!C4 -> 0 | H18: =CB_SMI_Mixto!D4 -> 0 | I18: =CB_SMI_Mixto!E4 -> 0 | J18: =CB_SMI_Mixto!F4 -> 0 | K18: =CB_SMI_Mixto!G4 -> 0 | L18: =CB_SMI_Mixto!H4 -> 0 | M18: =CB_SMI_Mixto!I4 -> 0 | ... U18: =CB_SMI_Mixto!Q4 -> 0
C19: UM 3F Indirecta [N° Equipos] | F19: =CB_SMI_Mixto!B5 -> 215824 | G19: =CB_SMI_Mixto!C5 -> 734 | H19: =CB_SMI_Mixto!D5 -> 734 | I19: =CB_SMI_Mixto!E5 -> 739 | J19: =CB_SMI_Mixto!F5 -> 741 | K19: =CB_SMI_Mixto!G5 -> 750 | L19: =CB_SMI_Mixto!H5 -> 750 | M19: =CB_SMI_Mixto!I5 -> 755 | ... U19: =CB_SMI_Mixto!Q5 -> 788
B21: Despliegue | C21: UM 1F instalados | F21: 0 | G21: =IF(G$12<=$J$6,$J7,G17) -> 7497.3333 | H21: =IF(H$12<=$J$6,$J7,H17) -> 7497.3333 | I21: =IF(I$12<=$J$6,$J7,I17) -> 7497.3333 | J21: =IF(J$12<=$J$6,$J7,J17) -> 59 | K21: =IF(K$12<=$J$6,$J7,K17) -> 62 | L21: =IF(L$12<=$J$6,$J7,L17) -> 62 | M21: =IF(M$12<=$J$6,$J7,M17) -> 62 | N21: =IF(N$12<=$J$6,$J7,N17) -> 62 | ... U21: =IF(U$12<=$J$6,$J7,U17) -> 64
C22: UM 3F Directa instalados | F22: 0 | G22: =IF(G$12<=$J$6,$J8,G18) -> 0 | H22: =IF(H$12<=$J$6,$J8,H18) -> 0 | I22: =IF(I$12<=$J$6,$J8,I18) -> 0 | J22: =IF(J$12<=$J$6,$J8,J18) -> 0 | K22: =IF(K$12<=$J$6,$J8,K18) -> 0 | L22: =IF(L$12<=$J$6,$J8,L18) -> 0 | M22: =IF(M$12<=$J$6,$J8,M18) -> 0 | N22: =IF(N$12<=$J$6,$J8,N18) -> 0 | ... U22: =IF(U$12<=$J$6,$J8,U18) -> 0
C23: UM 3F Indirecta instalados | F23: 0 | G23: =IF(G$12<=$J$6,$J9,G19) -> 72677 | H23: =IF(H$12<=$J$6,$J9,H19) -> 72677 | I23: =IF(I$12<=$J$6,$J9,I19) -> 72677 | J23: =IF(J$12<=$J$6,$J9,J19) -> 741 | K23: =IF(K$12<=$J$6,$J9,K19) -> 750 | L23: =IF(L$12<=$J$6,$J9,L19) -> 750 | M23: =IF(M$12<=$J$6,$J9,M19) -> 755 | N23: =IF(N$12<=$J$6,$J9,N19) -> 757 | ... U23: =IF(U$12<=$J$6,$J9,U19) -> 788
C24: UM faltantes por instalar | F24: =SUM(F17:F19) -> 238141 | G24: =SUM(F24,G17:G19)-SUM(G21:G23) -> 158758.67 | H24: =SUM(G24,H17:H19)-SUM(H21:H23) -> 79376.333 | I24: =SUM(H24,I17:I19)-SUM(I21:I23) -> 0 | J24: =SUM(I24,J17:J19)-SUM(J21:J23) -> 0 | K24: =SUM(J24,K17:K19)-SUM(K21:K23) -> 0 | L24: =SUM(K24,L17:L19)-SUM(L21:L23) -> 0 | M24: =SUM(L24,M17:M19)-SUM(M21:M23) -> 0 | N24: =SUM(M24,N17:N19)-SUM(N21:N23) -> 0 | ... U24: =SUM(T24,U17:U19)-SUM(U21:U23) -> 0
C25: % de avance | F25: 0 | G25: =IF(G$12<=$J$6,SUM($F$21:G23)/SUM($F$17:G19),1) -> 0.33555153 | H25: =IF(H$12<=$J$6,SUM($F$21:H23)/SUM($F$17:H19),1) -> 0.66888588 | I25: =IF(I$12<=$J$6,SUM($F$21:I23)/SUM($F$17:I19),1) -> 1 | J25: =IF(J$12<=$J$6,SUM($F$21:J23)/SUM($F$17:J19),1) -> 1 | K25: =IF(K$12<=$J$6,SUM($F$21:K23)/SUM($F$17:K19),1) -> 1 | L25: =IF(L$12<=$J$6,SUM($F$21:L23)/SUM($F$17:L19),1) -> 1 | M25: =IF(M$12<=$J$6,SUM($F$21:M23)/SUM($F$17:M19),1) -> 1 | N25: =IF(N$12<=$J$6,SUM($F$21:N23)/SUM($F$17:N19),1) -> 1 | ... U25: =IF(U$12<=$J$6,SUM($F$21:U23)/SUM($F$17:U19),1) -> 1
B27: Flujo de caja [MUSD] | E27: Periodo | F27: 0 | G27: 1 | H27: 2 | I27: 3 | J27: 4 | K27: 5 | L27: 6 | M27: 7 | N27: 8 | O27: 9 | P27: 10 | Q27: 11 | R27: 12 | S27: 13 | T27: 14 | U27: 15
E28: Año | F28: 2025 | G28: 2026 | H28: 2027 | I28: 2028 | J28: 2029 | K28: 2030 | L28: 2031 | M28: 2032 | N28: 2033 | O28: 2034 | P28: 2035 | Q28: 2036 | R28: 2037 | S28: 2038 | T28: 2039 | U28: 2040 | W28: VAN [MUSD] | X28: AVAN [MUSD] | Y28: VAN [USD/# Clientes] | Z28: Participación %
B30: VI [MUSD] | C30: UM 1F | F30: 0 | G30: =((-CB_SMI_Mixto!C7)*G21)/1000000 -> -1.3126391 | H30: =((-CB_SMI_Mixto!D7)*H21)/1000000 -> -1.3126391 | I30: =((-CB_SMI_Mixto!E7)*I21)/1000000 -> -1.3068353 | J30: =((-CB_SMI_Mixto!F7)*J21)/1000000 -> -0.010284094 | K30: =((-CB_SMI_Mixto!G7)*K21)/1000000 -> -0.010747049 | L30: =((-CB_SMI_Mixto!H7)*L21)/1000000 -> -0.010747049 | M30: =((-CB_SMI_Mixto!I7)*M21)/1000000 -> -0.010747049 | N30: =((-CB_SMI_Mixto!J7)*N21)/1000000 -> -0.010747049 | ... U30: =((-CB_SMI_Mixto!Q7)*U21)/1000000 -> -0.011117919 | W30: =NPV($D$67,G30:U30)+F30 -> -3.5795169 | X30: =PMT($D$67,15,-W30) -> -0.36855696 | Y30: =W30*1000000/7744865 -> -0.46217939 | Z30: =W30/$W$36 -> 0.022701612
C31: UM 3F Directa | F31: 0 | G31: =((-CB_SMI_Mixto!C8)*G22)/1000000 -> 0 | H31: =((-CB_SMI_Mixto!D8)*H22)/1000000 -> 0 | I31: =((-CB_SMI_Mixto!E8)*I22)/1000000 -> 0 | J31: =((-CB_SMI_Mixto!F8)*J22)/1000000 -> 0 | K31: =((-CB_SMI_Mixto!G8)*K22)/1000000 -> 0 | L31: =((-CB_SMI_Mixto!H8)*L22)/1000000 -> 0 | M31: =((-CB_SMI_Mixto!I8)*M22)/1000000 -> 0 | N31: =((-CB_SMI_Mixto!J8)*N22)/1000000 -> 0 | ... U31: =((-CB_SMI_Mixto!Q8)*U22)/1000000 -> 0 | W31: =NPV($D$67,G31:U31)+F31 -> 0 | X31: =PMT($D$67,15,-W31) -> 0 | Y31: =W31*1000000/7744865 -> 0 | Z31: =W31/$W$36 -> 0
C32: UM 3F Indirecta | F32: 0 | G32: =((-CB_SMI_Mixto!C9)*G23)/1000000 -> -54.34084 | H32: =((-CB_SMI_Mixto!D9)*H23)/1000000 -> -54.34084 | I32: =((-CB_SMI_Mixto!E9)*I23)/1000000 -> -54.332156 | J32: =((-CB_SMI_Mixto!F9)*J23)/1000000 -> -0.55402421 | K32: =((-CB_SMI_Mixto!G9)*K23)/1000000 -> -0.56091832 | L32: =((-CB_SMI_Mixto!H9)*L23)/1000000 -> -0.56091832 | M32: =((-CB_SMI_Mixto!I9)*M23)/1000000 -> -0.56469305 | N32: =((-CB_SMI_Mixto!J9)*N23)/1000000 -> -0.56612823 | ... U32: =((-CB_SMI_Mixto!Q9)*U23)/1000000 -> -0.58924515 | W32: =NPV($D$67,G32:U32)+F32 -> -149.24284 | X32: =PMT($D$67,15,-W32) -> -15.366456 | Y32: =W32*1000000/7744865 -> -19.269909 | Z32: =W32/$W$36 -> 0.94651126
C33: DCU | F33: =((-CB_SMI_Mixto!B10)*CB_SMI_Mixto!B6)/1000000 -> 0 | G33: =((-CB_SMI_Mixto!C10)*CB_SMI_Mixto!C6)/1000000 -> 0 | H33: =((-CB_SMI_Mixto!D10)*CB_SMI_Mixto!D6)/1000000 -> 0 | I33: =((-CB_SMI_Mixto!E10)*CB_SMI_Mixto!E6)/1000000 -> 0 | J33: =((-CB_SMI_Mixto!F10)*CB_SMI_Mixto!F6)/1000000 -> 0 | K33: =((-CB_SMI_Mixto!G10)*CB_SMI_Mixto!G6)/1000000 -> 0 | L33: =((-CB_SMI_Mixto!H10)*CB_SMI_Mixto!H6)/1000000 -> 0 | M33: =((-CB_SMI_Mixto!I10)*CB_SMI_Mixto!I6)/1000000 -> 0 | ... U33: =((-CB_SMI_Mixto!Q10)*CB_SMI_Mixto!Q6)/1000000 -> 0 | W33: =NPV($D$67,G33:U33)+F33 -> 0 | X33: =PMT($D$67,15,-W33) -> 0 | Y33: =W33*1000000/7744865 -> 0 | Z33: =W33/$W$36 -> 0
C34: HES | F34: =(-CB_SMI_Mixto!B11)/1000000 -> -4.3701255 | G34: =(-CB_SMI_Mixto!C11)/1000000 -> -0.014533992 | H34: =(-CB_SMI_Mixto!D11)/1000000 -> -0.014533992 | I34: =(-CB_SMI_Mixto!E11)/1000000 -> -0.014644098 | J34: =(-CB_SMI_Mixto!F11)/1000000 -> -0.0146808 | K34: =(-CB_SMI_Mixto!G11)/1000000 -> -0.014901012 | L34: =(-CB_SMI_Mixto!H11)/1000000 -> -0.014901012 | M34: =(-CB_SMI_Mixto!I11)/1000000 -> -0.014992767 | ... U34: =(-CB_SMI_Mixto!Q11)/1000000 -> -0.015635052 | W34: =NPV($D$67,G34:U34)+F34 -> -4.5151355 | X34: =PMT($D$67,15,-W34) -> -0.46489083 | Y34: =W34*1000000/7744865 -> -0.5829844 | Z34: =W34/$W$36 -> 0.028635387
C35: MDMS | F35: =(-CB_SMI_Mixto!B12)/1000000 -> -0.32838391 | G35: =(-CB_SMI_Mixto!C12)/1000000 -> -0.0010921263 | H35: =(-CB_SMI_Mixto!D12)/1000000 -> -0.0010921263 | I35: =(-CB_SMI_Mixto!E12)/1000000 -> -0.0011004 | J35: =(-CB_SMI_Mixto!F12)/1000000 -> -0.0011031579 | K35: =(-CB_SMI_Mixto!G12)/1000000 -> -0.0011197053 | L35: =(-CB_SMI_Mixto!H12)/1000000 -> -0.0011197053 | M35: =(-CB_SMI_Mixto!I12)/1000000 -> -0.0011266 | ... U35: =(-CB_SMI_Mixto!Q12)/1000000 -> -0.0011748632 | W35: =NPV($D$67,G35:U35)+F35 -> -0.33928037 | X35: =PMT($D$67,15,-W35) -> -0.034933245 | Y35: =W35*1000000/7744865 -> -0.043807139 | Z35: =W35/$W$36 -> 0.002151746
C36: VI Total: | F36: =SUM(F30:F35) -> -4.6985094 | G36: =SUM(G30:G35) -> -55.669106 | H36: =SUM(H30:H35) -> -55.669106 | I36: =SUM(I30:I35) -> -55.654736 | J36: =SUM(J30:J35) -> -0.58009226 | K36: =SUM(K30:K35) -> -0.58768609 | L36: =SUM(L30:L35) -> -0.58768609 | M36: =SUM(M30:M35) -> -0.59155946 | ... U36: =SUM(U30:U35) -> -0.61717298 | W36: =NPV($D$67,G36:U36)+F36 -> -157.67678 | X36: =PMT($D$67,15,-W36) -> -16.234837 | Y36: =W36*1000000/7744865 -> -20.35888 | Z36: =W36/$W$36 -> 1
B38: COMA [MUSD] | C38: Operación Comunicaciones UM - SGO | F38: 0 | G38: =(-CB_SMI_Mixto!C13/1000000)*G$25 -> 0 | H38: =(-CB_SMI_Mixto!D13/1000000)*H$25 -> 0 | I38: =(-CB_SMI_Mixto!E13/1000000)*I$25 -> 0 | J38: =(-CB_SMI_Mixto!F13/1000000)*J$25 -> 0 | K38: =(-CB_SMI_Mixto!G13/1000000)*K$25 -> 0 | L38: =(-CB_SMI_Mixto!H13/1000000)*L$25 -> 0 | M38: =(-CB_SMI_Mixto!I13/1000000)*M$25 -> 0 | N38: =(-CB_SMI_Mixto!J13/1000000)*N$25 -> 0 | ... U38: =(-CB_SMI_Mixto!Q13/1000000)*U$25 -> 0 | W38: =NPV($D$67,G38:U38)+F38 -> 0 | X38: =PMT($D$67,15,-W38) -> 0 | Y38: =W38*1000000/7744865 -> 0 | Z38: =W38/$W$43 -> 0
C39: Operación Comunicaciones DCU - SGO | F39: 0 | G39: =(-CB_SMI_Mixto!C14/1000000)*G$25 -> -1.3433597 | H39: =(-CB_SMI_Mixto!D14/1000000)*H$25 -> -2.677843 | I39: =(-CB_SMI_Mixto!E14/1000000)*I$25 -> -4.0034378 | J39: =(-CB_SMI_Mixto!F14/1000000)*J$25 -> -4.0034378 | K39: =(-CB_SMI_Mixto!G14/1000000)*K$25 -> -4.0034378 | L39: =(-CB_SMI_Mixto!H14/1000000)*L$25 -> -4.0034378 | M39: =(-CB_SMI_Mixto!I14/1000000)*M$25 -> -4.0034378 | N39: =(-CB_SMI_Mixto!J14/1000000)*N$25 -> -4.0034378 | ... U39: =(-CB_SMI_Mixto!Q14/1000000)*U$25 -> -4.0034378 | W39: =NPV($D$67,G39:U39)+F39 -> -35.193102 | X39: =PMT($D$67,15,-W39) -> -3.6235791 | Y39: =W39*1000000/7744865 -> -4.5440562 | Z39: =W39/$W$43 -> 0.61274697
C40: Operación HES | F40: 0 | G40: =(-CB_SMI_Mixto!C15/1000000)*G$25 -> -0.64021799 | H40: =(-CB_SMI_Mixto!D15/1000000)*H$25 -> -1.280436 | I40: =(-CB_SMI_Mixto!E15/1000000)*I$25 -> -1.920654 | J40: =(-CB_SMI_Mixto!F15/1000000)*J$25 -> -1.9270422 | K40: =(-CB_SMI_Mixto!G15/1000000)*K$25 -> -1.9335263 | L40: =(-CB_SMI_Mixto!H15/1000000)*L$25 -> -1.9400104 | M40: =(-CB_SMI_Mixto!I15/1000000)*M$25 -> -1.9465344 | N40: =(-CB_SMI_Mixto!J15/1000000)*N$25 -> -1.9530744 | ... U40: =(-CB_SMI_Mixto!Q15/1000000)*U$25 -> -1.9995889 | W40: =NPV($D$67,G40:U40)+F40 -> -17.142575 | X40: =PMT($D$67,15,-W40) -> -1.7650469 | Y40: =W40*1000000/7744865 -> -2.2134117 | Z40: =W40/$W$43 -> 0.29846931
C41: Operación MDMS | F41: 0 | G41: =(-CB_SMI_Mixto!C16/1000000)*G$25 -> -0.090864948 | H41: =(-CB_SMI_Mixto!D16/1000000)*H$25 -> -0.1817299 | I41: =(-CB_SMI_Mixto!E16/1000000)*I$25 -> -0.27259484 | J41: =(-CB_SMI_Mixto!F16/1000000)*J$25 -> -0.27350152 | K41: =(-CB_SMI_Mixto!G16/1000000)*K$25 -> -0.27442179 | L41: =(-CB_SMI_Mixto!H16/1000000)*L$25 -> -0.27534206 | M41: =(-CB_SMI_Mixto!I16/1000000)*M$25 -> -0.276268 | N41: =(-CB_SMI_Mixto!J16/1000000)*N$25 -> -0.27719621 | ... U41: =(-CB_SMI_Mixto!Q16/1000000)*U$25 -> -0.28379793 | W41: =NPV($D$67,G41:U41)+F41 -> -2.4330137 | X41: =PMT($D$67,15,-W41) -> -0.25050982 | Y41: =W41*1000000/7744865 -> -0.3141454 | Z41: =W41/$W$43 -> 0.042361193
C42: SyM Equipos | F42: 0 | G42: =(-CB_SMI_Mixto!C17/1000000)*G$25 -> -0.099576522 | H42: =(-CB_SMI_Mixto!D17/1000000)*H$25 -> -0.19915304 | I42: =(-CB_SMI_Mixto!E17/1000000)*I$25 -> -0.29872957 | J42: =(-CB_SMI_Mixto!F17/1000000)*J$25 -> -0.29972317 | K42: =(-CB_SMI_Mixto!G17/1000000)*K$25 -> -0.30073167 | L42: =(-CB_SMI_Mixto!H17/1000000)*L$25 -> -0.30174017 | M42: =(-CB_SMI_Mixto!I17/1000000)*M$25 -> -0.30275489 | N42: =(-CB_SMI_Mixto!J17/1000000)*N$25 -> -0.30377209 | ... U42: =(-CB_SMI_Mixto!Q17/1000000)*U$25 -> -0.31100674 | W42: =NPV($D$67,G42:U42)+F42 -> -2.6662762 | X42: =PMT($D$67,15,-W42) -> -0.27452717 | Y42: =W42*1000000/7744865 -> -0.34426374 | Z42: =W42/$W$43 -> 0.046422525
C43: COMA Total: | F43: =SUM(F38:F42) -> 0 | G43: =SUM(G38:G42) -> -2.1740191 | H43: =SUM(H38:H42) -> -4.3391619 | I43: =SUM(I38:I42) -> -6.4954161 | J43: =SUM(J38:J42) -> -6.5037047 | K43: =SUM(K38:K42) -> -6.5121175 | L43: =SUM(L38:L42) -> -6.5205304 | M43: =SUM(M38:M42) -> -6.5289951 | ... U43: =SUM(U38:U42) -> -6.5978313 | W43: =NPV($D$67,G43:U43)+F43 -> -57.434967 | X43: =PMT($D$67,15,-W43) -> -5.9136629 | Y43: =W43*1000000/7744865 -> -7.4158771 | Z43: =W43/$W$43 -> 1
B45: Costos Totales (VI + COMA) | F45: =F36+F43 -> -4.6985094 | G45: =G36+G43 -> -57.843125 | H45: =H36+H43 -> -60.008267 | I45: =I36+I43 -> -62.150152 | J45: =J36+J43 -> -7.0837969 | K45: =K36+K43 -> -7.0998036 | L45: =L36+L43 -> -7.1082165 | M45: =M36+M43 -> -7.1205545 | ... U45: =U36+U43 -> -7.2150043 | W45: =NPV($D$67,G45:U45)+F45 -> -215.11174 | X45: =PMT($D$67,15,-W45) -> -22.1485 | Y45: =W45*1000000/7744865 -> -27.774757
B47: Beneficios [MUSD] | C47: Ahorro de lectura pedestre | F47: 0 | G47: =(CB_SMI_Mixto!C18/1000000)*G$25 -> 0 | H47: =(CB_SMI_Mixto!D18/1000000)*H$25 -> 0 | I47: =(CB_SMI_Mixto!E18/1000000)*I$25 -> 0 | J47: =(CB_SMI_Mixto!F18/1000000)*J$25 -> 0 | K47: =(CB_SMI_Mixto!G18/1000000)*K$25 -> 0 | L47: =(CB_SMI_Mixto!H18/1000000)*L$25 -> 0 | M47: =(CB_SMI_Mixto!I18/1000000)*M$25 -> 0 | N47: =(CB_SMI_Mixto!J18/1000000)*N$25 -> 0 | ... U47: =(CB_SMI_Mixto!Q18/1000000)*U$25 -> 0 | W47: =NPV($D$67,G47:U47)+F47 -> 0 | X47: =PMT($D$67,15,-W47) -> 0 | Y47: =W47*1000000/7744865 -> 0 | Z47: =W47/$W$56 -> 0
C48: Corte y Reposición remoto | F48: 0 | G48: =(CB_SMI_Mixto!C19/1000000)*G$25 -> 0 | H48: =(CB_SMI_Mixto!D19/1000000)*H$25 -> 0 | I48: =(CB_SMI_Mixto!E19/1000000)*I$25 -> 0 | J48: =(CB_SMI_Mixto!F19/1000000)*J$25 -> 0 | K48: =(CB_SMI_Mixto!G19/1000000)*K$25 -> 0 | L48: =(CB_SMI_Mixto!H19/1000000)*L$25 -> 0 | M48: =(CB_SMI_Mixto!I19/1000000)*M$25 -> 0 | N48: =(CB_SMI_Mixto!J19/1000000)*N$25 -> 0 | ... U48: =(CB_SMI_Mixto!Q19/1000000)*U$25 -> 0 | W48: =NPV($D$67,G48:U48)+F48 -> 0 | X48: =PMT($D$67,15,-W48) -> 0 | Y48: =W48*1000000/7744865 -> 0 | Z48: =W48/$W$56 -> 0
C49: Reducción de Pérdidas No Técnicas (PNT) | F49: 0 | G49: =(CB_SMI_Mixto!C20/1000000)*G$25 -> 0 | H49: =(CB_SMI_Mixto!D20/1000000)*H$25 -> 0 | I49: =(CB_SMI_Mixto!E20/1000000)*I$25 -> 0 | J49: =(CB_SMI_Mixto!F20/1000000)*J$25 -> 0 | K49: =(CB_SMI_Mixto!G20/1000000)*K$25 -> 0 | L49: =(CB_SMI_Mixto!H20/1000000)*L$25 -> 0 | M49: =(CB_SMI_Mixto!I20/1000000)*M$25 -> 0 | N49: =(CB_SMI_Mixto!J20/1000000)*N$25 -> 0 | ... U49: =(CB_SMI_Mixto!Q20/1000000)*U$25 -> 0 | W49: =NPV($D$67,G49:U49)+F49 -> 0 | X49: =PMT($D$67,15,-W49) -> 0 | Y49: =W49*1000000/7744865 -> 0 | Z49: =W49/$W$56 -> 0
C50: Reducción del tiempo de respuesta ante Fallas | F50: 0 | G50: =(CB_SMI_Mixto!C21/1000000)*G$25 -> 0.71829259 | H50: =(CB_SMI_Mixto!D21/1000000)*H$25 -> 1.431839 | I50: =(CB_SMI_Mixto!E21/1000000)*I$25 -> 2.1406328 | J50: =(CB_SMI_Mixto!F21/1000000)*J$25 -> 2.1406328 | K50: =(CB_SMI_Mixto!G21/1000000)*K$25 -> 2.1406328 | L50: =(CB_SMI_Mixto!H21/1000000)*L$25 -> 2.1406328 | M50: =(CB_SMI_Mixto!I21/1000000)*M$25 -> 2.1406328 | N50: =(CB_SMI_Mixto!J21/1000000)*N$25 -> 2.1406328 | ... U50: =(CB_SMI_Mixto!Q21/1000000)*U$25 -> 2.1406328 | W50: =NPV($D$67,G50:U50)+F50 -> 18.817704 | X50: =PMT($D$67,15,-W50) -> 1.9375228 | Y50: =W50*1000000/7744865 -> 2.4297007 | Z50: =W50/$W$56 -> 0.12287878
C51: Gestión del consumo | F51: 0 | G51: =(CB_SMI_Mixto!C22/1000000)*G$25 -> 0 | H51: =(CB_SMI_Mixto!D22/1000000)*H$25 -> 0 | I51: =(CB_SMI_Mixto!E22/1000000)*I$25 -> 0 | J51: =(CB_SMI_Mixto!F22/1000000)*J$25 -> 0 | K51: =(CB_SMI_Mixto!G22/1000000)*K$25 -> 0 | L51: =(CB_SMI_Mixto!H22/1000000)*L$25 -> 0 | M51: =(CB_SMI_Mixto!I22/1000000)*M$25 -> 0 | N51: =(CB_SMI_Mixto!J22/1000000)*N$25 -> 0 | ... U51: =(CB_SMI_Mixto!Q22/1000000)*U$25 -> 0 | W51: =NPV($D$67,G51:U51)+F51 -> 0 | X51: =PMT($D$67,15,-W51) -> 0 | Y51: =W51*1000000/7744865 -> 0 | Z51: =W51/$W$56 -> 0
C52: Reducción del consumo de Clientes Finales | F52: 0 | G52: =(CB_SMI_Mixto!C23/1000000)*G$25 -> 0 | H52: =(CB_SMI_Mixto!D23/1000000)*H$25 -> 0 | I52: =(CB_SMI_Mixto!E23/1000000)*I$25 -> 0 | J52: =(CB_SMI_Mixto!F23/1000000)*J$25 -> 0 | K52: =(CB_SMI_Mixto!G23/1000000)*K$25 -> 0 | L52: =(CB_SMI_Mixto!H23/1000000)*L$25 -> 0 | M52: =(CB_SMI_Mixto!I23/1000000)*M$25 -> 0 | N52: =(CB_SMI_Mixto!J23/1000000)*N$25 -> 0 | ... U52: =(CB_SMI_Mixto!Q23/1000000)*U$25 -> 0 | W52: =NPV($D$67,G52:U52)+F52 -> 0 | X52: =PMT($D$67,15,-W52) -> 0 | Y52: =W52*1000000/7744865 -> 0 | Z52: =W52/$W$56 -> 0
C53: Reducción de emisiones de CO2 | F53: 0 | G53: =(CB_SMI_Mixto!C24/1000000)*G$25 -> 0 | H53: =(CB_SMI_Mixto!D24/1000000)*H$25 -> 0 | I53: =(CB_SMI_Mixto!E24/1000000)*I$25 -> 0 | J53: =(CB_SMI_Mixto!F24/1000000)*J$25 -> 0 | K53: =(CB_SMI_Mixto!G24/1000000)*K$25 -> 0 | L53: =(CB_SMI_Mixto!H24/1000000)*L$25 -> 0 | M53: =(CB_SMI_Mixto!I24/1000000)*M$25 -> 0 | N53: =(CB_SMI_Mixto!J24/1000000)*N$25 -> 0 | ... U53: =(CB_SMI_Mixto!Q24/1000000)*U$25 -> 0 | W53: =NPV($D$67,G53:U53)+F53 -> 0 | X53: =PMT($D$67,15,-W53) -> 0 | Y53: =W53*1000000/7744865 -> 0 | Z53: =W53/$W$56 -> 0
C54: Reducción servicio Atención al Cliente | F54: 0 | G54: =(CB_SMI_Mixto!C25/1000000)*G$25 -> 0 | H54: =(CB_SMI_Mixto!D25/1000000)*H$25 -> 0 | I54: =(CB_SMI_Mixto!E25/1000000)*I$25 -> 0 | J54: =(CB_SMI_Mixto!F25/1000000)*J$25 -> 0 | K54: =(CB_SMI_Mixto!G25/1000000)*K$25 -> 0 | L54: =(CB_SMI_Mixto!H25/1000000)*L$25 -> 0 | M54: =(CB_SMI_Mixto!I25/1000000)*M$25 -> 0 | N54: =(CB_SMI_Mixto!J25/1000000)*N$25 -> 0 | ... U54: =(CB_SMI_Mixto!Q25/1000000)*U$25 -> 0 | W54: =NPV($D$67,G54:U54)+F54 -> 0 | X54: =PMT($D$67,15,-W54) -> 0 | Y54: =W54*1000000/7744865 -> 0 | Z54: =W54/$W$56 -> 0
C55: Reducción en Inversión de infraestructura de red | F55: 0 | G55: =(CB_SMI_Mixto!C26/1000000)*G$25 -> 5.0164844 | H55: =(CB_SMI_Mixto!D26/1000000)*H$25 -> 10.007386 | I55: =(CB_SMI_Mixto!E26/1000000)*I$25 -> 15.126164 | J55: =(CB_SMI_Mixto!F26/1000000)*J$25 -> 15.161638 | K55: =(CB_SMI_Mixto!G26/1000000)*K$25 -> 15.184728 | L55: =(CB_SMI_Mixto!H26/1000000)*L$25 -> 15.201353 | M55: =(CB_SMI_Mixto!I26/1000000)*M$25 -> 15.217576 | N55: =(CB_SMI_Mixto!J26/1000000)*N$25 -> 15.343357 | ... U55: =(CB_SMI_Mixto!Q26/1000000)*U$25 -> 15.594942 | W55: =NPV($D$67,G55:U55)+F55 -> 134.32268 | X55: =PMT($D$67,15,-W55) -> 13.830234 | Y55: =W55*1000000/7744865 -> 17.34345 | Z55: =W55/$W$56 -> 0.87712122
C56: Beneficios Total: | F56: =SUM(F47:F55) -> 0 | G56: =SUM(G47:G55) -> 5.734777 | H56: =SUM(H47:H55) -> 11.439225 | I56: =SUM(I47:I55) -> 17.266796 | J56: =SUM(J47:J55) -> 17.302271 | K56: =SUM(K47:K55) -> 17.325361 | L56: =SUM(L47:L55) -> 17.341985 | M56: =SUM(M47:M55) -> 17.358209 | ... U56: =SUM(U47:U55) -> 17.735574 | W56: =NPV($D$67,G56:U56)+F56 -> 153.14038 | X56: =PMT($D$67,15,-W56) -> 15.767757 | Y56: =W56*1000000/7744865 -> 19.773151 | Z56: =W56/$W$56 -> 1
B58: Flujo | F58: =F45+F56 -> -4.6985094 | G58: =G45+G56 -> -52.108348 | H58: =H45+H56 -> -48.569042 | I58: =I45+I56 -> -44.883356 | J58: =J45+J56 -> 10.218474 | K58: =K45+K56 -> 10.225558 | L58: =L45+L56 -> 10.233769 | M58: =M45+M56 -> 10.237654 | ... U58: =U45+U56 -> 10.52057
B60: Flujo del periodo anterior | F60: 0 | G60: =F61 -> -4.6985094 | H60: =G61 -> -56.806857 | I60: =H61 -> -105.3759 | J60: =I61 -> -150.25925 | K60: =J61 -> -140.04078 | L60: =K61 -> -129.81522 | M60: =L61 -> -119.58145 | N60: =M61 -> -109.3438 | ... U60: =T61 -> -36.437362
B61: Flujo Acumulado | F61: =F58+F60 -> -4.6985094 | G61: =G58+G60 -> -56.806857 | H61: =H58+H60 -> -105.3759 | I61: =I58+I60 -> -150.25925 | J61: =J58+J60 -> -140.04078 | K61: =K58+K60 -> -129.81522 | L61: =L58+L60 -> -119.58145 | M61: =M58+M60 -> -109.3438 | ... U61: =U58+U60 -> -25.916792
B63: Flujo descontado (6%) | F63: =F58/(1+0.06)^F27 -> -4.6985094 | G63: =G58/(1+0.06)^G27 -> -49.158819 | H63: =H58/(1+0.06)^H27 -> -43.226274 | I63: =I58/(1+0.06)^I27 -> -37.684931 | J63: =J58/(1+0.06)^J27 -> 8.0939887 | K63: =K58/(1+0.06)^K27 -> 7.6411314 | L63: =L58/(1+0.06)^L27 -> 7.2144032 | M63: =M58/(1+0.06)^M27 -> 6.8086248 | ... U63: =U58/(1+0.06)^U27 -> 4.3898663
B64: Flujo Acumulado descontado (6%) | F64: =F63 -> -4.6985094 | G64: =F64+G63 -> -53.857328 | H64: =G64+H63 -> -97.083602 | I64: =H64+I63 -> -134.76853 | J64: =I64+J63 -> -126.67454 | K64: =J64+K63 -> -119.03341 | L64: =K64+L63 -> -111.81901 | M64: =L64+M63 -> -105.01039 | N64: =M64+N63 -> -98.514487 | ... U64: =T64+U63 -> -61.97136
B67: Tasa | D67: =J4 -> 0.06 | H67: Monto [MUSD] | J67: Monto [USD/cliente] | L67: Monto [$/cliente]
F68: VAN (Costos) | H68: =NPV(D67,G45:U45)+F45 -> -215.11174 | J68: =H68*1000000/$D$79 -> -27.788585 | L68: =J68*$S$4 -> -26659.257
B69: VAN | D69: =NPV(D67,G58:U58)+F58 -> -61.97136 | F69: Anualidad (Costos) | H69: =PMT(D67,15,-H68) -> -22.1485 | J69: =H69*1000000/$D$79 -> -2.8611895 | L69: =J69*$S$4 -> -2744.9108
B70: TIR | D70: =IRR(F58:U58) -> -0.024041099 | F70: Mensualidad (Costos) | H70: =H69/12 -> -1.8457083 | J70: =J69/12 -> -0.23843246 | L70: =L69/12 -> -228.74256
B71: B/C | D71: =NPV(D67,G56:U56)/-(F36+NPV(D67,G36:U36)+NPV(D67,G43:U43)) -> 0.71191085
F72: VAN (Beneficios) | H72: =NPV(D67,G56:U56)+F56 -> 153.14038 | J72: =H72*1000000/$D$79 -> 19.782995 | L72: =J72*$S$4 -> 18979.014
B73: # Clientes Alta | D73: 2527114 | F73: Anualidad (Beneficios) | H73: =PMT(D67,15,-H72) -> 15.767757 | J73: =H73*1000000/$D$79 -> 2.0369119 | L73: =J73*$S$4 -> 1954.1318
B74: # Clientes Media | D74: 2158536 | F74: Mensualidad (Beneficios) | H74: =H73/12 -> 1.3139798 | J74: =J73/12 -> 0.16974265 | L74: =L73/12 -> 162.84431
B75: # Clientes Baja | D75: 1173397
B76: # Clientes Muy Baja | D76: 1288141 | F76: VAN (Neto) | H76: =H72+H68 -> -61.97136 | J76: =H76*1000000/$D$79 -> -8.0055899 | L76: =J76*$S$4 -> -7680.2427
B77: # Clientes Ext. Baja | D77: 593823 | F77: Anualidad (Neto) | H77: =PMT(D67,15,-H76) -> -6.3807425 | J77: =H77*1000000/$D$79 -> -0.82427767 | L77: =J77*$S$4 -> -790.77902
F78: Mensualidad (Neto) | H78: =H77/12 -> -0.53172854 | J78: =J77/12 -> -0.068689805 | L78: =L77/12 -> -65.898252
B79: # Clientes Regulados | D79: =SUM(D73:D77) -> 7741011

Sheet CB_SMI_Mixto_ALTA
A1: Concepto | B1: Periodo 0 | C1: Periodo 1 | D1: Periodo 2 | E1: Periodo 3 | F1: Periodo 4 | G1: Periodo 5 | H1: Periodo 6 | I1: Periodo 7 | J1: Periodo 8 | K1: Periodo 9 | L1: Periodo 10 | M1: Periodo 11 | N1: Periodo 12 | O1: Periodo 13 | P1: Periodo 14 | Q1: Periodo 15
A2: Energía facturada anual [MWh/año] | B2: 11914419 | C2: 12274234 | D2: 12644916 | E2: 13026793 | F2: 13420202 | G2: 13825492 | H2: 14243022 | I2: 14673161 | J2: 15116290 | K2: 15572802 | L2: 16043101 | M2: 16527603 | N2: 17026736 | O2: 17540944 | P2: 18070680 | Q2: 18616415
A3: Cantidad UM 1F | B3: 1231 | C3: 1 | D3: 1 | E3: 2 | F3: 2 | G3: 2 | H3: 2 | I3: 2 | J3: 2 | K3: 2 | L3: 2 | M3: 2 | N3: 2 | O3: 2 | P3: 2 | Q3: 2
A4: Cantidad UM 3F Directa | B4: 0 | C4: 0 | D4: 0 | E4: 0 | F4: 0 | G4: 0 | H4: 0 | I4: 0 | J4: 0 | K4: 0 | L4: 0 | M4: 0 | N4: 0 | O4: 0 | P4: 0 | Q4: 0
A5: Cantidad UM 3F Indirecta | B5: 42167 | C5: 147 | D5: 147 | E5: 148 | F5: 148 | G5: 148 | H5: 148 | I5: 150 | J5: 150 | K5: 150 | L5: 150 | M5: 150 | N5: 152 | O5: 152 | P5: 153 | Q5: 156
A6: Cantidad DCU | B6: 0 | C6: 0 | D6: 0 | E6: 0 | F6: 0 | G6: 0 | H6: 0 | I6: 0 | J6: 0 | K6: 0 | L6: 0 | M6: 0 | N6: 0 | O6: 0 | P6: 0 | Q6: 0
A7: Inversión UM 1F [USD/equipo] | B7: 129.408 | C7: 129.408 | D7: 129.408 | E7: 129.408 | F7: 129.408 | G7: 129.408 | H7: 129.408 | I7: 129.408 | J7: 129.408 | K7: 129.408 | L7: 129.408 | M7: 129.408 | N7: 129.408 | O7: 129.408 | P7: 129.408 | Q7: 129.408
A8: Inversión UM 3F Directa [USD/equipo] | B8: 0 | C8: 0 | D8: 0 | E8: 0 | F8: 0 | G8: 0 | H8: 0 | I8: 0 | J8: 0 | K8: 0 | L8: 0 | M8: 0 | N8: 0 | O8: 0 | P8: 0 | Q8: 0
A9: Inversión UM 3F Indirecta [USD/equipo] | B9: 717.592 | C9: 717.592 | D9: 717.592 | E9: 717.592 | F9: 717.592 | G9: 717.592 | H9: 717.592 | I9: 717.592 | J9: 717.592 | K9: 717.592 | L9: 717.592 | M9: 717.592 | N9: 717.592 | O9: 717.592 | P9: 717.592 | Q9: 717.592
A10: Inversión DCU [USD/equipo] | B10: 0 | C10: 0 | D10: 0 | E10: 0 | F10: 0 | G10: 0 | H10: 0 | I10: 0 | J10: 0 | K10: 0 | L10: 0 | M10: 0 | N10: 0 | O10: 0 | P10: 0 | Q10: 0
A11: Inversión SGO [USD] | B11: 796396.7 | C11: 2715.948 | D11: 2715.948 | E11: 2752.65 | F11: 2752.65 | G11: 2752.65 | H11: 2752.65 | I11: 2789.352 | J11: 2789.352 | K11: 2789.352 | L11: 2789.352 | M11: 2789.352 | N11: 2826.054 | O11: 2826.054 | P11: 2844.405 | Q11: 2899.458
A12: Inversión MDMS [USD] | B12: 59843.558 | C12: 204.08421 | D12: 204.08421 | E12: 206.84211 | F12: 206.84211 | G12: 206.84211 | H12: 206.84211 | I12: 209.6 | J12: 209.6 | K12: 209.6 | L12: 209.6 | M12: 209.6 | N12: 212.35789 | O12: 212.35789 | P12: 213.73684 | Q12: 217.87368
A13: Operación Comunicaciones [USD/año] | B13: 0 | C13: 0 | D13: 0 | E13: 0 | F13: 0 | G13: 0 | H13: 0 | I13: 0 | J13: 0 | K13: 0 | L13: 0 | M13: 0 | N13: 0 | O13: 0 | P13: 0 | Q13: 0
... A26: Ahorro por inversión evitada [USD/año] | B26: 1403357.3 | C26: 1404390.9 | D26: 1405453.2 | E26: 1420942.7 | F26: 1424275.1 | G26: 1426444.2 | H26: 1428005.8 | I26: 1429529.9 | J26: 1441345.7 | K26: 1444399 | L26: 1446816.9 | M26: 1449240.7 | N26: 1452114.7 | O26: 1456390.3 | P26: 1460678.6 | Q26: 1464979.4

Sheet Flujo SMI_Mixto_ALTA
B2: Escenario de implementación | G2: Supuestos y Consideraciones
B4: Densidad de clientes | D4: Tecnología | G4: Tasa de descuento | J4: 0.06 | K4: % | R4: Dólar | S4: 959.36 | T4: USD/$ | U4: 45946
B5: Alta | D5: Mixto_ALTA | G5: Vida útil del proyecto | J5: 15 | K5: años | R5: UF | S5: 39521.26 | T5: UF/$ | U5: 45946
B6: Media | D6: Mixto_ALTA | G6: Meta de despligue | J6: 3 | K6: años
B7: Baja | D7: Mixto_ALTA | G7: Objetivo de despligue UM 1F | J7: =(SUMIF($F$12:$U$12,"<="&$J$6,$F$17:$U$17)) / ($J$6) -> 411.66667 | K7: UM/año | L7: ="Razonable para chile en torno a 1M y 1,5M por año." -> Razonable para chile en torno a 1M y 1,5M por año.
B8: Muy Baja | D8: Mixto_ALTA | G8: Objetivo de despligue UM 3F Directa | J8: =(SUMIF($F$12:$U$12,"<="&$J$6,$F$18:$U$18)) / ($J$6) -> 0 | K8: UM/año | L8: ="Razonable para chile en torno a 1M y 1,5M por año." -> Razonable para chile en torno a 1M y 1,5M por año.
B9: Extremadamente Baja | D9: Mixto_ALTA | G9: Objetivo de despligue UM 3F Indirecta | J9: =(SUMIF($F$12:$U$12,"<="&$J$6,$F$19:$U$19)) / ($J$6) -> 14203 | K9: UM/año | L9: ="Razonable para chile en torno a 1M y 1,5M por año." -> Razonable para chile en torno a 1M y 1,5M por año.
B12: Despligue SMI Chile | E12: Periodo | F12: 0 | G12: 1 | H12: 2 | I12: 3 | J12: 4 | K12: 5 | L12: 6 | M12: 7 | N12: 8 | O12: 9 | P12: 10 | Q12: 11 | R12: 12 | S12: 13 | T12: 14 | U12: 15
E13: Año | F13: 2025 | G13: 2026 | H13: 2027 | I13: 2028 | J13: 2029 | K13: 2030 | L13: 2031 | M13: 2032 | N13: 2033 | O13: 2034 | P13: 2035 | Q13: 2036 | R13: 2037 | S13: 2038 | T13: 2039 | U13: 2040
B15: Datos de despliegue | C15: Energía Facturada anual [GWh] | F15: =CB_SMI_Mixto_ALTA!B2/1000 -> 11914.419 | G15: =CB_SMI_Mixto_ALTA!C2/1000 -> 12274.234 | H15: =CB_SMI_Mixto_ALTA!D2/1000 -> 12644.916 | I15: =CB_SMI_Mixto_ALTA!E2/1000 -> 13026.793 | J15: =CB_SMI_Mixto_ALTA!F2/1000 -> 13420.202 | K15: =CB_SMI_Mixto_ALTA!G2/1000 -> 13825.492 | L15: =CB_SMI_Mixto_ALTA!H2/1000 -> 14243.022 | M15: =CB_SMI_Mixto_ALTA!I2/1000 -> 14673.161 | ... U15: =CB_SMI_Mixto_ALTA!Q2/1000 -> 18616.415
C17: UM 1F [N° Equipos] | F17: =CB_SMI_Mixto_ALTA!B3 -> 1231 | G17: =CB_SMI_Mixto_ALTA!C3 -> 1 | H17: =CB_SMI_Mixto_ALTA!D3 -> 1 | I17: =CB_SMI_Mixto_ALTA!E3 -> 2 | J17: =CB_SMI_Mixto_ALTA!F3 -> 2 | K17: =CB_SMI_Mixto_ALTA!G3 -> 2 | L17: =CB_SMI_Mixto_ALTA!H3 -> 2 | M17: =CB_SMI_Mixto_ALTA!I3 -> 2 | ... U17: =CB_SMI_Mixto_ALTA!Q3 -> 2
C18: UM 3F Directa [N° Equipos] | F18: =CB_SMI_Mixto_ALTA!B4 -> 0 | G18: =CB_SMI_Mixto_ALTA!C4 -> 0 | H18: =CB_SMI_Mixto_ALTA!D4 -> 0 | I18: =CB_SMI_Mixto_ALTA!E4 -> 0 | J18: =CB_SMI_Mixto_ALTA!F4 -> 0 | K18: =CB_SMI_Mixto_ALTA!G4 -> 0 | L18: =CB_SMI_Mixto_ALTA!H4 -> 0 | M18: =CB_SMI_Mixto_ALTA!I4 -> 0 | ... U18: =CB_SMI_Mixto_ALTA!Q4 -> 0
C19: UM 3F Indirecta [N° Equipos] | F19: =CB_SMI_Mixto_ALTA!B5 -> 42167 | G19: =CB_SMI_Mixto_ALTA!C5 -> 147 | H19: =CB_SMI_Mixto_ALTA!D5 -> 147 | I19: =CB_SMI_Mixto_ALTA!E5 -> 148 | J19: =CB_SMI_Mixto_ALTA!F5 -> 148 | K19: =CB_SMI_Mixto_ALTA!G5 -> 148 | L19: =CB_SMI_Mixto_ALTA!H5 -> 148 | M19: =CB_SMI_Mixto_ALTA!I5 -> 150 | ... U19: =CB_SMI_Mixto_ALTA!Q5 -> 156
B21: Despliegue | C21: UM 1F instalados | F21: 0 | G21: =IF(G$12<=$J$6,$J7,G17) -> 411.66667 | H21: =IF(H$12<=$J$6,$J7,H17) -> 411.66667 | I21: =IF(I$12<=$J$6,$J7,I17) -> 411.66667 | J21: =IF(J$12<=$J$6,$J7,J17) -> 2 | K21: =IF(K$12<=$J$6,$J7,K17) -> 2 | L21: =IF(L$12<=$J$6,$J7,L17) -> 2 | M21: =IF(M$12<=$J$6,$J7,M17) -> 2 | N21: =IF(N$12<=$J$6,$J7,N17) -> 2 | ... U21: =IF(U$12<=$J$6,$J7,U17) -> 2
C22: UM 3F Directa instalados | F22: 0 | G22: =IF(G$12<=$J$6,$J8,G18) -> 0 | H22: =IF(H$12<=$J$6,$J8,H18) -> 0 | I22: =IF(I$12<=$J$6,$J8,I18) -> 0 | J22: =IF(J$12<=$J$6,$J8,J18) -> 0 | K22: =IF(K$12<=$J$6,$J8,K18) -> 0 | L22: =IF(L$12<=$J$6,$J8,L18) -> 0 | M22: =IF(M$12<=$J$6,$J8,M18) -> 0 | N22: =IF(N$12<=$J$6,$J8,N18) -> 0 | ... U22: =IF(U$12<=$J$6,$J8,U18) -> 0
C23: UM 3F Indirecta instalados | F23: 0 | G23: =IF(G$12<=$J$6,$J9,G19) -> 14203 | H23: =IF(H$12<=$J$6,$J9,H19) -> 14203 | I23: =IF(I$12<=$J$6,$J9,I19) -> 14203 | J23: =IF(J$12<=$J$6,$J9,J19) -> 148 | K23: =IF(K$12<=$J$6,$J9,K19) -> 148 | L23: =IF(L$12<=$J$6,$J9,L19) -> 148 | M23: =IF(M$12<=$J$6,$J9,M19) -> 150 | N23: =IF(N$12<=$J$6,$J9,N19) -> 150 | ... U23: =IF(U$12<=$J$6,$J9,U19) -> 156
C24: UM faltantes por instalar | F24: =SUM(F17:F19) -> 43398 | G24: =SUM(F24,G17:G19)-SUM(G21:G23) -> 28931.333 | H24: =SUM(G24,H17:H19)-SUM(H21:H23) -> 14464.667 | I24: =SUM(H24,I17:I19)-SUM(I21:I23) -> 0 | J24: =SUM(I24,J17:J19)-SUM(J21:J23) -> 0 | K24: =SUM(J24,K17:K19)-SUM(K21:K23) -> 0 | L24: =SUM(K24,L17:L19)-SUM(L21:L23) -> 0 | M24: =SUM(L24,M17:M19)-SUM(M21:M23) -> 0 | N24: =SUM(M24,N17:N19)-SUM(N21:N23) -> 0 | ... U24: =SUM(T24,U17:U19)-SUM(U21:U23) -> 0
C25: % de avance | F25: 0 | G25: =IF(G$12<=$J$6,SUM($F$21:G23)/SUM($F$17:G19),1) -> 0.33561445 | H25: =IF(H$12<=$J$6,SUM($F$21:H23)/SUM($F$17:H19),1) -> 0.66895531 | I25: =IF(I$12<=$J$6,SUM($F$21:I23)/SUM($F$17:I19),1) -> 1 | J25: =IF(J$12<=$J$6,SUM($F$21:J23)/SUM($F$17:J19),1) -> 1 | K25: =IF(K$12<=$J$6,SUM($F$21:K23)/SUM($F$17:K19),1) -> 1 | L25: =IF(L$12<=$J$6,SUM($F$21:L23)/SUM($F$17:L19),1) -> 1 | M25: =IF(M$12<=$J$6,SUM($F$21:M23)/SUM($F$17:M19),1) -> 1 | N25: =IF(N$12<=$J$6,SUM($F$21:N23)/SUM($F$17:N19),1) -> 1 | ... U25: =IF(U$12<=$J$6,SUM($F$21:U23)/SUM($F$17:U19),1) -> 1
B27: Flujo de caja [MUSD] | E27: Periodo | F27: 0 | G27: 1 | H27: 2 | I27: 3 | J27: 4 | K27: 5 | L27: 6 | M27: 7 | N27: 8 | O27: 9 | P27: 10 | Q27: 11 | R27: 12 | S27: 13 | T27: 14 | U27: 15
E28: Año | F28: 2025 | G28: 2026 | H28: 2027 | I28: 2028 | J28: 2029 | K28: 2030 | L28: 2031 | M28: 2032 | N28: 2033 | O28: 2034 | P28: 2035 | Q28: 2036 | R28: 2037 | S28: 2038 | T28: 2039 | U28: 2040 | W28: VAN [MUSD] | X28: AVAN [MUSD] | Y28: VAN [USD/# Clientes] | Z28: Participación %
B30: VI [MUSD] | C30: UM 1F | F30: 0 | G30: =((-CB_SMI_Mixto_ALTA!C7)*G21)/1000000 -> -0.05327296 | H30: =((-CB_SMI_Mixto_ALTA!D7)*H21)/1000000 -> -0.05327296 | I30: =((-CB_SMI_Mixto_ALTA!E7)*I21)/1000000 -> -0.05327296 | J30: =((-CB_SMI_Mixto_ALTA!F7)*J21)/1000000 -> -0.000258816 | K30: =((-CB_SMI_Mixto_ALTA!G7)*K21)/1000000 -> -0.000258816 | L30: =((-CB_SMI_Mixto_ALTA!H7)*L21)/1000000 -> -0.000258816 | M30: =((-CB_SMI_Mixto_ALTA!I7)*M21)/1000000 -> -0.000258816 | N30: =((-CB_SMI_Mixto_ALTA!J7)*N21)/1000000 -> -0.000258816 | ... U30: =((-CB_SMI_Mixto_ALTA!Q7)*U21)/1000000 -> -0.000258816 | W30: =NPV($D$67,G30:U30)+F30 -> -0.14422113 | X30: =PMT($D$67,15,-W30) -> -0.014849406 | Y30: =W30*1000000/7744865 -> -0.018621516 | Z30: =W30/$W$36 -> 0.0049677851
C31: UM 3F Directa | F31: 0 | G31: =((-CB_SMI_Mixto_ALTA!C8)*G22)/1000000 -> 0 | H31: =((-CB_SMI_Mixto_ALTA!D8)*H22)/1000000 -> 0 | I31: =((-CB_SMI_Mixto_ALTA!E8)*I22)/1000000 -> 0 | J31: =((-CB_SMI_Mixto_ALTA!F8)*J22)/1000000 -> 0 | K31: =((-CB_SMI_Mixto_ALTA!G8)*K22)/1000000 -> 0 | L31: =((-CB_SMI_Mixto_ALTA!H8)*L22)/1000000 -> 0 | M31: =((-CB_SMI_Mixto_ALTA!I8)*M22)/1000000 -> 0 | N31: =((-CB_SMI_Mixto_ALTA!J8)*N22)/1000000 -> 0 | ... U31: =((-CB_SMI_Mixto_ALTA!Q8)*U22)/1000000 -> 0 | W31: =NPV($D$67,G31:U31)+F31 -> 0 | X31: =PMT($D$67,15,-W31) -> 0 | Y31: =W31*1000000/7744865 -> 0 | Z31: =W31/$W$36 -> 0
C32: UM 3F Indirecta | F32: 0 | G32: =((-CB_SMI_Mixto_ALTA!C9)*G23)/1000000 -> -10.191959 | H32: =((-CB_SMI_Mixto_ALTA!D9)*H23)/1000000 -> -10.191959 | I32: =((-CB_SMI_Mixto_ALTA!E9)*I23)/1000000 -> -10.191959 | J32: =((-CB_SMI_Mixto_ALTA!F9)*J23)/1000000 -> -0.10620362 | K32: =((-CB_SMI_Mixto_ALTA!G9)*K23)/1000000 -> -0.10620362 | L32: =((-CB_SMI_Mixto_ALTA!H9)*L23)/1000000 -> -0.10620362 | M32: =((-CB_SMI_Mixto_ALTA!I9)*M23)/1000000 -> -0.1076388 | N32: =((-CB_SMI_Mixto_ALTA!J9)*N23)/1000000 -> -0.1076388 | ... U32: =((-CB_SMI_Mixto_ALTA!Q9)*U23)/1000000 -> -0.11194435 | W32: =NPV($D$67,G32:U32)+F32 -> -28.001838 | X32: =PMT($D$67,15,-W32) -> -2.8831466 | Y32: =W32*1000000/7744865 -> -3.6155359 | Z32: =W32/$W$36 -> 0.96454047
C33: DCU | F33: =((-CB_SMI_Mixto_ALTA!B10)*CB_SMI_Mixto_ALTA!B6)/1000000 -> 0 | G33: =((-CB_SMI_Mixto_ALTA!C10)*CB_SMI_Mixto_ALTA!C6)/1000000 -> 0 | H33: =((-CB_SMI_Mixto_ALTA!D10)*CB_SMI_Mixto_ALTA!D6)/1000000 -> 0 | I33: =((-CB_SMI_Mixto_ALTA!E10)*CB_SMI_Mixto_ALTA!E6)/1000000 -> 0 | J33: =((-CB_SMI_Mixto_ALTA!F10)*CB_SMI_Mixto_ALTA!F6)/1000000 -> 0 | K33: =((-CB_SMI_Mixto_ALTA!G10)*CB_SMI_Mixto_ALTA!G6)/1000000 -> 0 | L33: =((-CB_SMI_Mixto_ALTA!H10)*CB_SMI_Mixto_ALTA!H6)/1000000 -> 0 | M33: =((-CB_SMI_Mixto_ALTA!I10)*CB_SMI_Mixto_ALTA!I6)/1000000 -> 0 | ... U33: =((-CB_SMI_Mixto_ALTA!Q10)*CB_SMI_Mixto_ALTA!Q6)/1000000 -> 0 | W33: =NPV($D$67,G33:U33)+F33 -> 0 | X33: =PMT($D$67,15,-W33) -> 0 | Y33: =W33*1000000/7744865 -> 0 | Z33: =W33/$W$36 -> 0
C34: HES | F34: =(-CB_SMI_Mixto_ALTA!B11)/1000000 -> -0.7963967 | G34: =(-CB_SMI_Mixto_ALTA!C11)/1000000 -> -0.002715948 | H34: =(-CB_SMI_Mixto_ALTA!D11)/1000000 -> -0.002715948 | I34: =(-CB_SMI_Mixto_ALTA!E11)/1000000 -> -0.00275265 | J34: =(-CB_SMI_Mixto_ALTA!F11)/1000000 -> -0.00275265 | K34: =(-CB_SMI_Mixto_ALTA!G11)/1000000 -> -0.00275265 | L34: =(-CB_SMI_Mixto_ALTA!H11)/1000000 -> -0.00275265 | M34: =(-CB_SMI_Mixto_ALTA!I11)/1000000 -> -0.002789352 | ... U34: =(-CB_SMI_Mixto_ALTA!Q11)/1000000 -> -0.002899458 | W34: =NPV($D$67,G34:U34)+F34 -> -0.82334555 | X34: =PMT($D$67,15,-W34) -> -0.084773934 | Y34: =W34*1000000/7744865 -> -0.10630857 | Z34: =W34/$W$36 -> 0.028360643
C35: MDMS | F35: =(-CB_SMI_Mixto_ALTA!B12)/1000000 -> -0.059843558 | G35: =(-CB_SMI_Mixto_ALTA!C12)/1000000 -> -0.00020408421 | H35: =(-CB_SMI_Mixto_ALTA!D12)/1000000 -> -0.00020408421 | I35: =(-CB_SMI_Mixto_ALTA!E12)/1000000 -> -0.00020684211 | J35: =(-CB_SMI_Mixto_ALTA!F12)/1000000 -> -0.00020684211 | K35: =(-CB_SMI_Mixto_ALTA!G12)/1000000 -> -0.00020684211 | L35: =(-CB_SMI_Mixto_ALTA!H12)/1000000 -> -0.00020684211 | M35: =(-CB_SMI_Mixto_ALTA!I12)/1000000 -> -0.0002096 | ... U35: =(-CB_SMI_Mixto_ALTA!Q12)/1000000 -> -0.00021787368 | W35: =NPV($D$67,G35:U35)+F35 -> -0.061868573 | X35: =PMT($D$67,15,-W35) -> -0.0063701593 | Y35: =W35*1000000/7744865 -> -0.0079883346 | Z35: =W35/$W$36 -> 0.002131101
C36: VI Total: | F36: =SUM(F30:F35) -> -0.85624026 | G36: =SUM(G30:G35) -> -10.248152 | H36: =SUM(H30:H35) -> -10.248152 | I36: =SUM(I30:I35) -> -10.248192 | J36: =SUM(J30:J35) -> -0.10942192 | K36: =SUM(K30:K35) -> -0.10942192 | L36: =SUM(L30:L35) -> -0.10942192 | M36: =SUM(M30:M35) -> -0.11089657 | ... U36: =SUM(U30:U35) -> -0.1153205 | W36: =NPV($D$67,G36:U36)+F36 -> -29.031273 | X36: =PMT($D$67,15,-W36) -> -2.9891401 | Y36: =W36*1000000/7744865 -> -3.7484543 | Z36: =W36/$W$36 -> 1
B38: COMA [MUSD] | C38: Operación Comunicaciones UM - SGO | F38: 0 | G38: =(-CB_SMI_Mixto_ALTA!C13/1000000)*G$25 -> 0 | H38: =(-CB_SMI_Mixto_ALTA!D13/1000000)*H$25 -> 0 | I38: =(-CB_SMI_Mixto_ALTA!E13/1000000)*I$25 -> 0 | J38: =(-CB_SMI_Mixto_ALTA!F13/1000000)*J$25 -> 0 | K38: =(-CB_SMI_Mixto_ALTA!G13/1000000)*K$25 -> 0 | L38: =(-CB_SMI_Mixto_ALTA!H13/1000000)*L$25 -> 0 | M38: =(-CB_SMI_Mixto_ALTA!I13/1000000)*M$25 -> 0 | N38: =(-CB_SMI_Mixto_ALTA!J13/1000000)*N$25 -> 0 | ... U38: =(-CB_SMI_Mixto_ALTA!Q13/1000000)*U$25 -> 0 | W38: =NPV($D$67,G38:U38)+F38 -> 0 | X38: =PMT($D$67,15,-W38) -> 0 | Y38: =W38*1000000/7744865 -> 0 | Z38: =W38/$W$43 -> 0
C39: Operación Comunicaciones DCU - SGO | F39: 0 | G39: =(-CB_SMI_Mixto_ALTA!C14/1000000)*G$25 -> -0.24485517 | H39: =(-CB_SMI_Mixto_ALTA!D14/1000000)*H$25 -> -0.48805159 | I39: =(-CB_SMI_Mixto_ALTA!E14/1000000)*I$25 -> -0.72957278 | J39: =(-CB_SMI_Mixto_ALTA!F14/1000000)*J$25 -> -0.72957278 | K39: =(-CB_SMI_Mixto_ALTA!G14/1000000)*K$25 -> -0.72957278 | L39: =(-CB_SMI_Mixto_ALTA!H14/1000000)*L$25 -> -0.72957278 | M39: =(-CB_SMI_Mixto_ALTA!I14/1000000)*M$25 -> -0.72957278 | N39: =(-CB_SMI_Mixto_ALTA!J14/1000000)*N$25 -> -0.72957278 | ... U39: =(-CB_SMI_Mixto_ALTA!Q14/1000000)*U$25 -> -0.72957278 | W39: =NPV($D$67,G39:U39)+F39 -> -6.4135587 | X39: =PMT($D$67,15,-W39) -> -0.66035773 | Y39: =W39*1000000/7744865 -> -0.82810465 | Z39: =W39/$W$43 -> 0.6126196
C40: Operación HES | F40: 0 | G40: =(-CB_SMI_Mixto_ALTA!C15/1000000)*G$25 -> -0.11670284 | H40: =(-CB_SMI_Mixto_ALTA!D15/1000000)*H$25 -> -0.23340568 | I40: =(-CB_SMI_Mixto_ALTA!E15/1000000)*I$25 -> -0.35010853 | J40: =(-CB_SMI_Mixto_ALTA!F15/1000000)*J$25 -> -0.35130632 | K40: =(-CB_SMI_Mixto_ALTA!G15/1000000)*K$25 -> -0.35250412 | L40: =(-CB_SMI_Mixto_ALTA!H15/1000000)*L$25 -> -0.35370192 | M40: =(-CB_SMI_Mixto_ALTA!I15/1000000)*M$25 -> -0.35491569 | N40: =(-CB_SMI_Mixto_ALTA!J15/1000000)*N$25 -> -0.35612946 | ... U40: =(-CB_SMI_Mixto_ALTA!Q15/1000000)*U$25 -> -0.36472965 | W40: =NPV($D$67,G40:U40)+F40 -> -3.1257244 | X40: =PMT($D$67,15,-W40) -> -0.32183322 | Y40: =W40*1000000/7744865 -> -0.40358669 | Z40: =W40/$W$43 -> 0.29856748
C41: Operación MDMS | F41: 0 | G41: =(-CB_SMI_Mixto_ALTA!C16/1000000)*G$25 -> -0.016563417 | H41: =(-CB_SMI_Mixto_ALTA!D16/1000000)*H$25 -> -0.033126834 | I41: =(-CB_SMI_Mixto_ALTA!E16/1000000)*I$25 -> -0.049690251 | J41: =(-CB_SMI_Mixto_ALTA!F16/1000000)*J$25 -> -0.049860253 | K41: =(-CB_SMI_Mixto_ALTA!G16/1000000)*K$25 -> -0.050030254 | L41: =(-CB_SMI_Mixto_ALTA!H16/1000000)*L$25 -> -0.050200255 | M41: =(-CB_SMI_Mixto_ALTA!I16/1000000)*M$25 -> -0.050372523 | N41: =(-CB_SMI_Mixto_ALTA!J16/1000000)*N$25 -> -0.050544791 | ... U41: =(-CB_SMI_Mixto_ALTA!Q16/1000000)*U$25 -> -0.051765401 | W41: =NPV($D$67,G41:U41)+F41 -> -0.44362825 | X41: =PMT($D$67,15,-W41) -> -0.04567719 | Y41: =W41*1000000/7744865 -> -0.057280307 | Z41: =W41/$W$43 -> 0.042375126
C42: SyM Equipos | F42: 0 | G42: =(-CB_SMI_Mixto_ALTA!C17/1000000)*G$25 -> -0.018151416 | H42: =(-CB_SMI_Mixto_ALTA!D17/1000000)*H$25 -> -0.036302832 | I42: =(-CB_SMI_Mixto_ALTA!E17/1000000)*I$25 -> -0.054454248 | J42: =(-CB_SMI_Mixto_ALTA!F17/1000000)*J$25 -> -0.054640548 | K42: =(-CB_SMI_Mixto_ALTA!G17/1000000)*K$25 -> -0.054826848 | L42: =(-CB_SMI_Mixto_ALTA!H17/1000000)*L$25 -> -0.055013148 | M42: =(-CB_SMI_Mixto_ALTA!I17/1000000)*M$25 -> -0.055201932 | N42: =(-CB_SMI_Mixto_ALTA!J17/1000000)*N$25 -> -0.055390716 | ... U42: =(-CB_SMI_Mixto_ALTA!Q17/1000000)*U$25 -> -0.05672835 | W42: =NPV($D$67,G42:U42)+F42 -> -0.4861606 | X42: =PMT($D$67,15,-W42) -> -0.050056439 | Y42: =W42*1000000/7744865 -> -0.062771992 | Z42: =W42/$W$43 -> 0.046437793
C43: COMA Total: | F43: =SUM(F38:F42) -> 0 | G43: =SUM(G38:G42) -> -0.39627284 | H43: =SUM(H38:H42) -> -0.79088694 | I43: =SUM(I38:I42) -> -1.1838258 | J43: =SUM(J38:J42) -> -1.1853799 | K43: =SUM(K38:K42) -> -1.186934 | L43: =SUM(L38:L42) -> -1.1884881 | M43: =SUM(M38:M42) -> -1.1900629 | ... U43: =SUM(U38:U42) -> -1.2027962 | W43: =NPV($D$67,G43:U43)+F43 -> -10.469072 | X43: =PMT($D$67,15,-W43) -> -1.0779246 | Y43: =W43*1000000/7744865 -> -1.3517436 | Z43: =W43/$W$43 -> 1
B45: Costos Totales (VI + COMA) | F45: =F36+F43 -> -0.85624026 | G45: =G36+G43 -> -10.644425 | H45: =H36+H43 -> -11.039039 | I45: =I36+I43 -> -11.432017 | J45: =J36+J43 -> -1.2948018 | K45: =K36+K43 -> -1.2963559 | L45: =L36+L43 -> -1.29791 | M45: =M36+M43 -> -1.3009595 | ... U45: =U36+U43 -> -1.3181167 | W45: =NPV($D$67,G45:U45)+F45 -> -39.500345 | X45: =PMT($D$67,15,-W45) -> -4.0670647 | Y45: =W45*1000000/7744865 -> -5.100198
B47: Beneficios [MUSD] | C47: Ahorro de lectura pedestre | F47: 0 | G47: =(CB_SMI_Mixto_ALTA!C18/1000000)*G$25 -> 0 | H47: =(CB_SMI_Mixto_ALTA!D18/1000000)*H$25 -> 0 | I47: =(CB_SMI_Mixto_ALTA!E18/1000000)*I$25 -> 0 | J47: =(CB_SMI_Mixto_ALTA!F18/1000000)*J$25 -> 0 | K47: =(CB_SMI_Mixto_ALTA!G18/1000000)*K$25 -> 0 | L47: =(CB_SMI_Mixto_ALTA!H18/1000000)*L$25 -> 0 | M47: =(CB_SMI_Mixto_ALTA!I18/1000000)*M$25 -> 0 | N47: =(CB_SMI_Mixto_ALTA!J18/1000000)*N$25 -> 0 | ... U47: =(CB_SMI_Mixto_ALTA!Q18/1000000)*U$25 -> 0 | V47: =U47/$U$56 -> 0 | W47: =NPV($D$67,G47:U47)+F47 -> 0 | X47: =PMT($D$67,15,-W47) -> 0 | Y47: =W47*1000000/7744865 -> 0 | Z47: =W47/$W$56 -> 0
C48: Corte y Reposición remoto | F48: 0 | G48: =(CB_SMI_Mixto_ALTA!C19/1000000)*G$25 -> 0 | H48: =(CB_SMI_Mixto_ALTA!D19/1000000)*H$25 -> 0 | I48: =(CB_SMI_Mixto_ALTA!E19/1000000)*I$25 -> 0 | J48: =(CB_SMI_Mixto_ALTA!F19/1000000)*J$25 -> 0 | K48: =(CB_SMI_Mixto_ALTA!G19/1000000)*K$25 -> 0 | L48: =(CB_SMI_Mixto_ALTA!H19/1000000)*L$25 -> 0 | M48: =(CB_SMI_Mixto_ALTA!I19/1000000)*M$25 -> 0 | N48: =(CB_SMI_Mixto_ALTA!J19/1000000)*N$25 -> 0 | ... U48: =(CB_SMI_Mixto_ALTA!Q19/1000000)*U$25 -> 0 | V48: =U48/$U$56 -> 0 | W48: =NPV($D$67,G48:U48)+F48 -> 0 | X48: =PMT($D$67,15,-W48) -> 0 | Y48: =W48*1000000/7744865 -> 0 | Z48: =W48/$W$56 -> 0
C49: Reducción de Pérdidas No Técnicas | F49: 0 | G49: =(CB_SMI_Mixto_ALTA!C20/1000000)*G$25 -> 0 | H49: =(CB_SMI_Mixto_ALTA!D20/1000000)*H$25 -> 0 | I49: =(CB_SMI_Mixto_ALTA!E20/1000000)*I$25 -> 0 | J49: =(CB_SMI_Mixto_ALTA!F20/1000000)*J$25 -> 0 | K49: =(CB_SMI_Mixto_ALTA!G20/1000000)*K$25 -> 0 | L49: =(CB_SMI_Mixto_ALTA!H20/1000000)*L$25 -> 0 | M49: =(CB_SMI_Mixto_ALTA!I20/1000000)*M$25 -> 0 | N49: =(CB_SMI_Mixto_ALTA!J20/1000000)*N$25 -> 0 | ... U49: =(CB_SMI_Mixto_ALTA!Q20/1000000)*U$25 -> 0 | V49: =U49/$U$56 -> 0 | W49: =NPV($D$67,G49:U49)+F49 -> 0 | X49: =PMT($D$67,15,-W49) -> 0 | Y49: =W49*1000000/7744865 -> 0 | Z49: =W49/$W$56 -> 0
C50: Reducción del tiempo de respuesta ante Fallas | F50: 0 | G50: =(CB_SMI_Mixto_ALTA!C21/1000000)*G$25 -> 0.045996825 | H50: =(CB_SMI_Mixto_ALTA!D21/1000000)*H$25 -> 0.09168205 | I50: =(CB_SMI_Mixto_ALTA!E21/1000000)*I$25 -> 0.13705258 | J50: =(CB_SMI_Mixto_ALTA!F21/1000000)*J$25 -> 0.13705258 | K50: =(CB_SMI_Mixto_ALTA!G21/1000000)*K$25 -> 0.13705258 | L50: =(CB_SMI_Mixto_ALTA!H21/1000000)*L$25 -> 0.13705258 | M50: =(CB_SMI_Mixto_ALTA!I21/1000000)*M$25 -> 0.13705258 | N50: =(CB_SMI_Mixto_ALTA!J21/1000000)*N$25 -> 0.13705258 | ... U50: =(CB_SMI_Mixto_ALTA!Q21/1000000)*U$25 -> 0.13705258 | V50: =U50/$U$56 -> 0.085549216 | W50: =NPV($D$67,G50:U50)+F50 -> 1.2048075 | X50: =PMT($D$67,15,-W50) -> 0.12405031 | Y50: =W50*1000000/7744865 -> 0.1555621 | Z50: =W50/$W$56 -> 0.087158561
C51: Reducción del costo de la energía en horas de Sol | F51: 0 | G51: =(CB_SMI_Mixto_ALTA!C22/1000000)*G$25 -> 0 | H51: =(CB_SMI_Mixto_ALTA!D22/1000000)*H$25 -> 0 | I51: =(CB_SMI_Mixto_ALTA!E22/1000000)*I$25 -> 0 | J51: =(CB_SMI_Mixto_ALTA!F22/1000000)*J$25 -> 0 | K51: =(CB_SMI_Mixto_ALTA!G22/1000000)*K$25 -> 0 | L51: =(CB_SMI_Mixto_ALTA!H22/1000000)*L$25 -> 0 | M51: =(CB_SMI_Mixto_ALTA!I22/1000000)*M$25 -> 0 | N51: =(CB_SMI_Mixto_ALTA!J22/1000000)*N$25 -> 0 | ... U51: =(CB_SMI_Mixto_ALTA!Q22/1000000)*U$25 -> 0 | V51: =U51/$U$56 -> 0 | W51: =NPV($D$67,G51:U51)+F51 -> 0 | X51: =PMT($D$67,15,-W51) -> 0 | Y51: =W51*1000000/7744865 -> 0 | Z51: =W51/$W$56 -> 0
C52: Reducción del consumo de Clientes Finales | F52: 0 | G52: =(CB_SMI_Mixto_ALTA!C23/1000000)*G$25 -> 0 | H52: =(CB_SMI_Mixto_ALTA!D23/1000000)*H$25 -> 0 | I52: =(CB_SMI_Mixto_ALTA!E23/1000000)*I$25 -> 0 | J52: =(CB_SMI_Mixto_ALTA!F23/1000000)*J$25 -> 0 | K52: =(CB_SMI_Mixto_ALTA!G23/1000000)*K$25 -> 0 | L52: =(CB_SMI_Mixto_ALTA!H23/1000000)*L$25 -> 0 | M52: =(CB_SMI_Mixto_ALTA!I23/1000000)*M$25 -> 0 | N52: =(CB_SMI_Mixto_ALTA!J23/1000000)*N$25 -> 0 | ... U52: =(CB_SMI_Mixto_ALTA!Q23/1000000)*U$25 -> 0 | V52: =U52/$U$56 -> 0 | W52: =NPV($D$67,G52:U52)+F52 -> 0 | X52: =PMT($D$67,15,-W52) -> 0 | Y52: =W52*1000000/7744865 -> 0 | Z52: =W52/$W$56 -> 0
C53: Reducción de emisiones de CO2 | F53: 0 | G53: =(CB_SMI_Mixto_ALTA!C24/1000000)*G$25 -> 0 | H53: =(CB_SMI_Mixto_ALTA!D24/1000000)*H$25 -> 0 | I53: =(CB_SMI_Mixto_ALTA!E24/1000000)*I$25 -> 0 | J53: =(CB_SMI_Mixto_ALTA!F24/1000000)*J$25 -> 0 | K53: =(CB_SMI_Mixto_ALTA!G24/1000000)*K$25 -> 0 | L53: =(CB_SMI_Mixto_ALTA!H24/1000000)*L$25 -> 0 | M53: =(CB_SMI_Mixto_ALTA!I24/1000000)*M$25 -> 0 | N53: =(CB_SMI_Mixto_ALTA!J24/1000000)*N$25 -> 0 | ... U53: =(CB_SMI_Mixto_ALTA!Q24/1000000)*U$25 -> 0 | V53: =U53/$U$56 -> 0 | W53: =NPV($D$67,G53:U53)+F53 -> 0 | X53: =PMT($D$67,15,-W53) -> 0 | Y53: =W53*1000000/7744865 -> 0 | Z53: =W53/$W$56 -> 0
C54: Reducción servicio Atención al Cliente | F54: 0 | G54: =(CB_SMI_Mixto_ALTA!C25/1000000)*G$25 -> 0 | H54: =(CB_SMI_Mixto_ALTA!D25/1000000)*H$25 -> 0 | I54: =(CB_SMI_Mixto_ALTA!E25/1000000)*I$25 -> 0 | J54: =(CB_SMI_Mixto_ALTA!F25/1000000)*J$25 -> 0 | K54: =(CB_SMI_Mixto_ALTA!G25/1000000)*K$25 -> 0 | L54: =(CB_SMI_Mixto_ALTA!H25/1000000)*L$25 -> 0 | M54: =(CB_SMI_Mixto_ALTA!I25/1000000)*M$25 -> 0 | N54: =(CB_SMI_Mixto_ALTA!J25/1000000)*N$25 -> 0 | ... U54: =(CB_SMI_Mixto_ALTA!Q25/1000000)*U$25 -> 0 | V54: =U54/$U$56 -> 0 | W54: =NPV($D$67,G54:U54)+F54 -> 0 | X54: =PMT($D$67,15,-W54) -> 0 | Y54: =W54*1000000/7744865 -> 0 | Z54: =W54/$W$56 -> 0
C55: Reducción en Inversión de infraestructura de red | F55: 0 | G55: =(CB_SMI_Mixto_ALTA!C26/1000000)*G$25 -> 0.47133387 | H55: =(CB_SMI_Mixto_ALTA!D26/1000000)*H$25 -> 0.94018541 | I55: =(CB_SMI_Mixto_ALTA!E26/1000000)*I$25 -> 1.4209427 | J55: =(CB_SMI_Mixto_ALTA!F26/1000000)*J$25 -> 1.4242751 | K55: =(CB_SMI_Mixto_ALTA!G26/1000000)*K$25 -> 1.4264442 | L55: =(CB_SMI_Mixto_ALTA!H26/1000000)*L$25 -> 1.4280058 | M55: =(CB_SMI_Mixto_ALTA!I26/1000000)*M$25 -> 1.4295299 | N55: =(CB_SMI_Mixto_ALTA!J26/1000000)*N$25 -> 1.4413457 | ... U55: =(CB_SMI_Mixto_ALTA!Q26/1000000)*U$25 -> 1.4649794 | V55: =U55/$U$56 -> 0.91445078 | W55: =NPV($D$67,G55:U55)+F55 -> 12.618361 | X55: =PMT($D$67,15,-W55) -> 1.2992214 | Y55: =W55*1000000/7744865 -> 1.6292552 | Z55: =W55/$W$56 -> 0.91284144
C56: Beneficios Total: | F56: =SUM(F47:F55) -> 0 | G56: =SUM(G47:G55) -> 0.51733069 | H56: =SUM(H47:H55) -> 1.0318675 | I56: =SUM(I47:I55) -> 1.5579952 | J56: =SUM(J47:J55) -> 1.5613277 | K56: =SUM(K47:K55) -> 1.5634968 | L56: =SUM(L47:L55) -> 1.5650584 | M56: =SUM(M47:M55) -> 1.5665824 | ... U56: =SUM(U47:U55) -> 1.6020319 | W56: =NPV($D$67,G56:U56)+F56 -> 13.823169 | X56: =PMT($D$67,15,-W56) -> 1.4232717 | Y56: =W56*1000000/7744865 -> 1.7848173 | Z56: =W56/$W$56 -> 1
B58: Flujo | F58: =F45+F56 -> -0.85624026 | G58: =G45+G56 -> -10.127094 | H58: =H45+H56 -> -10.007172 | I58: =I45+I56 -> -9.8740222 | J58: =J45+J56 -> 0.26652587 | K58: =K45+K56 -> 0.26714083 | L58: =L45+L56 -> 0.26714839 | M58: =M45+M56 -> 0.26562295 | ... U58: =U45+U56 -> 0.28391526
B60: Flujo del periodo anterior | F60: 0 | G60: =F61 -> -0.85624026 | H60: =G61 -> -10.983335 | I60: =H61 -> -20.990506 | J60: =I61 -> -30.864528 | K60: =J61 -> -30.598003 | L60: =K61 -> -30.330862 | M60: =L61 -> -30.063713 | N60: =M61 -> -29.79809 | ... U60: =T61 -> -27.843844
B61: Flujo Acumulado | F61: =F58+F60 -> -0.85624026 | G61: =G58+G60 -> -10.983335 | H61: =H58+H60 -> -20.990506 | I61: =I58+I60 -> -30.864528 | J61: =J58+J60 -> -30.598003 | K61: =K58+K60 -> -30.330862 | L61: =L58+L60 -> -30.063713 | M61: =M58+M60 -> -29.79809 | ... U61: =U58+U60 -> -27.559929
B63: Flujo descontado (6%) | F63: =F58/(1+0.06)^F27 -> -0.85624026 | G63: =G58/(1+0.06)^G27 -> -9.5538626 | H63: =H58/(1+0.06)^H27 -> -8.9063471 | I63: =I58/(1+0.06)^I27 -> -8.2904194 | J63: =J58/(1+0.06)^J27 -> 0.21111345 | K63: =K58/(1+0.06)^K27 -> 0.19962317 | L63: =L58/(1+0.06)^L27 -> 0.18832907 | M63: =M58/(1+0.06)^M27 -> 0.17665443 | ... U63: =U58/(1+0.06)^U27 -> 0.11846792
B64: Flujo Acumulado descontado (6%) | F64: =F63 -> -0.85624026 | G64: =F64+G63 -> -10.410103 | H64: =G64+H63 -> -19.31645 | I64: =H64+I63 -> -27.606869 | J64: =I64+J63 -> -27.395756 | K64: =J64+K63 -> -27.196133 | L64: =K64+L63 -> -27.007804 | M64: =L64+M63 -> -26.831149 | N64: =M64+N63 -> -26.658069 | ... U64: =T64+U63 -> -25.677176
B67: Tasa | D67: =J4 -> 0.06 | H67: Monto [MUSD] | J67: Monto [USD/cliente] | L67: Monto [$/cliente]
F68: VAN (Costos) | H68: =NPV(D67,G45:U45)+F45 -> -39.500345 | J68: =H68*1000000/$D$73 -> -15.630615 | L68: =J68*$S$4 -> -14995.386
B69: VAN | D69: =NPV(D67,G58:U58)+F58 -> -25.677176 | F69: Anualidad (Costos) | H69: =PMT(D67,15,-H68) -> -4.0670647 | J69: =H69*1000000/$D$73 -> -1.6093713 | L69: =J69*$S$4 -> -1543.9664
B70: TIR | D70: =IRR(F58:U58) -> #NUM! | F70: Mensualidad (Costos) | H70: =H69/12 -> -0.33892206 | J70: =J69/12 -> -0.13411427 | L70: =L69/12 -> -128.66387
B71: B/C | D71: =NPV(D67,G56:U56)/-(F36+NPV(D67,G36:U36)+NPV(D67,G43:U43)) -> 0.34995058
F72: VAN (Beneficios) | H72: =NPV(D67,G56:U56)+F56 -> 13.823169 | J72: =H72*1000000/$D$73 -> 5.4699427 | L72: =J72*$S$4 -> 5247.6442
B73: # Clientes Alta | D73: 2527114 | F73: Anualidad (Beneficios) | H73: =PMT(D67,15,-H72) -> 1.4232717 | J73: =H73*1000000/$D$73 -> 0.56320042 | L73: =J73*$S$4 -> 540.31195
B74: # Clientes Media | D74: 2158536 | F74: Mensualidad (Beneficios) | H74: =H73/12 -> 0.11860597 | J74: =J73/12 -> 0.046933368 | L74: =L73/12 -> 45.025996
B75: # Clientes Baja | D75: 1173397
B76: # Clientes Muy Baja | D76: 1288141 | F76: VAN (Neto) | H76: =H72+H68 -> -25.677176 | J76: =H76*1000000/$D$73 -> -10.160672 | L76: =J76*$S$4 -> -9747.7421
B77: # Clientes Ext. Baja | D77: 593823 | F77: Anualidad (Neto) | H77: =PMT(D67,15,-H76) -> -2.643793 | J77: =H77*1000000/$D$73 -> -1.0461709 | L77: =J77*$S$4 -> -1003.6545
F78: Mensualidad (Neto) | H78: =H77/12 -> -0.22031608 | J78: =J77/12 -> -0.087180905 | L78: =L77/12 -> -83.637873
B79: # Clientes Regulados | D79: =SUM(D73:D77) -> 7741011

Sheet CB_SMI_Mixto_MEDIA
A1: Concepto | B1: Periodo 0 | C1: Periodo 1 | D1: Periodo 2 | E1: Periodo 3 | F1: Periodo 4 | G1: Periodo 5 | H1: Periodo 6 | I1: Periodo 7 | J1: Periodo 8 | K1: Periodo 9 | L1: Periodo 10 | M1: Periodo 11 | N1: Periodo 12 | O1: Periodo 13 | P1: Periodo 14 | Q1: Periodo 15
A2: Energía facturada anual [MWh/año] | B2: 8711682.8 | C2: 8974775.6 | D2: 9245813.9 | E2: 9525037.4 | F2: 9812693.6 | G2: 10109037 | H2: 10414330 | I2: 10728843 | J2: 11052854 | K2: 11386650 | L2: 11730527 | M2: 12084789 | N2: 12449749 | O2: 12825732 | P2: 13213069 | Q2: 13612103
A3: Cantidad UM 1F | B3: 2896 | C3: 11 | D3: 11 | E3: 11 | F3: 11 | G3: 13 | H3: 13 | I3: 13 | J3: 13 | K3: 13 | L3: 13 | M3: 13 | N3: 13 | O3: 13 | P3: 13 | Q3: 13
A4: Cantidad UM 3F Directa | B4: 0 | C4: 0 | D4: 0 | E4: 0 | F4: 0 | G4: 0 | H4: 0 | I4: 0 | J4: 0 | K4: 0 | L4: 0 | M4: 0 | N4: 0 | O4: 0 | P4: 0 | Q4: 0
A5: Cantidad UM 3F Indirecta | B5: 46463 | C5: 232 | D5: 232 | E5: 235 | F5: 235 | G5: 237 | H5: 237 | I5: 237 | J5: 239 | K5: 239 | L5: 239 | M5: 241 | N5: 241 | O5: 244 | P5: 247 | Q5: 250
A6: Cantidad DCU | B6: 0 | C6: 0 | D6: 0 | E6: 0 | F6: 0 | G6: 0 | H6: 0 | I6: 0 | J6: 0 | K6: 0 | L6: 0 | M6: 0 | N6: 0 | O6: 0 | P6: 0 | Q6: 0
A7: Inversión UM 1F [USD/equipo] | B7: 138.76 | C7: 138.76 | D7: 138.76 | E7: 138.76 | F7: 138.76 | G7: 138.76 | H7: 138.76 | I7: 138.76 | J7: 138.76 | K7: 138.76 | L7: 138.76 | M7: 138.76 | N7: 138.76 | O7: 138.76 | P7: 138.76 | Q7: 138.76
A8: Inversión UM 3F Directa [USD/equipo] | B8: 0 | C8: 0 | D8: 0 | E8: 0 | F8: 0 | G8: 0 | H8: 0 | I8: 0 | J8: 0 | K8: 0 | L8: 0 | M8: 0 | N8: 0 | O8: 0 | P8: 0 | Q8: 0
A9: Inversión UM 3F Indirecta [USD/equipo] | B9: 717.592 | C9: 717.592 | D9: 717.592 | E9: 717.592 | F9: 717.592 | G9: 717.592 | H9: 717.592 | I9: 717.592 | J9: 717.592 | K9: 717.592 | L9: 717.592 | M9: 717.592 | N9: 717.592 | O9: 717.592 | P9: 717.592 | Q9: 717.592
A10: Inversión DCU [USD/equipo] | B10: 0 | C10: 0 | D10: 0 | E10: 0 | F10: 0 | G10: 0 | H10: 0 | I10: 0 | J10: 0 | K10: 0 | L10: 0 | M10: 0 | N10: 0 | O10: 0 | P10: 0 | Q10: 0
A11: Inversión SGO [USD] | B11: 905787.01 | C11: 4459.293 | D11: 4459.293 | E11: 4514.346 | F11: 4514.346 | G11: 4587.75 | H11: 4587.75 | I11: 4587.75 | J11: 4624.452 | K11: 4624.452 | L11: 4624.452 | M11: 4661.154 | N11: 4661.154 | O11: 4716.207 | P11: 4771.26 | Q11: 4826.313
A12: Inversión MDMS [USD] | B12: 68063.463 | C12: 335.08421 | D12: 335.08421 | E12: 339.22105 | F12: 339.22105 | G12: 344.73684 | H12: 344.73684 | I12: 344.73684 | J12: 347.49474 | K12: 347.49474 | L12: 347.49474 | M12: 350.25263 | N12: 350.25263 | O12: 354.38947 | P12: 358.52632 | Q12: 362.66316
A13: Operación Comunicaciones [USD/año] | B13: 0 | C13: 0 | D13: 0 | E13: 0 | F13: 0 | G13: 0 | H13: 0 | I13: 0 | J13: 0 | K13: 0 | L13: 0 | M13: 0 | N13: 0 | O13: 0 | P13: 0 | Q13: 0
... A26: Ahorro por inversión evitada [USD/año] | B26: 1901322.8 | C26: 1902723.1 | D26: 1904162.4 | E26: 1925148.1 | F26: 1929663.1 | G26: 1932601.8 | H26: 1934717.6 | I26: 1936782.4 | J26: 1952790.9 | K26: 1956927.7 | L26: 1960203.6 | M26: 1963487.4 | N26: 1967381.3 | O26: 1973174 | P26: 1978983.8 | Q26: 1984810.8

Sheet Flujo SMI_Mixto_MEDIA
B2: Escenario de implementación | G2: Supuestos y Consideraciones
B4: Densidad de clientes | D4: Tecnología | G4: Tasa de descuento | J4: 0.06 | K4: % | R4: Dólar | S4: 959.36 | T4: USD/$ | U4: 45946
B5: Alta | D5: Mixto_MEDIA | G5: Vida útil del proyecto | J5: 15 | K5: años | R5: UF | S5: 39521.26 | T5: UF/$ | U5: 45946
B6: Media | D6: Mixto_MEDIA | G6: Meta de despligue | J6: 3 | K6: años
B7: Baja | D7: Mixto_MEDIA | G7: Objetivo de despligue UM 1F | J7: =(SUMIF($F$12:$U$12,"<="&$J$6,$F$17:$U$17)) / ($J$6) -> 976.33333 | K7: UM/año | L7: ="Razonable para chile en torno a 1M y 1,5M por año." -> Razonable para chile en torno a 1M y 1,5M por año.
B8: Muy Baja | D8: Mixto_MEDIA | G8: Objetivo de despligue UM 3F Directa | J8: =(SUMIF($F$12:$U$12,"<="&$J$6,$F$18:$U$18)) / ($J$6) -> 0 | K8: UM/año | L8: ="Razonable para chile en torno a 1M y 1,5M por año." -> Razonable para chile en torno a 1M y 1,5M por año.
B9: Extremadamente Baja | D9: Mixto_MEDIA | G9: Objetivo de despligue UM 3F Indirecta | J9: =(SUMIF($F$12:$U$12,"<="&$J$6,$F$19:$U$19)) / ($J$6) -> 15720.667 | K9: UM/año | L9: ="Razonable para chile en torno a 1M y 1,5M por año." -> Razonable para chile en torno a 1M y 1,5M por año.
B12: Despligue SMI Chile | E12: Periodo | F12: 0 | G12: 1 | H12: 2 | I12: 3 | J12: 4 | K12: 5 | L12: 6 | M12: 7 | N12: 8 | O12: 9 | P12: 10 | Q12: 11 | R12: 12 | S12: 13 | T12: 14 | U12: 15
E13: Año | F13: 2025 | G13: 2026 | H13: 2027 | I13: 2028 | J13: 2029 | K13: 2030 | L13: 2031 | M13: 2032 | N13: 2033 | O13: 2034 | P13: 2035 | Q13: 2036 | R13: 2037 | S13: 2038 | T13: 2039 | U13: 2040
B15: Datos de despliegue | C15: Energía Facturada anual [GWh] | F15: =CB_SMI_Mixto_MEDIA!B2/1000 -> 8711.6828 | G15: =CB_SMI_Mixto_MEDIA!C2/1000 -> 8974.7756 | H15: =CB_SMI_Mixto_MEDIA!D2/1000 -> 9245.8139 | I15: =CB_SMI_Mixto_MEDIA!E2/1000 -> 9525.0374 | J15: =CB_SMI_Mixto_MEDIA!F2/1000 -> 9812.6936 | K15: =CB_SMI_Mixto_MEDIA!G2/1000 -> 10109.037 | L15: =CB_SMI_Mixto_MEDIA!H2/1000 -> 10414.33 | M15: =CB_SMI_Mixto_MEDIA!I2/1000 -> 10728.843 | ... U15: =CB_SMI_Mixto_MEDIA!Q2/1000 -> 13612.103
C17: UM 1F [N° Equipos] | F17: =CB_SMI_Mixto_MEDIA!B3 -> 2896 | G17: =CB_SMI_Mixto_MEDIA!C3 -> 11 | H17: =CB_SMI_Mixto_MEDIA!D3 -> 11 | I17: =CB_SMI_Mixto_MEDIA!E3 -> 11 | J17: =CB_SMI_Mixto_MEDIA!F3 -> 11 | K17: =CB_SMI_Mixto_MEDIA!G3 -> 13 | L17: =CB_SMI_Mixto_MEDIA!H3 -> 13 | M17: =CB_SMI_Mixto_MEDIA!I3 -> 13 | ... U17: =CB_SMI_Mixto_MEDIA!Q3 -> 13
C18: UM 3F Directa [N° Equipos] | F18: =CB_SMI_Mixto_MEDIA!B4 -> 0 | G18: =CB_SMI_Mixto_MEDIA!C4 -> 0 | H18: =CB_SMI_Mixto_MEDIA!D4 -> 0 | I18: =CB_SMI_Mixto_MEDIA!E4 -> 0 | J18: =CB_SMI_Mixto_MEDIA!F4 -> 0 | K18: =CB_SMI_Mixto_MEDIA!G4 -> 0 | L18: =CB_SMI_Mixto_MEDIA!H4 -> 0 | M18: =CB_SMI_Mixto_MEDIA!I4 -> 0 | ... U18: =CB_SMI_Mixto_MEDIA!Q4 -> 0
C19: UM 3F Indirecta [N° Equipos] | F19: =CB_SMI_Mixto_MEDIA!B5 -> 46463 | G19: =CB_SMI_Mixto_MEDIA!C5 -> 232 | H19: =CB_SMI_Mixto_MEDIA!D5 -> 232 | I19: =CB_SMI_Mixto_MEDIA!E5 -> 235 | J19: =CB_SMI_Mixto_MEDIA!F5 -> 235 | K19: =CB_SMI_Mixto_MEDIA!G5 -> 237 | L19: =CB_SMI_Mixto_MEDIA!H5 -> 237 | M19: =CB_SMI_Mixto_MEDIA!I5 -> 237 | ... U19: =CB_SMI_Mixto_MEDIA!Q5 -> 250
B21: Despliegue | C21: UM 1F instalados | F21: 0 | G21: =IF(G$12<=$J$6,$J7,G17) -> 976.33333 | H21: =IF(H$12<=$J$6,$J7,H17) -> 976.33333 | I21: =IF(I$12<=$J$6,$J7,I17) -> 976.33333 | J21: =IF(J$12<=$J$6,$J7,J17) -> 11 | K21: =IF(K$12<=$J$6,$J7,K17) -> 13 | L21: =IF(L$12<=$J$6,$J7,L17) -> 13 | M21: =IF(M$12<=$J$6,$J7,M17) -> 13 | N21: =IF(N$12<=$J$6,$J7,N17) -> 13 | ... U21: =IF(U$12<=$J$6,$J7,U17) -> 13
C22: UM 3F Directa instalados | F22: 0 | G22: =IF(G$12<=$J$6,$J8,G18) -> 0 | H22: =IF(H$12<=$J$6,$J8,H18) -> 0 | I22: =IF(I$12<=$J$6,$J8,I18) -> 0 | J22: =IF(J$12<=$J$6,$J8,J18) -> 0 | K22: =IF(K$12<=$J$6,$J8,K18) -> 0 | L22: =IF(L$12<=$J$6,$J8,L18) -> 0 | M22: =IF(M$12<=$J$6,$J8,M18) -> 0 | N22: =IF(N$12<=$J$6,$J8,N18) -> 0 | ... U22: =IF(U$12<=$J$6,$J8,U18) -> 0
C23: UM 3F Indirecta instalados | F23: 0 | G23: =IF(G$12<=$J$6,$J9,G19) -> 15720.667 | H23: =IF(H$12<=$J$6,$J9,H19) -> 15720.667 | I23: =IF(I$12<=$J$6,$J9,I19) -> 15720.667 | J23: =IF(J$12<=$J$6,$J9,J19) -> 235 | K23: =IF(K$12<=$J$6,$J9,K19) -> 237 | L23: =IF(L$12<=$J$6,$J9,L19) -> 237 | M23: =IF(M$12<=$J$6,$J9,M19) -> 237 | N23: =IF(N$12<=$J$6,$J9,N19) -> 239 | ... U23: =IF(U$12<=$J$6,$J9,U19) -> 250
C24: UM faltantes por instalar | F24: =SUM(F17:F19) -> 49359 | G24: =SUM(F24,G17:G19)-SUM(G21:G23) -> 32905 | H24: =SUM(G24,H17:H19)-SUM(H21:H23) -> 16451 | I24: =SUM(H24,I17:I19)-SUM(I21:I23) -> 0 | J24: =SUM(I24,J17:J19)-SUM(J21:J23) -> 0 | K24: =SUM(J24,K17:K19)-SUM(K21:K23) -> 0 | L24: =SUM(K24,L17:L19)-SUM(L21:L23) -> 0 | M24: =SUM(L24,M17:M19)-SUM(M21:M23) -> 0 | N24: =SUM(M24,N17:N19)-SUM(N21:N23) -> 0 | ... U24: =SUM(T24,U17:U19)-SUM(U21:U23) -> 0
C25: % de avance | F25: 0 | G25: =IF(G$12<=$J$6,SUM($F$21:G23)/SUM($F$17:G19),1) -> 0.33661949 | H25: =IF(H$12<=$J$6,SUM($F$21:H23)/SUM($F$17:H19),1) -> 0.66995687 | I25: =IF(I$12<=$J$6,SUM($F$21:I23)/SUM($F$17:I19),1) -> 1 | J25: =IF(J$12<=$J$6,SUM($F$21:J23)/SUM($F$17:J19),1) -> 1 | K25: =IF(K$12<=$J$6,SUM($F$21:K23)/SUM($F$17:K19),1) -> 1 | L25: =IF(L$12<=$J$6,SUM($F$21:L23)/SUM($F$17:L19),1) -> 1 | M25: =IF(M$12<=$J$6,SUM($F$21:M23)/SUM($F$17:M19),1) -> 1 | N25: =IF(N$12<=$J$6,SUM($F$21:N23)/SUM($F$17:N19),1) -> 1 | ... U25: =IF(U$12<=$J$6,SUM($F$21:U23)/SUM($F$17:U19),1) -> 1
B27: Flujo de caja [MUSD] | E27: Periodo | F27: 0 | G27: 1 | H27: 2 | I27: 3 | J27: 4 | K27: 5 | L27: 6 | M27: 7 | N27: 8 | O27: 9 | P27: 10 | Q27: 11 | R27: 12 | S27: 13 | T27: 14 | U27: 15
E28: Año | F28: 2025 | G28: 2026 | H28: 2027 | I28: 2028 | J28: 2029 | K28: 2030 | L28: 2031 | M28: 2032 | N28: 2033 | O28: 2034 | P28: 2035 | Q28: 2036 | R28: 2037 | S28: 2038 | T28: 2039 | U28: 2040 | W28: VAN [MUSD] | X28: AVAN [MUSD] | Y28: VAN [USD/# Clientes] | Z28: Participación %
B30: VI [MUSD] | C30: UM 1F | F30: 0 | G30: =((-CB_SMI_Mixto_MEDIA!C7)*G21)/1000000 -> -0.13547601 | H30: =((-CB_SMI_Mixto_MEDIA!D7)*H21)/1000000 -> -0.13547601 | I30: =((-CB_SMI_Mixto_MEDIA!E7)*I21)/1000000 -> -0.13547601 | J30: =((-CB_SMI_Mixto_MEDIA!F7)*J21)/1000000 -> -0.00152636 | K30: =((-CB_SMI_Mixto_MEDIA!G7)*K21)/1000000 -> -0.00180388 | L30: =((-CB_SMI_Mixto_MEDIA!H7)*L21)/1000000 -> -0.00180388 | M30: =((-CB_SMI_Mixto_MEDIA!I7)*M21)/1000000 -> -0.00180388 | N30: =((-CB_SMI_Mixto_MEDIA!J7)*N21)/1000000 -> -0.00180388 | ... U30: =((-CB_SMI_Mixto_MEDIA!Q7)*U21)/1000000 -> -0.00180388 | W30: =NPV($D$67,G30:U30)+F30 -> -0.37460712 | X30: =PMT($D$67,15,-W30) -> -0.038570584 | Y30: =W30*1000000/7744865 -> -0.048368451 | Z30: =W30/$W$36 -> 0.011434322
C31: UM 3F Directa | F31: 0 | G31: =((-CB_SMI_Mixto_MEDIA!C8)*G22)/1000000 -> 0 | H31: =((-CB_SMI_Mixto_MEDIA!D8)*H22)/1000000 -> 0 | I31: =((-CB_SMI_Mixto_MEDIA!E8)*I22)/1000000 -> 0 | J31: =((-CB_SMI_Mixto_MEDIA!F8)*J22)/1000000 -> 0 | K31: =((-CB_SMI_Mixto_MEDIA!G8)*K22)/1000000 -> 0 | L31: =((-CB_SMI_Mixto_MEDIA!H8)*L22)/1000000 -> 0 | M31: =((-CB_SMI_Mixto_MEDIA!I8)*M22)/1000000 -> 0 | N31: =((-CB_SMI_Mixto_MEDIA!J8)*N22)/1000000 -> 0 | ... U31: =((-CB_SMI_Mixto_MEDIA!Q8)*U22)/1000000 -> 0 | W31: =NPV($D$67,G31:U31)+F31 -> 0 | X31: =PMT($D$67,15,-W31) -> 0 | Y31: =W31*1000000/7744865 -> 0 | Z31: =W31/$W$36 -> 0
C32: UM 3F Indirecta | F32: 0 | G32: =((-CB_SMI_Mixto_MEDIA!C9)*G23)/1000000 -> -11.281025 | H32: =((-CB_SMI_Mixto_MEDIA!D9)*H23)/1000000 -> -11.281025 | I32: =((-CB_SMI_Mixto_MEDIA!E9)*I23)/1000000 -> -11.281025 | J32: =((-CB_SMI_Mixto_MEDIA!F9)*J23)/1000000 -> -0.16863412 | K32: =((-CB_SMI_Mixto_MEDIA!G9)*K23)/1000000 -> -0.1700693 | L32: =((-CB_SMI_Mixto_MEDIA!H9)*L23)/1000000 -> -0.1700693 | M32: =((-CB_SMI_Mixto_MEDIA!I9)*M23)/1000000 -> -0.1700693 | N32: =((-CB_SMI_Mixto_MEDIA!J9)*N23)/1000000 -> -0.17150449 | ... U32: =((-CB_SMI_Mixto_MEDIA!Q9)*U23)/1000000 -> -0.179398 | W32: =NPV($D$67,G32:U32)+F32 -> -31.365246 | X32: =PMT($D$67,15,-W32) -> -3.2294525 | Y32: =W32*1000000/7744865 -> -4.0498119 | Z32: =W32/$W$36 -> 0.95737725
C33: DCU | F33: =((-CB_SMI_Mixto_MEDIA!B10)*CB_SMI_Mixto_MEDIA!B6)/1000000 -> 0 | G33: =((-CB_SMI_Mixto_MEDIA!C10)*CB_SMI_Mixto_MEDIA!C6)/1000000 -> 0 | H33: =((-CB_SMI_Mixto_MEDIA!D10)*CB_SMI_Mixto_MEDIA!D6)/1000000 -> 0 | I33: =((-CB_SMI_Mixto_MEDIA!E10)*CB_SMI_Mixto_MEDIA!E6)/1000000 -> 0 | J33: =((-CB_SMI_Mixto_MEDIA!F10)*CB_SMI_Mixto_MEDIA!F6)/1000000 -> 0 | K33: =((-CB_SMI_Mixto_MEDIA!G10)*CB_SMI_Mixto_MEDIA!G6)/1000000 -> 0 | L33: =((-CB_SMI_Mixto_MEDIA!H10)*CB_SMI_Mixto_MEDIA!H6)/1000000 -> 0 | M33: =((-CB_SMI_Mixto_MEDIA!I10)*CB_SMI_Mixto_MEDIA!I6)/1000000 -> 0 | ... U33: =((-CB_SMI_Mixto_MEDIA!Q10)*CB_SMI_Mixto_MEDIA!Q6)/1000000 -> 0 | W33: =NPV($D$67,G33:U33)+F33 -> 0 | X33: =PMT($D$67,15,-W33) -> 0 | Y33: =W33*1000000/7744865 -> 0 | Z33: =W33/$W$36 -> 0
C34: HES | F34: =(-CB_SMI_Mixto_MEDIA!B11)/1000000 -> -0.90578701 | G34: =(-CB_SMI_Mixto_MEDIA!C11)/1000000 -> -0.004459293 | H34: =(-CB_SMI_Mixto_MEDIA!D11)/1000000 -> -0.004459293 | I34: =(-CB_SMI_Mixto_MEDIA!E11)/1000000 -> -0.004514346 | J34: =(-CB_SMI_Mixto_MEDIA!F11)/1000000 -> -0.004514346 | K34: =(-CB_SMI_Mixto_MEDIA!G11)/1000000 -> -0.00458775 | L34: =(-CB_SMI_Mixto_MEDIA!H11)/1000000 -> -0.00458775 | M34: =(-CB_SMI_Mixto_MEDIA!I11)/1000000 -> -0.00458775 | ... U34: =(-CB_SMI_Mixto_MEDIA!Q11)/1000000 -> -0.004826313 | W34: =NPV($D$67,G34:U34)+F34 -> -0.95037042 | X34: =PMT($D$67,15,-W34) -> -0.097852765 | Y34: =W34*1000000/7744865 -> -0.12270975 | Z34: =W34/$W$36 -> 0.029008636
C35: MDMS | F35: =(-CB_SMI_Mixto_MEDIA!B12)/1000000 -> -0.068063463 | G35: =(-CB_SMI_Mixto_MEDIA!C12)/1000000 -> -0.00033508421 | H35: =(-CB_SMI_Mixto_MEDIA!D12)/1000000 -> -0.00033508421 | I35: =(-CB_SMI_Mixto_MEDIA!E12)/1000000 -> -0.00033922105 | J35: =(-CB_SMI_Mixto_MEDIA!F12)/1000000 -> -0.00033922105 | K35: =(-CB_SMI_Mixto_MEDIA!G12)/1000000 -> -0.00034473684 | L35: =(-CB_SMI_Mixto_MEDIA!H12)/1000000 -> -0.00034473684 | M35: =(-CB_SMI_Mixto_MEDIA!I12)/1000000 -> -0.00034473684 | ... U35: =(-CB_SMI_Mixto_MEDIA!Q12)/1000000 -> -0.00036266316 | W35: =NPV($D$67,G35:U35)+F35 -> -0.07141359 | X35: =PMT($D$67,15,-W35) -> -0.0073529406 | Y35: =W35*1000000/7744865 -> -0.0092207663 | Z35: =W35/$W$36 -> 0.0021797931
C36: VI Total: | F36: =SUM(F30:F35) -> -0.97385047 | G36: =SUM(G30:G35) -> -11.421295 | H36: =SUM(H30:H35) -> -11.421295 | I36: =SUM(I30:I35) -> -11.421354 | J36: =SUM(J30:J35) -> -0.17501405 | K36: =SUM(K30:K35) -> -0.17680567 | L36: =SUM(L30:L35) -> -0.17680567 | M36: =SUM(M30:M35) -> -0.17680567 | ... U36: =SUM(U30:U35) -> -0.18639086 | W36: =NPV($D$67,G36:U36)+F36 -> -32.761638 | X36: =PMT($D$67,15,-W36) -> -3.3732288 | Y36: =W36*1000000/7744865 -> -4.2301109 | Z36: =W36/$W$36 -> 1
B38: COMA [MUSD] | C38: Operación Comunicaciones UM - SGO | F38: 0 | G38: =(-CB_SMI_Mixto_MEDIA!C13/1000000)*G$25 -> 0 | H38: =(-CB_SMI_Mixto_MEDIA!D13/1000000)*H$25 -> 0 | I38: =(-CB_SMI_Mixto_MEDIA!E13/1000000)*I$25 -> 0 | J38: =(-CB_SMI_Mixto_MEDIA!F13/1000000)*J$25 -> 0 | K38: =(-CB_SMI_Mixto_MEDIA!G13/1000000)*K$25 -> 0 | L38: =(-CB_SMI_Mixto_MEDIA!H13/1000000)*L$25 -> 0 | M38: =(-CB_SMI_Mixto_MEDIA!I13/1000000)*M$25 -> 0 | N38: =(-CB_SMI_Mixto_MEDIA!J13/1000000)*N$25 -> 0 | ... U38: =(-CB_SMI_Mixto_MEDIA!Q13/1000000)*U$25 -> 0 | W38: =NPV($D$67,G38:U38)+F38 -> 0 | X38: =PMT($D$67,15,-W38) -> 0 | Y38: =W38*1000000/7744865 -> 0 | Z38: =W38/$W$43 -> 0
C39: Operación Comunicaciones DCU - SGO | F39: 0 | G39: =(-CB_SMI_Mixto_MEDIA!C14/1000000)*G$25 -> -0.2793216 | H39: =(-CB_SMI_Mixto_MEDIA!D14/1000000)*H$25 -> -0.55591975 | I39: =(-CB_SMI_Mixto_MEDIA!E14/1000000)*I$25 -> -0.82978439 | J39: =(-CB_SMI_Mixto_MEDIA!F14/1000000)*J$25 -> -0.82978439 | K39: =(-CB_SMI_Mixto_MEDIA!G14/1000000)*K$25 -> -0.82978439 | L39: =(-CB_SMI_Mixto_MEDIA!H14/1000000)*L$25 -> -0.82978439 | M39: =(-CB_SMI_Mixto_MEDIA!I14/1000000)*M$25 -> -0.82978439 | N39: =(-CB_SMI_Mixto_MEDIA!J14/1000000)*N$25 -> -0.82978439 | ... U39: =(-CB_SMI_Mixto_MEDIA!Q14/1000000)*U$25 -> -0.82978439 | W39: =NPV($D$67,G39:U39)+F39 -> -7.2960295 | X39: =PMT($D$67,15,-W39) -> -0.75121937 | Y39: =W39*1000000/7744865 -> -0.94204735 | Z39: =W39/$W$43 -> 0.60991407
C40: Operación HES | F40: 0 | G40: =(-CB_SMI_Mixto_MEDIA!C15/1000000)*G$25 -> -0.13333095 | H40: =(-CB_SMI_Mixto_MEDIA!D15/1000000)*H$25 -> -0.26666189 | I40: =(-CB_SMI_Mixto_MEDIA!E15/1000000)*I$25 -> -0.39999284 | J40: =(-CB_SMI_Mixto_MEDIA!F15/1000000)*J$25 -> -0.40195723 | K40: =(-CB_SMI_Mixto_MEDIA!G15/1000000)*K$25 -> -0.40395356 | L40: =(-CB_SMI_Mixto_MEDIA!H15/1000000)*L$25 -> -0.40594989 | M40: =(-CB_SMI_Mixto_MEDIA!I15/1000000)*M$25 -> -0.40794622 | N40: =(-CB_SMI_Mixto_MEDIA!J15/1000000)*N$25 -> -0.40995853 | ... U40: =(-CB_SMI_Mixto_MEDIA!Q15/1000000)*U$25 -> -0.42426823 | W40: =NPV($D$67,G40:U40)+F40 -> -3.596525 | X40: =PMT($D$67,15,-W40) -> -0.37030815 | Y40: =W40*1000000/7744865 -> -0.46437542 | Z40: =W40/$W$43 -> 0.30065273
C41: Operación MDMS | F41: 0 | G41: =(-CB_SMI_Mixto_MEDIA!C16/1000000)*G$25 -> -0.018923413 | H41: =(-CB_SMI_Mixto_MEDIA!D16/1000000)*H$25 -> -0.037846826 | I41: =(-CB_SMI_Mixto_MEDIA!E16/1000000)*I$25 -> -0.056770239 | J41: =(-CB_SMI_Mixto_MEDIA!F16/1000000)*J$25 -> -0.057049042 | K41: =(-CB_SMI_Mixto_MEDIA!G16/1000000)*K$25 -> -0.057332377 | L41: =(-CB_SMI_Mixto_MEDIA!H16/1000000)*L$25 -> -0.057615713 | M41: =(-CB_SMI_Mixto_MEDIA!I16/1000000)*M$25 -> -0.057899048 | N41: =(-CB_SMI_Mixto_MEDIA!J16/1000000)*N$25 -> -0.05818465 | ... U41: =(-CB_SMI_Mixto_MEDIA!Q16/1000000)*U$25 -> -0.060215599 | W41: =NPV($D$67,G41:U41)+F41 -> -0.51044809 | X41: =PMT($D$67,15,-W41) -> -0.052557146 | Y41: =W41*1000000/7744865 -> -0.065907939 | Z41: =W41/$W$43 -> 0.042671082
C42: SyM Equipos | F42: 0 | G42: =(-CB_SMI_Mixto_MEDIA!C17/1000000)*G$25 -> -0.020737674 | H42: =(-CB_SMI_Mixto_MEDIA!D17/1000000)*H$25 -> -0.041475348 | I42: =(-CB_SMI_Mixto_MEDIA!E17/1000000)*I$25 -> -0.062213022 | J42: =(-CB_SMI_Mixto_MEDIA!F17/1000000)*J$25 -> -0.062518554 | K42: =(-CB_SMI_Mixto_MEDIA!G17/1000000)*K$25 -> -0.062829054 | L42: =(-CB_SMI_Mixto_MEDIA!H17/1000000)*L$25 -> -0.063139554 | M42: =(-CB_SMI_Mixto_MEDIA!I17/1000000)*M$25 -> -0.063450054 | N42: =(-CB_SMI_Mixto_MEDIA!J17/1000000)*N$25 -> -0.063763038 | ... U42: =(-CB_SMI_Mixto_MEDIA!Q17/1000000)*U$25 -> -0.065988702 | W42: =NPV($D$67,G42:U42)+F42 -> -0.55938673 | X42: =PMT($D$67,15,-W42) -> -0.057596003 | Y42: =W42*1000000/7744865 -> -0.072226788 | Z42: =W42/$W$43 -> 0.046762123
C43: COMA Total: | F43: =SUM(F38:F42) -> 0 | G43: =SUM(G38:G42) -> -0.45231363 | H43: =SUM(H38:H42) -> -0.90190382 | I43: =SUM(I38:I42) -> -1.3487605 | J43: =SUM(J38:J42) -> -1.3513092 | K43: =SUM(K38:K42) -> -1.3538994 | L43: =SUM(L38:L42) -> -1.3564895 | M43: =SUM(M38:M42) -> -1.3590797 | ... U43: =SUM(U38:U42) -> -1.3802569 | W43: =NPV($D$67,G43:U43)+F43 -> -11.962389 | X43: =PMT($D$67,15,-W43) -> -1.2316807 | Y43: =W43*1000000/7744865 -> -1.5445575 | Z43: =W43/$W$43 -> 1
B45: Costos Totales (VI + COMA) | F45: =F36+F43 -> -0.97385047 | G45: =G36+G43 -> -11.873609 | H45: =H36+H43 -> -12.323199 | I45: =I36+I43 -> -12.770115 | J45: =J36+J43 -> -1.5263233 | K45: =K36+K43 -> -1.5307051 | L45: =L36+L43 -> -1.5332952 | M45: =M36+M43 -> -1.5358854 | ... U45: =U36+U43 -> -1.5666478 | W45: =NPV($D$67,G45:U45)+F45 -> -44.724027 | X45: =PMT($D$67,15,-W45) -> -4.6049094 | Y45: =W45*1000000/7744865 -> -5.7746684
B47: Beneficios [MUSD] | C47: Ahorro de lectura pedestre | F47: 0 | G47: =(CB_SMI_Mixto_MEDIA!C18/1000000)*G$25 -> 0 | H47: =(CB_SMI_Mixto_MEDIA!D18/1000000)*H$25 -> 0 | I47: =(CB_SMI_Mixto_MEDIA!E18/1000000)*I$25 -> 0 | J47: =(CB_SMI_Mixto_MEDIA!F18/1000000)*J$25 -> 0 | K47: =(CB_SMI_Mixto_MEDIA!G18/1000000)*K$25 -> 0 | L47: =(CB_SMI_Mixto_MEDIA!H18/1000000)*L$25 -> 0 | M47: =(CB_SMI_Mixto_MEDIA!I18/1000000)*M$25 -> 0 | N47: =(CB_SMI_Mixto_MEDIA!J18/1000000)*N$25 -> 0 | ... U47: =(CB_SMI_Mixto_MEDIA!Q18/1000000)*U$25 -> 0 | V47: =U47/$U$56 -> 0 | W47: =NPV($D$67,G47:U47)+F47 -> 0 | X47: =PMT($D$67,15,-W47) -> 0 | Y47: =W47*1000000/7744865 -> 0 | Z47: =W47/$W$56 -> 0
C48: Corte y Reposición remoto | F48: 0 | G48: =(CB_SMI_Mixto_MEDIA!C19/1000000)*G$25 -> 0 | H48: =(CB_SMI_Mixto_MEDIA!D19/1000000)*H$25 -> 0 | I48: =(CB_SMI_Mixto_MEDIA!E19/1000000)*I$25 -> 0 | J48: =(CB_SMI_Mixto_MEDIA!F19/1000000)*J$25 -> 0 | K48: =(CB_SMI_Mixto_MEDIA!G19/1000000)*K$25 -> 0 | L48: =(CB_SMI_Mixto_MEDIA!H19/1000000)*L$25 -> 0 | M48: =(CB_SMI_Mixto_MEDIA!I19/1000000)*M$25 -> 0 | N48: =(CB_SMI_Mixto_MEDIA!J19/1000000)*N$25 -> 0 | ... U48: =(CB_SMI_Mixto_MEDIA!Q19/1000000)*U$25 -> 0 | V48: =U48/$U$56 -> 0 | W48: =NPV($D$67,G48:U48)+F48 -> 0 | X48: =PMT($D$67,15,-W48) -> 0 | Y48: =W48*1000000/7744865 -> 0 | Z48: =W48/$W$56 -> 0
C49: Reducción de Pérdidas No Técnicas | F49: 0 | G49: =(CB_SMI_Mixto_MEDIA!C20/1000000)*G$25 -> 0 | H49: =(CB_SMI_Mixto_MEDIA!D20/1000000)*H$25 -> 0 | I49: =(CB_SMI_Mixto_MEDIA!E20/1000000)*I$25 -> 0 | J49: =(CB_SMI_Mixto_MEDIA!F20/1000000)*J$25 -> 0 | K49: =(CB_SMI_Mixto_MEDIA!G20/1000000)*K$25 -> 0 | L49: =(CB_SMI_Mixto_MEDIA!H20/1000000)*L$25 -> 0 | M49: =(CB_SMI_Mixto_MEDIA!I20/1000000)*M$25 -> 0 | N49: =(CB_SMI_Mixto_MEDIA!J20/1000000)*N$25 -> 0 | ... U49: =(CB_SMI_Mixto_MEDIA!Q20/1000000)*U$25 -> 0 | V49: =U49/$U$56 -> 0 | W49: =NPV($D$67,G49:U49)+F49 -> 0 | X49: =PMT($D$67,15,-W49) -> 0 | Y49: =W49*1000000/7744865 -> 0 | Z49: =W49/$W$56 -> 0
C50: Reducción del tiempo de respuesta ante Fallas | F50: 0 | G50: =(CB_SMI_Mixto_MEDIA!C21/1000000)*G$25 -> 0.24434502 | H50: =(CB_SMI_Mixto_MEDIA!D21/1000000)*H$25 -> 0.48630762 | I50: =(CB_SMI_Mixto_MEDIA!E21/1000000)*I$25 -> 0.725879 | J50: =(CB_SMI_Mixto_MEDIA!F21/1000000)*J$25 -> 0.725879 | K50: =(CB_SMI_Mixto_MEDIA!G21/1000000)*K$25 -> 0.725879 | L50: =(CB_SMI_Mixto_MEDIA!H21/1000000)*L$25 -> 0.725879 | M50: =(CB_SMI_Mixto_MEDIA!I21/1000000)*M$25 -> 0.725879 | N50: =(CB_SMI_Mixto_MEDIA!J21/1000000)*N$25 -> 0.725879 | ... U50: =(CB_SMI_Mixto_MEDIA!Q21/1000000)*U$25 -> 0.725879 | V50: =U50/$U$56 -> 0.26778387 | W50: =NPV($D$67,G50:U50)+F50 -> 6.3824226 | X50: =PMT($D$67,15,-W50) -> 0.65715187 | Y50: =W50*1000000/7744865 -> 0.82408442 | Z50: =W50/$W$56 -> 0.27180332
C51: Reducción del costo de la energía en horas de Sol | F51: 0 | G51: =(CB_SMI_Mixto_MEDIA!C22/1000000)*G$25 -> 0 | H51: =(CB_SMI_Mixto_MEDIA!D22/1000000)*H$25 -> 0 | I51: =(CB_SMI_Mixto_MEDIA!E22/1000000)*I$25 -> 0 | J51: =(CB_SMI_Mixto_MEDIA!F22/1000000)*J$25 -> 0 | K51: =(CB_SMI_Mixto_MEDIA!G22/1000000)*K$25 -> 0 | L51: =(CB_SMI_Mixto_MEDIA!H22/1000000)*L$25 -> 0 | M51: =(CB_SMI_Mixto_MEDIA!I22/1000000)*M$25 -> 0 | N51: =(CB_SMI_Mixto_MEDIA!J22/1000000)*N$25 -> 0 | ... U51: =(CB_SMI_Mixto_MEDIA!Q22/1000000)*U$25 -> 0 | V51: =U51/$U$56 -> 0 | W51: =NPV($D$67,G51:U51)+F51 -> 0 | X51: =PMT($D$67,15,-W51) -> 0 | Y51: =W51*1000000/7744865 -> 0 | Z51: =W51/$W$56 -> 0
C52: Reducción del consumo de Clientes Finales | F52: 0 | G52: =(CB_SMI_Mixto_MEDIA!C23/1000000)*G$25 -> 0 | H52: =(CB_SMI_Mixto_MEDIA!D23/1000000)*H$25 -> 0 | I52: =(CB_SMI_Mixto_MEDIA!E23/1000000)*I$25 -> 0 | J52: =(CB_SMI_Mixto_MEDIA!F23/1000000)*J$25 -> 0 | K52: =(CB_SMI_Mixto_MEDIA!G23/1000000)*K$25 -> 0 | L52: =(CB_SMI_Mixto_MEDIA!H23/1000000)*L$25 -> 0 | M52: =(CB_SMI_Mixto_MEDIA!I23/1000000)*M$25 -> 0 | N52: =(CB_SMI_Mixto_MEDIA!J23/1000000)*N$25 -> 0 | ... U52: =(CB_SMI_Mixto_MEDIA!Q23/1000000)*U$25 -> 0 | V52: =U52/$U$56 -> 0 | W52: =NPV($D$67,G52:U52)+F52 -> 0 | X52: =PMT($D$67,15,-W52) -> 0 | Y52: =W52*1000000/7744865 -> 0 | Z52: =W52/$W$56 -> 0
C53: Reducción de emisiones de CO2 | F53: 0 | G53: =(CB_SMI_Mixto_MEDIA!C24/1000000)*G$25 -> 0 | H53: =(CB_SMI_Mixto_MEDIA!D24/1000000)*H$25 -> 0 | I53: =(CB_SMI_Mixto_MEDIA!E24/1000000)*I$25 -> 0 | J53: =(CB_SMI_Mixto_MEDIA!F24/1000000)*J$25 -> 0 | K53: =(CB_SMI_Mixto_MEDIA!G24/1000000)*K$25 -> 0 | L53: =(CB_SMI_Mixto_MEDIA!H24/1000000)*L$25 -> 0 | M53: =(CB_SMI_Mixto_MEDIA!I24/1000000)*M$25 -> 0 | N53: =(CB_SMI_Mixto_MEDIA!J24/1000000)*N$25 -> 0 | ... U53: =(CB_SMI_Mixto_MEDIA!Q24/1000000)*U$25 -> 0 | V53: =U53/$U$56 -> 0 | W53: =NPV($D$67,G53:U53)+F53 -> 0 | X53: =PMT($D$67,15,-W53) -> 0 | Y53: =W53*1000000/7744865 -> 0 | Z53: =W53/$W$56 -> 0
C54: Reducción servicio Atención al Cliente | F54: 0 | G54: =(CB_SMI_Mixto_MEDIA!C25/1000000)*G$25 -> 0 | H54: =(CB_SMI_Mixto_MEDIA!D25/1000000)*H$25 -> 0 | I54: =(CB_SMI_Mixto_MEDIA!E25/1000000)*I$25 -> 0 | J54: =(CB_SMI_Mixto_MEDIA!F25/1000000)*J$25 -> 0 | K54: =(CB_SMI_Mixto_MEDIA!G25/1000000)*K$25 -> 0 | L54: =(CB_SMI_Mixto_MEDIA!H25/1000000)*L$25 -> 0 | M54: =(CB_SMI_Mixto_MEDIA!I25/1000000)*M$25 -> 0 | N54: =(CB_SMI_Mixto_MEDIA!J25/1000000)*N$25 -> 0 | ... U54: =(CB_SMI_Mixto_MEDIA!Q25/1000000)*U$25 -> 0 | V54: =U54/$U$56 -> 0 | W54: =NPV($D$67,G54:U54)+F54 -> 0 | X54: =PMT($D$67,15,-W54) -> 0 | Y54: =W54*1000000/7744865 -> 0 | Z54: =W54/$W$56 -> 0
C55: Reducción en Inversión de infraestructura de red | F55: 0 | G55: =(CB_SMI_Mixto_MEDIA!C26/1000000)*G$25 -> 0.64049369 | H55: =(CB_SMI_Mixto_MEDIA!D26/1000000)*H$25 -> 1.2757067 | I55: =(CB_SMI_Mixto_MEDIA!E26/1000000)*I$25 -> 1.9251481 | J55: =(CB_SMI_Mixto_MEDIA!F26/1000000)*J$25 -> 1.9296631 | K55: =(CB_SMI_Mixto_MEDIA!G26/1000000)*K$25 -> 1.9326018 | L55: =(CB_SMI_Mixto_MEDIA!H26/1000000)*L$25 -> 1.9347176 | M55: =(CB_SMI_Mixto_MEDIA!I26/1000000)*M$25 -> 1.9367824 | N55: =(CB_SMI_Mixto_MEDIA!J26/1000000)*N$25 -> 1.9527909 | ... U55: =(CB_SMI_Mixto_MEDIA!Q26/1000000)*U$25 -> 1.9848108 | V55: =U55/$U$56 -> 0.73221613 | W55: =NPV($D$67,G55:U55)+F55 -> 17.099346 | X55: =PMT($D$67,15,-W55) -> 1.7605959 | Y55: =W55*1000000/7744865 -> 2.20783 | Z55: =W55/$W$56 -> 0.72819668
C56: Beneficios Total: | F56: =SUM(F47:F55) -> 0 | G56: =SUM(G47:G55) -> 0.88483871 | H56: =SUM(H47:H55) -> 1.7620143 | I56: =SUM(I47:I55) -> 2.6510271 | J56: =SUM(J47:J55) -> 2.6555421 | K56: =SUM(K47:K55) -> 2.6584808 | L56: =SUM(L47:L55) -> 2.6605966 | M56: =SUM(M47:M55) -> 2.6626614 | ... U56: =SUM(U47:U55) -> 2.7106898 | W56: =NPV($D$67,G56:U56)+F56 -> 23.481768 | X56: =PMT($D$67,15,-W56) -> 2.4177478 | Y56: =W56*1000000/7744865 -> 3.0319145 | Z56: =W56/$W$56 -> 1
B58: Flujo | F58: =F45+F56 -> -0.97385047 | G58: =G45+G56 -> -10.98877 | H58: =H45+H56 -> -10.561185 | I58: =I45+I56 -> -10.119088 | J58: =J45+J56 -> 1.1292188 | K58: =K45+K56 -> 1.1277757 | L58: =L45+L56 -> 1.1273014 | M58: =M45+M56 -> 1.126776 | ... U58: =U45+U56 -> 1.144042
B60: Flujo del periodo anterior | F60: 0 | G60: =F61 -> -0.97385047 | H60: =G61 -> -11.96262 | I60: =H61 -> -22.523805 | J60: =I61 -> -32.642893 | K60: =J61 -> -31.513674 | L60: =K61 -> -30.385898 | M60: =L61 -> -29.258597 | N60: =M61 -> -28.131821 | ... U60: =T61 -> -20.14521
B61: Flujo Acumulado | F61: =F58+F60 -> -0.97385047 | G61: =G58+G60 -> -11.96262 | H61: =H58+H60 -> -22.523805 | I61: =I58+I60 -> -32.642893 | J61: =J58+J60 -> -31.513674 | K61: =K58+K60 -> -30.385898 | L61: =L58+L60 -> -29.258597 | M61: =M58+M60 -> -28.131821 | ... U61: =U58+U60 -> -19.001168
B63: Flujo descontado (6%) | F63: =F58/(1+0.06)^F27 -> -0.97385047 | G63: =G58/(1+0.06)^G27 -> -10.366764 | H63: =H58/(1+0.06)^H27 -> -9.3994166 | I63: =I58/(1+0.06)^I27 -> -8.4961811 | J63: =J58/(1+0.06)^J27 -> 0.89444706 | K63: =K58/(1+0.06)^K27 -> 0.84273964 | L63: =L58/(1+0.06)^L27 -> 0.79470298 | M63: =M58/(1+0.06)^M27 -> 0.7493704 | ... U63: =U58/(1+0.06)^U27 -> 0.47736875
B64: Flujo Acumulado descontado (6%) | F64: =F63 -> -0.97385047 | G64: =F64+G63 -> -11.340615 | H64: =G64+H63 -> -20.740031 | I64: =H64+I63 -> -29.236212 | J64: =I64+J63 -> -28.341765 | K64: =J64+K63 -> -27.499026 | L64: =K64+L63 -> -26.704323 | M64: =L64+M63 -> -25.954952 | N64: =M64+N63 -> -25.240518 | ... U64: =T64+U63 -> -21.242259
B67: Tasa | D67: =J4 -> 0.06 | H67: Monto [MUSD] | J67: Monto [USD/cliente] | L67: Monto [$/cliente]
F68: VAN (Costos) | H68: =NPV(D67,G45:U45)+F45 -> -44.724027 | J68: =H68*1000000/$D$74 -> -20.719611 | L68: =J68*$S$4 -> -19877.566
B69: VAN | D69: =NPV(D67,G58:U58)+F58 -> -21.242259 | F69: Anualidad (Costos) | H69: =PMT(D67,15,-H68) -> -4.6049094 | J69: =H69*1000000/$D$74 -> -2.1333484 | L69: =J69*$S$4 -> -2046.6492
B70: TIR | D70: =IRR(F58:U58) -> -0.10106413 | F70: Mensualidad (Costos) | H70: =H69/12 -> -0.38374245 | J70: =J69/12 -> -0.17777904 | L70: =L69/12 -> -170.5541
B71: B/C | D71: =NPV(D67,G56:U56)/-(F36+NPV(D67,G36:U36)+NPV(D67,G43:U43)) -> 0.52503699
F72: VAN (Beneficios) | H72: =NPV(D67,G56:U56)+F56 -> 23.481768 | J72: =H72*1000000/$D$74 -> 10.878562 | L72: =J72*$S$4 -> 10436.457
B73: # Clientes Alta | D73: 2527114 | F73: Anualidad (Beneficios) | H73: =PMT(D67,15,-H72) -> 2.4177478 | J73: =H73*1000000/$D$74 -> 1.1200868 | L73: =J73*$S$4 -> 1074.5665
B74: # Clientes Media | D74: 2158536 | F74: Mensualidad (Beneficios) | H74: =H73/12 -> 0.20147898 | J74: =J73/12 -> 0.09334057 | L74: =L73/12 -> 89.547209
B75: # Clientes Baja | D75: 1173397
B76: # Clientes Muy Baja | D76: 1288141 | F76: VAN (Neto) | H76: =H72+H68 -> -21.242259 | J76: =H76*1000000/$D$74 -> -9.841049 | L76: =J76*$S$4 -> -9441.1088
B77: # Clientes Ext. Baja | D77: 593823 | F77: Anualidad (Neto) | H77: =PMT(D67,15,-H76) -> -2.1871617 | J77: =H77*1000000/$D$74 -> -1.0132616 | L77: =J77*$S$4 -> -972.08266
F78: Mensualidad (Neto) | H78: =H77/12 -> -0.18226347 | J78: =J77/12 -> -0.084438467 | L78: =L77/12 -> -81.006888
B79: # Clientes Regulados | D79: =SUM(D73:D77) -> 7741011

Sheet CB_SMI_Mixto_BAJA
A1: Concepto | B1: Periodo 0 | C1: Periodo 1 | D1: Periodo 2 | E1: Periodo 3 | F1: Periodo 4 | G1: Periodo 5 | H1: Periodo 6 | I1: Periodo 7 | J1: Periodo 8 | K1: Periodo 9 | L1: Periodo 10 | M1: Periodo 11 | N1: Periodo 12 | O1: Periodo 13 | P1: Periodo 14 | Q1: Periodo 15
A2: Energía facturada anual [MWh/año] | B2: 7398893.4 | C2: 7622340 | D2: 7852534.6 | E2: 8089681.2 | F2: 8333989.5 | G2: 8585676 | H2: 8844963.4 | I2: 9112081.3 | J2: 9387266.2 | K2: 9670761.6 | L2: 9962818.6 | M2: 10263696 | N2: 10573659 | O2: 10892984 | P2: 11221952 | Q2: 11560855
A3: Cantidad UM 1F | B3: 3119 | C3: 1 | D3: 1 | E3: 1 | F3: 1 | G3: 1 | H3: 1 | I3: 1 | J3: 1 | K3: 1 | L3: 1 | M3: 1 | N3: 1 | O3: 1 | P3: 1 | Q3: 1
A4: Cantidad UM 3F Directa | B4: 0 | C4: 0 | D4: 0 | E4: 0 | F4: 0 | G4: 0 | H4: 0 | I4: 0 | J4: 0 | K4: 0 | L4: 0 | M4: 0 | N4: 0 | O4: 0 | P4: 0 | Q4: 0
A5: Cantidad UM 3F Indirecta | B5: 32811 | C5: 15 | D5: 15 | E5: 15 | F5: 15 | G5: 15 | H5: 15 | I5: 15 | J5: 15 | K5: 15 | L5: 15 | M5: 15 | N5: 15 | O5: 15 | P5: 15 | Q5: 15
A6: Cantidad DCU | B6: 0 | C6: 0 | D6: 0 | E6: 0 | F6: 0 | G6: 0 | H6: 0 | I6: 0 | J6: 0 | K6: 0 | L6: 0 | M6: 0 | N6: 0 | O6: 0 | P6: 0 | Q6: 0
A7: Inversión UM 1F [USD/equipo] | B7: 154.34667 | C7: 154.34667 | D7: 154.34667 | E7: 154.34667 | F7: 154.34667 | G7: 154.34667 | H7: 154.34667 | I7: 154.34667 | J7: 154.34667 | K7: 154.34667 | L7: 154.34667 | M7: 154.34667 | N7: 154.34667 | O7: 154.34667 | P7: 154.34667 | Q7: 154.34667
A8: Inversión UM 3F Directa [USD/equipo] | B8: 0 | C8: 0 | D8: 0 | E8: 0 | F8: 0 | G8: 0 | H8: 0 | I8: 0 | J8: 0 | K8: 0 | L8: 0 | M8: 0 | N8: 0 | O8: 0 | P8: 0 | Q8: 0
A9: Inversión UM 3F Indirecta [USD/equipo] | B9: 779.932 | C9: 779.932 | D9: 779.932 | E9: 779.932 | F9: 779.932 | G9: 779.932 | H9: 779.932 | I9: 779.932 | J9: 779.932 | K9: 779.932 | L9: 779.932 | M9: 779.932 | N9: 779.932 | O9: 779.932 | P9: 779.932 | Q9: 779.932
A10: Inversión DCU [USD/equipo] | B10: 0 | C10: 0 | D10: 0 | E10: 0 | F10: 0 | G10: 0 | H10: 0 | I10: 0 | J10: 0 | K10: 0 | L10: 0 | M10: 0 | N10: 0 | O10: 0 | P10: 0 | Q10: 0
A11: Inversión SGO [USD] | B11: 659351.43 | C11: 293.616 | D11: 293.616 | E11: 293.616 | F11: 293.616 | G11: 293.616 | H11: 293.616 | I11: 293.616 | J11: 293.616 | K11: 293.616 | L11: 293.616 | M11: 293.616 | N11: 293.616 | O11: 293.616 | P11: 293.616 | Q11: 293.616
A12: Inversión MDMS [USD] | B12: 49545.579 | C12: 22.063158 | D12: 22.063158 | E12: 22.063158 | F12: 22.063158 | G12: 22.063158 | H12: 22.063158 | I12: 22.063158 | J12: 22.063158 | K12: 22.063158 | L12: 22.063158 | M12: 22.063158 | N12: 22.063158 | O12: 22.063158 | P12: 22.063158 | Q12: 22.063158
A13: Operación Comunicaciones [USD/año] | B13: 0 | C13: 0 | D13: 0 | E13: 0 | F13: 0 | G13: 0 | H13: 0 | I13: 0 | J13: 0 | K13: 0 | L13: 0 | M13: 0 | N13: 0 | O13: 0 | P13: 0 | Q13: 0
... A26: Ahorro por inversión evitada [USD/año] | B26: 2218209.9 | C26: 2219843.6 | D26: 2221522.9 | E26: 2246006.1 | F26: 2251273.6 | G26: 2254702.1 | H26: 2257170.5 | I26: 2259579.5 | J26: 2278256 | K26: 2283082.3 | L26: 2286904.2 | M26: 2290735.3 | N26: 2295278.1 | O26: 2302036.4 | P26: 2308814.5 | Q26: 2315612.6

Sheet Flujo SMI_Mixto_BAJA
B2: Escenario de implementación | G2: Supuestos y Consideraciones
B4: Densidad de clientes | D4: Tecnología | G4: Tasa de descuento | J4: 0.06 | K4: % | R4: Dólar | S4: 959.36 | T4: USD/$ | U4: 45946
B5: Alta | D5: Mixto_BAJA | G5: Vida útil del proyecto | J5: 15 | K5: años | R5: UF | S5: 39521.26 | T5: UF/$ | U5: 45946
B6: Media | D6: Mixto_BAJA | G6: Meta de despligue | J6: 3 | K6: años
B7: Baja | D7: Mixto_BAJA | G7: Objetivo de despligue UM 1F | J7: =(SUMIF($F$12:$U$12,"<="&$J$6,$F$17:$U$17)) / ($J$6) -> 1040.6667 | K7: UM/año | L7: ="Razonable para chile en torno a 1M y 1,5M por año." -> Razonable para chile en torno a 1M y 1,5M por año.
B8: Muy Baja | D8: Mixto_BAJA | G8: Objetivo de despligue UM 3F Directa | J8: =(SUMIF($F$12:$U$12,"<="&$J$6,$F$18:$U$18)) / ($J$6) -> 0 | K8: UM/año | L8: ="Razonable para chile en torno a 1M y 1,5M por año." -> Razonable para chile en torno a 1M y 1,5M por año.
B9: Extremadamente Baja | D9: Mixto_BAJA | G9: Objetivo de despligue UM 3F Indirecta | J9: =(SUMIF($F$12:$U$12,"<="&$J$6,$F$19:$U$19)) / ($J$6) -> 10952 | K9: UM/año | L9: ="Razonable para chile en torno a 1M y 1,5M por año." -> Razonable para chile en torno a 1M y 1,5M por año.
B12: Despligue SMI Chile | E12: Periodo | F12: 0 | G12: 1 | H12: 2 | I12: 3 | J12: 4 | K12: 5 | L12: 6 | M12: 7 | N12: 8 | O12: 9 | P12: 10 | Q12: 11 | R12: 12 | S12: 13 | T12: 14 | U12: 15
E13: Año | F13: 2025 | G13: 2026 | H13: 2027 | I13: 2028 | J13: 2029 | K13: 2030 | L13: 2031 | M13: 2032 | N13: 2033 | O13: 2034 | P13: 2035 | Q13: 2036 | R13: 2037 | S13: 2038 | T13: 2039 | U13: 2040
B15: Datos de despliegue | C15: Energía Facturada anual [GWh] | F15: =CB_SMI_Mixto_BAJA!B2/1000 -> 7398.8934 | G15: =CB_SMI_Mixto_BAJA!C2/1000 -> 7622.34 | H15: =CB_SMI_Mixto_BAJA!D2/1000 -> 7852.5346 | I15: =CB_SMI_Mixto_BAJA!E2/1000 -> 8089.6812 | J15: =CB_SMI_Mixto_BAJA!F2/1000 -> 8333.9895 | K15: =CB_SMI_Mixto_BAJA!G2/1000 -> 8585.676 | L15: =CB_SMI_Mixto_BAJA!H2/1000 -> 8844.9634 | M15: =CB_SMI_Mixto_BAJA!I2/1000 -> 9112.0813 | ... U15: =CB_SMI_Mixto_BAJA!Q2/1000 -> 11560.855
C17: UM 1F [N° Equipos] | F17: =CB_SMI_Mixto_BAJA!B3 -> 3119 | G17: =CB_SMI_Mixto_BAJA!C3 -> 1 | H17: =CB_SMI_Mixto_BAJA!D3 -> 1 | I17: =CB_SMI_Mixto_BAJA!E3 -> 1 | J17: =CB_SMI_Mixto_BAJA!F3 -> 1 | K17: =CB_SMI_Mixto_BAJA!G3 -> 1 | L17: =CB_SMI_Mixto_BAJA!H3 -> 1 | M17: =CB_SMI_Mixto_BAJA!I3 -> 1 | ... U17: =CB_SMI_Mixto_BAJA!Q3 -> 1
C18: UM 3F Directa [N° Equipos] | F18: =CB_SMI_Mixto_BAJA!B4 -> 0 | G18: =CB_SMI_Mixto_BAJA!C4 -> 0 | H18: =CB_SMI_Mixto_BAJA!D4 -> 0 | I18: =CB_SMI_Mixto_BAJA!E4 -> 0 | J18: =CB_SMI_Mixto_BAJA!F4 -> 0 | K18: =CB_SMI_Mixto_BAJA!G4 -> 0 | L18: =CB_SMI_Mixto_BAJA!H4 -> 0 | M18: =CB_SMI_Mixto_BAJA!I4 -> 0 | ... U18: =CB_SMI_Mixto_BAJA!Q4 -> 0
C19: UM 3F Indirecta [N° Equipos] | F19: =CB_SMI_Mixto_BAJA!B5 -> 32811 | G19: =CB_SMI_Mixto_BAJA!C5 -> 15 | H19: =CB_SMI_Mixto_BAJA!D5 -> 15 | I19: =CB_SMI_Mixto_BAJA!E5 -> 15 | J19: =CB_SMI_Mixto_BAJA!F5 -> 15 | K19: =CB_SMI_Mixto_BAJA!G5 -> 15 | L19: =CB_SMI_Mixto_BAJA!H5 -> 15 | M19: =CB_SMI_Mixto_BAJA!I5 -> 15 | ... U19: =CB_SMI_Mixto_BAJA!Q5 -> 15
B21: Despliegue | C21: UM 1F instalados | F21: 0 | G21: =IF(G$12<=$J$6,$J7,G17) -> 1040.6667 | H21: =IF(H$12<=$J$6,$J7,H17) -> 1040.6667 | I21: =IF(I$12<=$J$6,$J7,I17) -> 1040.6667 | J21: =IF(J$12<=$J$6,$J7,J17) -> 1 | K21: =IF(K$12<=$J$6,$J7,K17) -> 1 | L21: =IF(L$12<=$J$6,$J7,L17) -> 1 | M21: =IF(M$12<=$J$6,$J7,M17) -> 1 | N21: =IF(N$12<=$J$6,$J7,N17) -> 1 | ... U21: =IF(U$12<=$J$6,$J7,U17) -> 1
C22: UM 3F Directa instalados | F22: 0 | G22: =IF(G$12<=$J$6,$J8,G18) -> 0 | H22: =IF(H$12<=$J$6,$J8,H18) -> 0 | I22: =IF(I$12<=$J$6,$J8,I18) -> 0 | J22: =IF(J$12<=$J$6,$J8,J18) -> 0 | K22: =IF(K$12<=$J$6,$J8,K18) -> 0 | L22: =IF(L$12<=$J$6,$J8,L18) -> 0 | M22: =IF(M$12<=$J$6,$J8,M18) -> 0 | N22: =IF(N$12<=$J$6,$J8,N18) -> 0 | ... U22: =IF(U$12<=$J$6,$J8,U18) -> 0
C23: UM 3F Indirecta instalados | F23: 0 | G23: =IF(G$12<=$J$6,$J9,G19) -> 10952 | H23: =IF(H$12<=$J$6,$J9,H19) -> 10952 | I23: =IF(I$12<=$J$6,$J9,I19) -> 10952 | J23: =IF(J$12<=$J$6,$J9,J19) -> 15 | K23: =IF(K$12<=$J$6,$J9,K19) -> 15 | L23: =IF(L$12<=$J$6,$J9,L19) -> 15 | M23: =IF(M$12<=$J$6,$J9,M19) -> 15 | N23: =IF(N$12<=$J$6,$J9,N19) -> 15 | ... U23: =IF(U$12<=$J$6,$J9,U19) -> 15
C24: UM faltantes por instalar | F24: =SUM(F17:F19) -> 35930 | G24: =SUM(F24,G17:G19)-SUM(G21:G23) -> 23953.333 | H24: =SUM(G24,H17:H19)-SUM(H21:H23) -> 11976.667 | I24: =SUM(H24,I17:I19)-SUM(I21:I23) -> 0 | J24: =SUM(I24,J17:J19)-SUM(J21:J23) -> 0 | K24: =SUM(J24,K17:K19)-SUM(K21:K23) -> 0 | L24: =SUM(K24,L17:L19)-SUM(L21:L23) -> 0 | M24: =SUM(L24,M17:M19)-SUM(M21:M23) -> 0 | N24: =SUM(M24,N17:N19)-SUM(N21:N23) -> 0 | ... U24: =SUM(T24,U17:U19)-SUM(U21:U23) -> 0
C25: % de avance | F25: 0 | G25: =IF(G$12<=$J$6,SUM($F$21:G23)/SUM($F$17:G19),1) -> 0.33363007 | H25: =IF(H$12<=$J$6,SUM($F$21:H23)/SUM($F$17:H19),1) -> 0.66696328 | I25: =IF(I$12<=$J$6,SUM($F$21:I23)/SUM($F$17:I19),1) -> 1 | J25: =IF(J$12<=$J$6,SUM($F$21:J23)/SUM($F$17:J19),1) -> 1 | K25: =IF(K$12<=$J$6,SUM($F$21:K23)/SUM($F$17:K19),1) -> 1 | L25: =IF(L$12<=$J$6,SUM($F$21:L23)/SUM($F$17:L19),1) -> 1 | M25: =IF(M$12<=$J$6,SUM($F$21:M23)/SUM($F$17:M19),1) -> 1 | N25: =IF(N$12<=$J$6,SUM($F$21:N23)/SUM($F$17:N19),1) -> 1 | ... U25: =IF(U$12<=$J$6,SUM($F$21:U23)/SUM($F$17:U19),1) -> 1
B27: Flujo de caja [MUSD] | E27: Periodo | F27: 0 | G27: 1 | H27: 2 | I27: 3 | J27: 4 | K27: 5 | L27: 6 | M27: 7 | N27: 8 | O27: 9 | P27: 10 | Q27: 11 | R27: 12 | S27: 13 | T27: 14 | U27: 15
E28: Año | F28: 2025 | G28: 2026 | H28: 2027 | I28: 2028 | J28: 2029 | K28: 2030 | L28: 2031 | M28: 2032 | N28: 2033 | O28: 2034 | P28: 2035 | Q28: 2036 | R28: 2037 | S28: 2038 | T28: 2039 | U28: 2040 | W28: VAN [MUSD] | X28: AVAN [MUSD] | Y28: VAN [USD/# Clientes] | Z28: Participación %
B30: VI [MUSD] | C30: UM 1F | F30: 0 | G30: =((-CB_SMI_Mixto_BAJA!C7)*G21)/1000000 -> -0.16062343 | H30: =((-CB_SMI_Mixto_BAJA!D7)*H21)/1000000 -> -0.16062343 | I30: =((-CB_SMI_Mixto_BAJA!E7)*I21)/1000000 -> -0.16062343 | J30: =((-CB_SMI_Mixto_BAJA!F7)*J21)/1000000 -> -0.00015434667 | K30: =((-CB_SMI_Mixto_BAJA!G7)*K21)/1000000 -> -0.00015434667 | L30: =((-CB_SMI_Mixto_BAJA!H7)*L21)/1000000 -> -0.00015434667 | M30: =((-CB_SMI_Mixto_BAJA!I7)*M21)/1000000 -> -0.00015434667 | N30: =((-CB_SMI_Mixto_BAJA!J7)*N21)/1000000 -> -0.00015434667 | ... U30: =((-CB_SMI_Mixto_BAJA!Q7)*U21)/1000000 -> -0.00015434667 | W30: =NPV($D$67,G30:U30)+F30 -> -0.43043483 | X30: =PMT($D$67,15,-W30) -> -0.04431876 | Y30: =W30*1000000/7744865 -> -0.055576803 | Z30: =W30/$W$36 -> 0.017892198
C31: UM 3F Directa | F31: 0 | G31: =((-CB_SMI_Mixto_BAJA!C8)*G22)/1000000 -> 0 | H31: =((-CB_SMI_Mixto_BAJA!D8)*H22)/1000000 -> 0 | I31: =((-CB_SMI_Mixto_BAJA!E8)*I22)/1000000 -> 0 | J31: =((-CB_SMI_Mixto_BAJA!F8)*J22)/1000000 -> 0 | K31: =((-CB_SMI_Mixto_BAJA!G8)*K22)/1000000 -> 0 | L31: =((-CB_SMI_Mixto_BAJA!H8)*L22)/1000000 -> 0 | M31: =((-CB_SMI_Mixto_BAJA!I8)*M22)/1000000 -> 0 | N31: =((-CB_SMI_Mixto_BAJA!J8)*N22)/1000000 -> 0 | ... U31: =((-CB_SMI_Mixto_BAJA!Q8)*U22)/1000000 -> 0 | W31: =NPV($D$67,G31:U31)+F31 -> 0 | X31: =PMT($D$67,15,-W31) -> 0 | Y31: =W31*1000000/7744865 -> 0 | Z31: =W31/$W$36 -> 0
C32: UM 3F Indirecta | F32: 0 | G32: =((-CB_SMI_Mixto_BAJA!C9)*G23)/1000000 -> -8.5418153 | H32: =((-CB_SMI_Mixto_BAJA!D9)*H23)/1000000 -> -8.5418153 | I32: =((-CB_SMI_Mixto_BAJA!E9)*I23)/1000000 -> -8.5418153 | J32: =((-CB_SMI_Mixto_BAJA!F9)*J23)/1000000 -> -0.01169898 | K32: =((-CB_SMI_Mixto_BAJA!G9)*K23)/1000000 -> -0.01169898 | L32: =((-CB_SMI_Mixto_BAJA!H9)*L23)/1000000 -> -0.01169898 | M32: =((-CB_SMI_Mixto_BAJA!I9)*M23)/1000000 -> -0.01169898 | N32: =((-CB_SMI_Mixto_BAJA!J9)*N23)/1000000 -> -0.01169898 | ... U32: =((-CB_SMI_Mixto_BAJA!Q9)*U23)/1000000 -> -0.01169898 | W32: =NPV($D$67,G32:U32)+F32 -> -22.914726 | X32: =PMT($D$67,15,-W32) -> -2.3593635 | Y32: =W32*1000000/7744865 -> -2.9586992 | Z32: =W32/$W$36 -> 0.95251312
C33: DCU | F33: =((-CB_SMI_Mixto_BAJA!B10)*CB_SMI_Mixto_BAJA!B6)/1000000 -> 0 | G33: =((-CB_SMI_Mixto_BAJA!C10)*CB_SMI_Mixto_BAJA!C6)/1000000 -> 0 | H33: =((-CB_SMI_Mixto_BAJA!D10)*CB_SMI_Mixto_BAJA!D6)/1000000 -> 0 | I33: =((-CB_SMI_Mixto_BAJA!E10)*CB_SMI_Mixto_BAJA!E6)/1000000 -> 0 | J33: =((-CB_SMI_Mixto_BAJA!F10)*CB_SMI_Mixto_BAJA!F6)/1000000 -> 0 | K33: =((-CB_SMI_Mixto_BAJA!G10)*CB_SMI_Mixto_BAJA!G6)/1000000 -> 0 | L33: =((-CB_SMI_Mixto_BAJA!H10)*CB_SMI_Mixto_BAJA!H6)/1000000 -> 0 | M33: =((-CB_SMI_Mixto_BAJA!I10)*CB_SMI_Mixto_BAJA!I6)/1000000 -> 0 | ... U33: =((-CB_SMI_Mixto_BAJA!Q10)*CB_SMI_Mixto_BAJA!Q6)/1000000 -> 0 | W33: =NPV($D$67,G33:U33)+F33 -> 0 | X33: =PMT($D$67,15,-W33) -> 0 | Y33: =W33*1000000/7744865 -> 0 | Z33: =W33/$W$36 -> 0
C34: HES | F34: =(-CB_SMI_Mixto_BAJA!B11)/1000000 -> -0.65935143 | G34: =(-CB_SMI_Mixto_BAJA!C11)/1000000 -> -0.000293616 | H34: =(-CB_SMI_Mixto_BAJA!D11)/1000000 -> -0.000293616 | I34: =(-CB_SMI_Mixto_BAJA!E11)/1000000 -> -0.000293616 | J34: =(-CB_SMI_Mixto_BAJA!F11)/1000000 -> -0.000293616 | K34: =(-CB_SMI_Mixto_BAJA!G11)/1000000 -> -0.000293616 | L34: =(-CB_SMI_Mixto_BAJA!H11)/1000000 -> -0.000293616 | M34: =(-CB_SMI_Mixto_BAJA!I11)/1000000 -> -0.000293616 | ... U34: =(-CB_SMI_Mixto_BAJA!Q11)/1000000 -> -0.000293616 | W34: =NPV($D$67,G34:U34)+F34 -> -0.6622031 | X34: =PMT($D$67,15,-W34) -> -0.068182262 | Y34: =W34*1000000/7744865 -> -0.085502214 | Z34: =W34/$W$36 -> 0.027526279
C35: MDMS | F35: =(-CB_SMI_Mixto_BAJA!B12)/1000000 -> -0.049545579 | G35: =(-CB_SMI_Mixto_BAJA!C12)/1000000 -> -2.2063158e-05 | H35: =(-CB_SMI_Mixto_BAJA!D12)/1000000 -> -2.2063158e-05 | I35: =(-CB_SMI_Mixto_BAJA!E12)/1000000 -> -2.2063158e-05 | J35: =(-CB_SMI_Mixto_BAJA!F12)/1000000 -> -2.2063158e-05 | K35: =(-CB_SMI_Mixto_BAJA!G12)/1000000 -> -2.2063158e-05 | L35: =(-CB_SMI_Mixto_BAJA!H12)/1000000 -> -2.2063158e-05 | M35: =(-CB_SMI_Mixto_BAJA!I12)/1000000 -> -2.2063158e-05 | ... U35: =(-CB_SMI_Mixto_BAJA!Q12)/1000000 -> -2.2063158e-05 | W35: =NPV($D$67,G35:U35)+F35 -> -0.049759862 | X35: =PMT($D$67,15,-W35) -> -0.0051234129 | Y35: =W35*1000000/7744865 -> -0.0064248843 | Z35: =W35/$W$36 -> 0.0020684044
C36: VI Total: | F36: =SUM(F30:F35) -> -0.70889701 | G36: =SUM(G30:G35) -> -8.7027544 | H36: =SUM(H30:H35) -> -8.7027544 | I36: =SUM(I30:I35) -> -8.7027544 | J36: =SUM(J30:J35) -> -0.012169006 | K36: =SUM(K30:K35) -> -0.012169006 | L36: =SUM(L30:L35) -> -0.012169006 | M36: =SUM(M30:M35) -> -0.012169006 | ... U36: =SUM(U30:U35) -> -0.012169006 | W36: =NPV($D$67,G36:U36)+F36 -> -24.057124 | X36: =PMT($D$67,15,-W36) -> -2.476988 | Y36: =W36*1000000/7744865 -> -3.1062031 | Z36: =W36/$W$36 -> 1
B38: COMA [MUSD] | C38: Operación Comunicaciones UM - SGO | F38: 0 | G38: =(-CB_SMI_Mixto_BAJA!C13/1000000)*G$25 -> 0 | H38: =(-CB_SMI_Mixto_BAJA!D13/1000000)*H$25 -> 0 | I38: =(-CB_SMI_Mixto_BAJA!E13/1000000)*I$25 -> 0 | J38: =(-CB_SMI_Mixto_BAJA!F13/1000000)*J$25 -> 0 | K38: =(-CB_SMI_Mixto_BAJA!G13/1000000)*K$25 -> 0 | L38: =(-CB_SMI_Mixto_BAJA!H13/1000000)*L$25 -> 0 | M38: =(-CB_SMI_Mixto_BAJA!I13/1000000)*M$25 -> 0 | N38: =(-CB_SMI_Mixto_BAJA!J13/1000000)*N$25 -> 0 | ... U38: =(-CB_SMI_Mixto_BAJA!Q13/1000000)*U$25 -> 0 | W38: =NPV($D$67,G38:U38)+F38 -> 0 | X38: =PMT($D$67,15,-W38) -> 0 | Y38: =W38*1000000/7744865 -> 0 | Z38: =W38/$W$43 -> 0
C39: Operación Comunicaciones DCU - SGO | F39: 0 | G39: =(-CB_SMI_Mixto_BAJA!C14/1000000)*G$25 -> -0.20152147 | H39: =(-CB_SMI_Mixto_BAJA!D14/1000000)*H$25 -> -0.40286362 | I39: =(-CB_SMI_Mixto_BAJA!E14/1000000)*I$25 -> -0.60402668 | J39: =(-CB_SMI_Mixto_BAJA!F14/1000000)*J$25 -> -0.60402668 | K39: =(-CB_SMI_Mixto_BAJA!G14/1000000)*K$25 -> -0.60402668 | L39: =(-CB_SMI_Mixto_BAJA!H14/1000000)*L$25 -> -0.60402668 | M39: =(-CB_SMI_Mixto_BAJA!I14/1000000)*M$25 -> -0.60402668 | N39: =(-CB_SMI_Mixto_BAJA!J14/1000000)*N$25 -> -0.60402668 | ... U39: =(-CB_SMI_Mixto_BAJA!Q14/1000000)*U$25 -> -0.60402668 | W39: =NPV($D$67,G39:U39)+F39 -> -5.3077012 | X39: =PMT($D$67,15,-W39) -> -0.54649559 | Y39: =W39*1000000/7744865 -> -0.68531875 | Z39: =W39/$W$43 -> 0.6179103
C40: Operación HES | F40: 0 | G40: =(-CB_SMI_Mixto_BAJA!C15/1000000)*G$25 -> -0.095765324 | H40: =(-CB_SMI_Mixto_BAJA!D15/1000000)*H$25 -> -0.19153065 | I40: =(-CB_SMI_Mixto_BAJA!E15/1000000)*I$25 -> -0.28729597 | J40: =(-CB_SMI_Mixto_BAJA!F15/1000000)*J$25 -> -0.28742374 | K40: =(-CB_SMI_Mixto_BAJA!G15/1000000)*K$25 -> -0.2875515 | L40: =(-CB_SMI_Mixto_BAJA!H15/1000000)*L$25 -> -0.28767927 | M40: =(-CB_SMI_Mixto_BAJA!I15/1000000)*M$25 -> -0.28780703 | N40: =(-CB_SMI_Mixto_BAJA!J15/1000000)*N$25 -> -0.2879348 | ... U40: =(-CB_SMI_Mixto_BAJA!Q15/1000000)*U$25 -> -0.28882915 | W40: =NPV($D$67,G40:U40)+F40 -> -2.5295964 | X40: =PMT($D$67,15,-W40) -> -0.26045424 | Y40: =W40*1000000/7744865 -> -0.32661594 | Z40: =W40/$W$43 -> 0.29448976
C41: Operación MDMS | F41: 0 | G41: =(-CB_SMI_Mixto_BAJA!C16/1000000)*G$25 -> -0.013591794 | H41: =(-CB_SMI_Mixto_BAJA!D16/1000000)*H$25 -> -0.027183588 | I41: =(-CB_SMI_Mixto_BAJA!E16/1000000)*I$25 -> -0.040775382 | J41: =(-CB_SMI_Mixto_BAJA!F16/1000000)*J$25 -> -0.040793516 | K41: =(-CB_SMI_Mixto_BAJA!G16/1000000)*K$25 -> -0.040811649 | L41: =(-CB_SMI_Mixto_BAJA!H16/1000000)*L$25 -> -0.040829783 | M41: =(-CB_SMI_Mixto_BAJA!I16/1000000)*M$25 -> -0.040847916 | N41: =(-CB_SMI_Mixto_BAJA!J16/1000000)*N$25 -> -0.04086605 | ... U41: =(-CB_SMI_Mixto_BAJA!Q16/1000000)*U$25 -> -0.040992984 | W41: =NPV($D$67,G41:U41)+F41 -> -0.35902091 | X41: =PMT($D$67,15,-W41) -> -0.036965785 | Y41: =W41*1000000/7744865 -> -0.046355993 | Z41: =W41/$W$43 -> 0.041796383
C42: SyM Equipos | F42: 0 | G42: =(-CB_SMI_Mixto_BAJA!C17/1000000)*G$25 -> -0.014894892 | H42: =(-CB_SMI_Mixto_BAJA!D17/1000000)*H$25 -> -0.029789784 | I42: =(-CB_SMI_Mixto_BAJA!E17/1000000)*I$25 -> -0.044684676 | J42: =(-CB_SMI_Mixto_BAJA!F17/1000000)*J$25 -> -0.044704548 | K42: =(-CB_SMI_Mixto_BAJA!G17/1000000)*K$25 -> -0.04472442 | L42: =(-CB_SMI_Mixto_BAJA!H17/1000000)*L$25 -> -0.044744292 | M42: =(-CB_SMI_Mixto_BAJA!I17/1000000)*M$25 -> -0.044764164 | N42: =(-CB_SMI_Mixto_BAJA!J17/1000000)*N$25 -> -0.044784036 | ... U42: =(-CB_SMI_Mixto_BAJA!Q17/1000000)*U$25 -> -0.04492314 | W42: =NPV($D$67,G42:U42)+F42 -> -0.39344163 | X42: =PMT($D$67,15,-W42) -> -0.040509838 | Y42: =W42*1000000/7744865 -> -0.050800321 | Z42: =W42/$W$43 -> 0.045803564
C43: COMA Total: | F43: =SUM(F38:F42) -> 0 | G43: =SUM(G38:G42) -> -0.32577348 | H43: =SUM(H38:H42) -> -0.65136764 | I43: =SUM(I38:I42) -> -0.97678271 | J43: =SUM(J38:J42) -> -0.97694848 | K43: =SUM(K38:K42) -> -0.97711425 | L43: =SUM(L38:L42) -> -0.97728003 | M43: =SUM(M38:M42) -> -0.9774458 | ... U43: =SUM(U38:U42) -> -0.97877196 | W43: =NPV($D$67,G43:U43)+F43 -> -8.5897602 | X43: =PMT($D$67,15,-W43) -> -0.88442545 | Y43: =W43*1000000/7744865 -> -1.109091 | Z43: =W43/$W$43 -> 1
B45: Costos Totales (VI + COMA) | F45: =F36+F43 -> -0.70889701 | G45: =G36+G43 -> -9.0285279 | H45: =H36+H43 -> -9.354122 | I45: =I36+I43 -> -9.6795371 | J45: =J36+J43 -> -0.98911749 | K45: =K36+K43 -> -0.98928326 | L45: =L36+L43 -> -0.98944903 | M45: =M36+M43 -> -0.9896148 | ... U45: =U36+U43 -> -0.99094097 | W45: =NPV($D$67,G45:U45)+F45 -> -32.646884 | X45: =PMT($D$67,15,-W45) -> -3.3614134 | Y45: =W45*1000000/7744865 -> -4.2152941
B47: Beneficios [MUSD] | C47: Ahorro de lectura pedestre | F47: 0 | G47: =(CB_SMI_Mixto_BAJA!C18/1000000)*G$25 -> 0 | H47: =(CB_SMI_Mixto_BAJA!D18/1000000)*H$25 -> 0 | I47: =(CB_SMI_Mixto_BAJA!E18/1000000)*I$25 -> 0 | J47: =(CB_SMI_Mixto_BAJA!F18/1000000)*J$25 -> 0 | K47: =(CB_SMI_Mixto_BAJA!G18/1000000)*K$25 -> 0 | L47: =(CB_SMI_Mixto_BAJA!H18/1000000)*L$25 -> 0 | M47: =(CB_SMI_Mixto_BAJA!I18/1000000)*M$25 -> 0 | N47: =(CB_SMI_Mixto_BAJA!J18/1000000)*N$25 -> 0 | ... U47: =(CB_SMI_Mixto_BAJA!Q18/1000000)*U$25 -> 0 | V47: =U47/$U$56 -> 0 | W47: =NPV($D$67,G47:U47)+F47 -> 0 | X47: =PMT($D$67,15,-W47) -> 0 | Y47: =W47*1000000/7744865 -> 0 | Z47: =W47/$W$56 -> 0
C48: Corte y Reposición remoto | F48: 0 | G48: =(CB_SMI_Mixto_BAJA!C19/1000000)*G$25 -> 0 | H48: =(CB_SMI_Mixto_BAJA!D19/1000000)*H$25 -> 0 | I48: =(CB_SMI_Mixto_BAJA!E19/1000000)*I$25 -> 0 | J48: =(CB_SMI_Mixto_BAJA!F19/1000000)*J$25 -> 0 | K48: =(CB_SMI_Mixto_BAJA!G19/1000000)*K$25 -> 0 | L48: =(CB_SMI_Mixto_BAJA!H19/1000000)*L$25 -> 0 | M48: =(CB_SMI_Mixto_BAJA!I19/1000000)*M$25 -> 0 | N48: =(CB_SMI_Mixto_BAJA!J19/1000000)*N$25 -> 0 | ... U48: =(CB_SMI_Mixto_BAJA!Q19/1000000)*U$25 -> 0 | V48: =U48/$U$56 -> 0 | W48: =NPV($D$67,G48:U48)+F48 -> 0 | X48: =PMT($D$67,15,-W48) -> 0 | Y48: =W48*1000000/7744865 -> 0 | Z48: =W48/$W$56 -> 0
C49: Reducción de Pérdidas No Técnicas | F49: 0 | G49: =(CB_SMI_Mixto_BAJA!C20/1000000)*G$25 -> 0 | H49: =(CB_SMI_Mixto_BAJA!D20/1000000)*H$25 -> 0 | I49: =(CB_SMI_Mixto_BAJA!E20/1000000)*I$25 -> 0 | J49: =(CB_SMI_Mixto_BAJA!F20/1000000)*J$25 -> 0 | K49: =(CB_SMI_Mixto_BAJA!G20/1000000)*K$25 -> 0 | L49: =(CB_SMI_Mixto_BAJA!H20/1000000)*L$25 -> 0 | M49: =(CB_SMI_Mixto_BAJA!I20/1000000)*M$25 -> 0 | N49: =(CB_SMI_Mixto_BAJA!J20/1000000)*N$25 -> 0 | ... U49: =(CB_SMI_Mixto_BAJA!Q20/1000000)*U$25 -> 0 | V49: =U49/$U$56 -> 0 | W49: =NPV($D$67,G49:U49)+F49 -> 0 | X49: =PMT($D$67,15,-W49) -> 0 | Y49: =W49*1000000/7744865 -> 0 | Z49: =W49/$W$56 -> 0
C50: Reducción del tiempo de respuesta ante Fallas | F50: 0 | G50: =(CB_SMI_Mixto_BAJA!C21/1000000)*G$25 -> 0.25223419 | H50: =(CB_SMI_Mixto_BAJA!D21/1000000)*H$25 -> 0.50424393 | I50: =(CB_SMI_Mixto_BAJA!E21/1000000)*I$25 -> 0.75602953 | J50: =(CB_SMI_Mixto_BAJA!F21/1000000)*J$25 -> 0.75602953 | K50: =(CB_SMI_Mixto_BAJA!G21/1000000)*K$25 -> 0.75602953 | L50: =(CB_SMI_Mixto_BAJA!H21/1000000)*L$25 -> 0.75602953 | M50: =(CB_SMI_Mixto_BAJA!I21/1000000)*M$25 -> 0.75602953 | N50: =(CB_SMI_Mixto_BAJA!J21/1000000)*N$25 -> 0.75602953 | ... U50: =(CB_SMI_Mixto_BAJA!Q21/1000000)*U$25 -> 0.75602953 | V50: =U50/$U$56 -> 0.24613204 | W50: =NPV($D$67,G50:U50)+F50 -> 6.6433801 | X50: =PMT($D$67,15,-W50) -> 0.68402078 | Y50: =W50*1000000/7744865 -> 0.85777868 | Z50: =W50/$W$56 -> 0.24993494
C51: Reducción del costo de la energía en horas de Sol | F51: 0 | G51: =(CB_SMI_Mixto_BAJA!C22/1000000)*G$25 -> 0 | H51: =(CB_SMI_Mixto_BAJA!D22/1000000)*H$25 -> 0 | I51: =(CB_SMI_Mixto_BAJA!E22/1000000)*I$25 -> 0 | J51: =(CB_SMI_Mixto_BAJA!F22/1000000)*J$25 -> 0 | K51: =(CB_SMI_Mixto_BAJA!G22/1000000)*K$25 -> 0 | L51: =(CB_SMI_Mixto_BAJA!H22/1000000)*L$25 -> 0 | M51: =(CB_SMI_Mixto_BAJA!I22/1000000)*M$25 -> 0 | N51: =(CB_SMI_Mixto_BAJA!J22/1000000)*N$25 -> 0 | ... U51: =(CB_SMI_Mixto_BAJA!Q22/1000000)*U$25 -> 0 | V51: =U51/$U$56 -> 0 | W51: =NPV($D$67,G51:U51)+F51 -> 0 | X51: =PMT($D$67,15,-W51) -> 0 | Y51: =W51*1000000/7744865 -> 0 | Z51: =W51/$W$56 -> 0
C52: Reducción del consumo de Clientes Finales | F52: 0 | G52: =(CB_SMI_Mixto_BAJA!C23/1000000)*G$25 -> 0 | H52: =(CB_SMI_Mixto_BAJA!D23/1000000)*H$25 -> 0 | I52: =(CB_SMI_Mixto_BAJA!E23/1000000)*I$25 -> 0 | J52: =(CB_SMI_Mixto_BAJA!F23/1000000)*J$25 -> 0 | K52: =(CB_SMI_Mixto_BAJA!G23/1000000)*K$25 -> 0 | L52: =(CB_SMI_Mixto_BAJA!H23/1000000)*L$25 -> 0 | M52: =(CB_SMI_Mixto_BAJA!I23/1000000)*M$25 -> 0 | N52: =(CB_SMI_Mixto_BAJA!J23/1000000)*N$25 -> 0 | ... U52: =(CB_SMI_Mixto_BAJA!Q23/1000000)*U$25 -> 0 | V52: =U52/$U$56 -> 0 | W52: =NPV($D$67,G52:U52)+F52 -> 0 | X52: =PMT($D$67,15,-W52) -> 0 | Y52: =W52*1000000/7744865 -> 0 | Z52: =W52/$W$56 -> 0
C53: Reducción de emisiones de CO2 | F53: 0 | G53: =(CB_SMI_Mixto_BAJA!C24/1000000)*G$25 -> 0 | H53: =(CB_SMI_Mixto_BAJA!D24/1000000)*H$25 -> 0 | I53: =(CB_SMI_Mixto_BAJA!E24/1000000)*I$25 -> 0 | J53: =(CB_SMI_Mixto_BAJA!F24/1000000)*J$25 -> 0 | K53: =(CB_SMI_Mixto_BAJA!G24/1000000)*K$25 -> 0 | L53: =(CB_SMI_Mixto_BAJA!H24/1000000)*L$25 -> 0 | M53: =(CB_SMI_Mixto_BAJA!I24/1000000)*M$25 -> 0 | N53: =(CB_SMI_Mixto_BAJA!J24/1000000)*N$25 -> 0 | ... U53: =(CB_SMI_Mixto_BAJA!Q24/1000000)*U$25 -> 0 | V53: =U53/$U$56 -> 0 | W53: =NPV($D$67,G53:U53)+F53 -> 0 | X53: =PMT($D$67,15,-W53) -> 0 | Y53: =W53*1000000/7744865 -> 0 | Z53: =W53/$W$56 -> 0
C54: Reducción servicio Atención al Cliente | F54: 0 | G54: =(CB_SMI_Mixto_BAJA!C25/1000000)*G$25 -> 0 | H54: =(CB_SMI_Mixto_BAJA!D25/1000000)*H$25 -> 0 | I54: =(CB_SMI_Mixto_BAJA!E25/1000000)*I$25 -> 0 | J54: =(CB_SMI_Mixto_BAJA!F25/1000000)*J$25 -> 0 | K54: =(CB_SMI_Mixto_BAJA!G25/1000000)*K$25 -> 0 | L54: =(CB_SMI_Mixto_BAJA!H25/1000000)*L$25 -> 0 | M54: =(CB_SMI_Mixto_BAJA!I25/1000000)*M$25 -> 0 | N54: =(CB_SMI_Mixto_BAJA!J25/1000000)*N$25 -> 0 | ... U54: =(CB_SMI_Mixto_BAJA!Q25/1000000)*U$25 -> 0 | V54: =U54/$U$56 -> 0 | W54: =NPV($D$67,G54:U54)+F54 -> 0 | X54: =PMT($D$67,15,-W54) -> 0 | Y54: =W54*1000000/7744865 -> 0 | Z54: =W54/$W$56 -> 0
C55: Reducción en Inversión de infraestructura de red | F55: 0 | G55: =(CB_SMI_Mixto_BAJA!C26/1000000)*G$25 -> 0.7406066 | H55: =(CB_SMI_Mixto_BAJA!D26/1000000)*H$25 -> 1.4816742 | I55: =(CB_SMI_Mixto_BAJA!E26/1000000)*I$25 -> 2.2460061 | J55: =(CB_SMI_Mixto_BAJA!F26/1000000)*J$25 -> 2.2512736 | K55: =(CB_SMI_Mixto_BAJA!G26/1000000)*K$25 -> 2.2547021 | L55: =(CB_SMI_Mixto_BAJA!H26/1000000)*L$25 -> 2.2571705 | M55: =(CB_SMI_Mixto_BAJA!I26/1000000)*M$25 -> 2.2595795 | N55: =(CB_SMI_Mixto_BAJA!J26/1000000)*N$25 -> 2.278256 | ... U55: =(CB_SMI_Mixto_BAJA!Q26/1000000)*U$25 -> 2.3156126 | V55: =U55/$U$56 -> 0.75386796 | W55: =NPV($D$67,G55:U55)+F55 -> 19.937057 | X55: =PMT($D$67,15,-W55) -> 2.0527745 | Y55: =W55*1000000/7744865 -> 2.5742292 | Z55: =W55/$W$56 -> 0.75006506
C56: Beneficios Total: | F56: =SUM(F47:F55) -> 0 | G56: =SUM(G47:G55) -> 0.99284079 | H56: =SUM(H47:H55) -> 1.9859181 | I56: =SUM(I47:I55) -> 3.0020357 | J56: =SUM(J47:J55) -> 3.0073031 | K56: =SUM(K47:K55) -> 3.0107316 | L56: =SUM(L47:L55) -> 3.0132 | M56: =SUM(M47:M55) -> 3.015609 | ... U56: =SUM(U47:U55) -> 3.0716421 | W56: =NPV($D$67,G56:U56)+F56 -> 26.580438 | X56: =PMT($D$67,15,-W56) -> 2.7367953 | Y56: =W56*1000000/7744865 -> 3.4320079 | Z56: =W56/$W$56 -> 1
B58: Flujo | F58: =F45+F56 -> -0.70889701 | G58: =G45+G56 -> -8.0356871 | H58: =H45+H56 -> -7.3682039 | I58: =I45+I56 -> -6.6775014 | J58: =J45+J56 -> 2.0181856 | K58: =K45+K56 -> 2.0214484 | L58: =L45+L56 -> 2.023751 | M58: =M45+M56 -> 2.0259942 | ... U58: =U45+U56 -> 2.0807011
B60: Flujo del periodo anterior | F60: 0 | G60: =F61 -> -0.70889701 | H60: =G61 -> -8.7445841 | I60: =H61 -> -16.112788 | J60: =I61 -> -22.790289 | K60: =J61 -> -20.772104 | L60: =K61 -> -18.750655 | M60: =L61 -> -16.726904 | N60: =M61 -> -14.70091 | ... U60: =T61 -> -0.29554195
B61: Flujo Acumulado | F61: =F58+F60 -> -0.70889701 | G61: =G58+G60 -> -8.7445841 | H61: =H58+H60 -> -16.112788 | I61: =I58+I60 -> -22.790289 | J61: =J58+J60 -> -20.772104 | K61: =K58+K60 -> -18.750655 | L61: =L58+L60 -> -16.726904 | M61: =M58+M60 -> -14.70091 | ... U61: =U58+U60 -> 1.7851592
B63: Flujo descontado (6%) | F63: =F58/(1+0.06)^F27 -> -0.70889701 | G63: =G58/(1+0.06)^G27 -> -7.5808369 | H63: =H58/(1+0.06)^H27 -> -6.5576753 | I63: =I58/(1+0.06)^I27 -> -5.606559 | J63: =J58/(1+0.06)^J27 -> 1.598592 | K63: =K58/(1+0.06)^K27 -> 1.5105438 | L63: =L58/(1+0.06)^L27 -> 1.4266646 | M63: =M58/(1+0.06)^M27 -> 1.3474018 | ... U63: =U58/(1+0.06)^U27 -> 0.86820388
B64: Flujo Acumulado descontado (6%) | F64: =F63 -> -0.70889701 | G64: =F64+G63 -> -8.2897339 | H64: =G64+H63 -> -14.847409 | I64: =H64+I63 -> -20.453968 | J64: =I64+J63 -> -18.855376 | K64: =J64+K63 -> -17.344832 | L64: =K64+L63 -> -15.918168 | M64: =L64+M63 -> -14.570766 | N64: =M64+N63 -> -13.288018 | ... U64: =T64+U63 -> -6.0664466
B67: Tasa | D67: =J4 -> 0.06 | H67: Monto [MUSD] | J67: Monto [USD/cliente] | L67: Monto [$/cliente]
F68: VAN (Costos) | H68: =NPV(D67,G45:U45)+F45 -> -32.646884 | J68: =H68*1000000/$D$75 -> -27.822539 | L68: =J68*$S$4 -> -26691.831
B69: VAN | D69: =NPV(D67,G58:U58)+F58 -> -6.0664466 | F69: Anualidad (Costos) | H69: =PMT(D67,15,-H68) -> -3.3614134 | J69: =H69*1000000/$D$75 -> -2.8646855 | L69: =J69*$S$4 -> -2748.2647
B70: TIR | D70: =IRR(F58:U58) -> 0.0099713554 | F70: Mensualidad (Costos) | H70: =H69/12 -> -0.28011779 | J70: =J69/12 -> -0.2387238 | L70: =L69/12 -> -229.02206
B71: B/C | D71: =NPV(D67,G56:U56)/-(F36+NPV(D67,G36:U36)+NPV(D67,G43:U43)) -> 0.81417992
F72: VAN (Beneficios) | H72: =NPV(D67,G56:U56)+F56 -> 26.580438 | J72: =H72*1000000/$D$75 -> 22.652553 | L72: =J72*$S$4 -> 21731.953
B73: # Clientes Alta | D73: 2527114 | F73: Anualidad (Beneficios) | H73: =PMT(D67,15,-H72) -> 2.7367953 | J73: =H73*1000000/$D$75 -> 2.3323695 | L73: =J73*$S$4 -> 2237.582
B74: # Clientes Media | D74: 2158536 | F74: Mensualidad (Beneficios) | H74: =H73/12 -> 0.22806628 | J74: =J73/12 -> 0.19436412 | L74: =L73/12 -> 186.46516
B75: # Clientes Baja | D75: 1173397
B76: # Clientes Muy Baja | D76: 1288141 | F76: VAN (Neto) | H76: =H72+H68 -> -6.0664466 | J76: =H76*1000000/$D$75 -> -5.1699864 | L76: =J76*$S$4 -> -4959.8782
B77: # Clientes Ext. Baja | D77: 593823 | F77: Anualidad (Neto) | H77: =PMT(D67,15,-H76) -> -0.62461811 | J77: =H77*1000000/$D$75 -> -0.53231609 | L77: =J77*$S$4 -> -510.68277
F78: Mensualidad (Neto) | H78: =H77/12 -> -0.052051509 | J78: =J77/12 -> -0.044359674 | L78: =L77/12 -> -42.556897
B79: # Clientes Regulados | D79: =SUM(D73:D77) -> 7741011

Sheet CB_SMI_Mixto_MUY_BAJA
A1: Concepto | B1: Periodo 0 | C1: Periodo 1 | D1: Periodo 2 | E1: Periodo 3 | F1: Periodo 4 | G1: Periodo 5 | H1: Periodo 6 | I1: Periodo 7 | J1: Periodo 8 | K1: Periodo 9 | L1: Periodo 10 | M1: Periodo 11 | N1: Periodo 12 | O1: Periodo 13 | P1: Periodo 14 | Q1: Periodo 15
A2: Energía facturada anual [MWh/año] | B2: 4883809.7 | C2: 5031300.8 | D2: 5183246.1 | E2: 5339780.1 | F2: 5501041.5 | G2: 5667172.9 | H2: 5838321.5 | I2: 6014638.8 | J2: 6196280.9 | K2: 6383408.6 | L2: 6576187.6 | M2: 6774788.4 | N2: 6979387 | O2: 7190164.5 | P2: 7407307.5 | Q2: 7631008.2
A3: Cantidad UM 1F | B3: 8294 | C3: 45 | D3: 45 | E3: 45 | F3: 45 | G3: 46 | H3: 46 | I3: 46 | J3: 46 | K3: 46 | L3: 46 | M3: 46 | N3: 46 | O3: 47 | P3: 48 | Q3: 48
A4: Cantidad UM 3F Directa | B4: 0 | C4: 0 | D4: 0 | E4: 0 | F4: 0 | G4: 0 | H4: 0 | I4: 0 | J4: 0 | K4: 0 | L4: 0 | M4: 0 | N4: 0 | O4: 0 | P4: 0 | Q4: 0
A5: Cantidad UM 3F Indirecta | B5: 54202 | C5: 340 | D5: 340 | E5: 341 | F5: 343 | G5: 350 | H5: 350 | I5: 353 | J5: 353 | K5: 353 | L5: 353 | M5: 356 | N5: 360 | O5: 363 | P5: 365 | Q5: 367
A6: Cantidad DCU | B6: 0 | C6: 0 | D6: 0 | E6: 0 | F6: 0 | G6: 0 | H6: 0 | I6: 0 | J6: 0 | K6: 0 | L6: 0 | M6: 0 | N6: 0 | O6: 0 | P6: 0 | Q6: 0
A7: Inversión UM 1F [USD/equipo] | B7: 185.43492 | C7: 185.43492 | D7: 185.43492 | E7: 185.43492 | F7: 185.43492 | G7: 185.43492 | H7: 185.43492 | I7: 185.43492 | J7: 185.43492 | K7: 185.43492 | L7: 185.43492 | M7: 185.43492 | N7: 185.43492 | O7: 185.43492 | P7: 185.43492 | Q7: 185.43492
A8: Inversión UM 3F Directa [USD/equipo] | B8: 0 | C8: 0 | D8: 0 | E8: 0 | F8: 0 | G8: 0 | H8: 0 | I8: 0 | J8: 0 | K8: 0 | L8: 0 | M8: 0 | N8: 0 | O8: 0 | P8: 0 | Q8: 0
A9: Inversión UM 3F Indirecta [USD/equipo] | B9: 779.84692 | C9: 779.84692 | D9: 779.84692 | E9: 779.84692 | F9: 779.84692 | G9: 779.84692 | H9: 779.84692 | I9: 779.84692 | J9: 779.84692 | K9: 779.84692 | L9: 779.84692 | M9: 779.84692 | N9: 779.84692 | O9: 779.84692 | P9: 779.84692 | Q9: 779.84692
A10: Inversión DCU [USD/equipo] | B10: 0 | C10: 0 | D10: 0 | E10: 0 | F10: 0 | G10: 0 | H10: 0 | I10: 0 | J10: 0 | K10: 0 | L10: 0 | M10: 0 | N10: 0 | O10: 0 | P10: 0 | Q10: 0
A11: Inversión SGO [USD] | B11: 1146864.1 | C11: 7065.135 | D11: 7065.135 | E11: 7083.486 | F11: 7120.188 | G11: 7266.996 | H11: 7266.996 | I11: 7322.049 | J11: 7322.049 | K11: 7322.049 | L11: 7322.049 | M11: 7377.102 | N11: 7450.506 | O11: 7523.91 | P11: 7578.963 | Q11: 7615.665
A12: Inversión MDMS [USD] | B12: 86178.695 | C12: 530.89474 | D12: 530.89474 | E12: 532.27368 | F12: 535.03158 | G12: 546.06316 | H12: 546.06316 | I12: 550.2 | J12: 550.2 | K12: 550.2 | L12: 550.2 | M12: 554.33684 | N12: 559.85263 | O12: 565.36842 | P12: 569.50526 | Q12: 572.26316
A13: Operación Comunicaciones [USD/año] | B13: 0 | C13: 0 | D13: 0 | E13: 0 | F13: 0 | G13: 0 | H13: 0 | I13: 0 | J13: 0 | K13: 0 | L13: 0 | M13: 0 | N13: 0 | O13: 0 | P13: 0 | Q13: 0
... A26: Ahorro por inversión evitada [USD/año] | B26: 4572228.6 | C26: 4575596.1 | D26: 4579057.3 | E26: 4629522.8 | F26: 4640380.2 | G26: 4647447.2 | H26: 4652535.2 | I26: 4657500.5 | J26: 4695997.1 | K26: 4705945.2 | L26: 4713822.9 | M26: 4721719.6 | N26: 4731083.5 | O26: 4745013.7 | P26: 4758985 | Q26: 4772997.3

Sheet Flujo SMI_Mixto_MUY_BAJA
B2: Escenario de implementación | G2: Supuestos y Consideraciones
B4: Densidad de clientes | D4: Tecnología | G4: Tasa de descuento | J4: 0.06 | K4: % | R4: Dólar | S4: 959.36 | T4: USD/$ | U4: 45946
B5: Alta | D5: Mixto_MUY_BAJA | G5: Vida útil del proyecto | J5: 15 | K5: años | R5: UF | S5: 39521.26 | T5: UF/$ | U5: 45946
B6: Media | D6: Mixto_MUY_BAJA | G6: Meta de despligue | J6: 3 | K6: años
B7: Baja | D7: Mixto_MUY_BAJA | G7: Objetivo de despligue UM 1F | J7: =(SUMIF($F$12:$U$12,"<="&$J$6,$F$17:$U$17)) / ($J$6) -> 2809.6667 | K7: UM/año | L7: ="Razonable para chile en torno a 1M y 1,5M por año." -> Razonable para chile en torno a 1M y 1,5M por año.
B8: Muy Baja | D8: Mixto_MUY_BAJA | G8: Objetivo de despligue UM 3F Directa | J8: =(SUMIF($F$12:$U$12,"<="&$J$6,$F$18:$U$18)) / ($J$6) -> 0 | K8: UM/año | L8: ="Razonable para chile en torno a 1M y 1,5M por año." -> Razonable para chile en torno a 1M y 1,5M por año.
B9: Extremadamente Baja | D9: Mixto_MUY_BAJA | G9: Objetivo de despligue UM 3F Indirecta | J9: =(SUMIF($F$12:$U$12,"<="&$J$6,$F$19:$U$19)) / ($J$6) -> 18407.667 | K9: UM/año | L9: ="Razonable para chile en torno a 1M y 1,5M por año." -> Razonable para chile en torno a 1M y 1,5M por año.
B12: Despligue SMI Chile | E12: Periodo | F12: 0 | G12: 1 | H12: 2 | I12: 3 | J12: 4 | K12: 5 | L12: 6 | M12: 7 | N12: 8 | O12: 9 | P12: 10 | Q12: 11 | R12: 12 | S12: 13 | T12: 14 | U12: 15
E13: Año | F13: 2025 | G13: 2026 | H13: 2027 | I13: 2028 | J13: 2029 | K13: 2030 | L13: 2031 | M13: 2032 | N13: 2033 | O13: 2034 | P13: 2035 | Q13: 2036 | R13: 2037 | S13: 2038 | T13: 2039 | U13: 2040
B15: Datos de despliegue | C15: Energía Facturada anual [GWh] | F15: =CB_SMI_Mixto_MUY_BAJA!B2/1000 -> 4883.8097 | G15: =CB_SMI_Mixto_MUY_BAJA!C2/1000 -> 5031.3008 | H15: =CB_SMI_Mixto_MUY_BAJA!D2/1000 -> 5183.2461 | I15: =CB_SMI_Mixto_MUY_BAJA!E2/1000 -> 5339.7801 | J15: =CB_SMI_Mixto_MUY_BAJA!F2/1000 -> 5501.0415 | K15: =CB_SMI_Mixto_MUY_BAJA!G2/1000 -> 5667.1729 | L15: =CB_SMI_Mixto_MUY_BAJA!H2/1000 -> 5838.3215 | M15: =CB_SMI_Mixto_MUY_BAJA!I2/1000 -> 6014.6388 | ... U15: =CB_SMI_Mixto_MUY_BAJA!Q2/1000 -> 7631.0082
C17: UM 1F [N° Equipos] | F17: =CB_SMI_Mixto_MUY_BAJA!B3 -> 8294 | G17: =CB_SMI_Mixto_MUY_BAJA!C3 -> 45 | H17: =CB_SMI_Mixto_MUY_BAJA!D3 -> 45 | I17: =CB_SMI_Mixto_MUY_BAJA!E3 -> 45 | J17: =CB_SMI_Mixto_MUY_BAJA!F3 -> 45 | K17: =CB_SMI_Mixto_MUY_BAJA!G3 -> 46 | L17: =CB_SMI_Mixto_MUY_BAJA!H3 -> 46 | M17: =CB_SMI_Mixto_MUY_BAJA!I3 -> 46 | ... U17: =CB_SMI_Mixto_MUY_BAJA!Q3 -> 48
C18: UM 3F Directa [N° Equipos] | F18: =CB_SMI_Mixto_MUY_BAJA!B4 -> 0 | G18: =CB_SMI_Mixto_MUY_BAJA!C4 -> 0 | H18: =CB_SMI_Mixto_MUY_BAJA!D4 -> 0 | I18: =CB_SMI_Mixto_MUY_BAJA!E4 -> 0 | J18: =CB_SMI_Mixto_MUY_BAJA!F4 -> 0 | K18: =CB_SMI_Mixto_MUY_BAJA!G4 -> 0 | L18: =CB_SMI_Mixto_MUY_BAJA!H4 -> 0 | M18: =CB_SMI_Mixto_MUY_BAJA!I4 -> 0 | ... U18: =CB_SMI_Mixto_MUY_BAJA!Q4 -> 0
C19: UM 3F Indirecta [N° Equipos] | F19: =CB_SMI_Mixto_MUY_BAJA!B5 -> 54202 | G19: =CB_SMI_Mixto_MUY_BAJA!C5 -> 340 | H19: =CB_SMI_Mixto_MUY_BAJA!D5 -> 340 | I19: =CB_SMI_Mixto_MUY_BAJA!E5 -> 341 | J19: =CB_SMI_Mixto_MUY_BAJA!F5 -> 343 | K19: =CB_SMI_Mixto_MUY_BAJA!G5 -> 350 | L19: =CB_SMI_Mixto_MUY_BAJA!H5 -> 350 | M19: =CB_SMI_Mixto_MUY_BAJA!I5 -> 353 | ... U19: =CB_SMI_Mixto_MUY_BAJA!Q5 -> 367
B21: Despliegue | C21: UM 1F instalados | F21: 0 | G21: =IF(G$12<=$J$6,$J7,G17) -> 2809.6667 | H21: =IF(H$12<=$J$6,$J7,H17) -> 2809.6667 | I21: =IF(I$12<=$J$6,$J7,I17) -> 2809.6667 | J21: =IF(J$12<=$J$6,$J7,J17) -> 45 | K21: =IF(K$12<=$J$6,$J7,K17) -> 46 | L21: =IF(L$12<=$J$6,$J7,L17) -> 46 | M21: =IF(M$12<=$J$6,$J7,M17) -> 46 | N21: =IF(N$12<=$J$6,$J7,N17) -> 46 | ... U21: =IF(U$12<=$J$6,$J7,U17) -> 48
C22: UM 3F Directa instalados | F22: 0 | G22: =IF(G$12<=$J$6,$J8,G18) -> 0 | H22: =IF(H$12<=$J$6,$J8,H18) -> 0 | I22: =IF(I$12<=$J$6,$J8,I18) -> 0 | J22: =IF(J$12<=$J$6,$J8,J18) -> 0 | K22: =IF(K$12<=$J$6,$J8,K18) -> 0 | L22: =IF(L$12<=$J$6,$J8,L18) -> 0 | M22: =IF(M$12<=$J$6,$J8,M18) -> 0 | N22: =IF(N$12<=$J$6,$J8,N18) -> 0 | ... U22: =IF(U$12<=$J$6,$J8,U18) -> 0
C23: UM 3F Indirecta instalados | F23: 0 | G23: =IF(G$12<=$J$6,$J9,G19) -> 18407.667 | H23: =IF(H$12<=$J$6,$J9,H19) -> 18407.667 | I23: =IF(I$12<=$J$6,$J9,I19) -> 18407.667 | J23: =IF(J$12<=$J$6,$J9,J19) -> 343 | K23: =IF(K$12<=$J$6,$J9,K19) -> 350 | L23: =IF(L$12<=$J$6,$J9,L19) -> 350 | M23: =IF(M$12<=$J$6,$J9,M19) -> 353 | N23: =IF(N$12<=$J$6,$J9,N19) -> 353 | ... U23: =IF(U$12<=$J$6,$J9,U19) -> 367
C24: UM faltantes por instalar | F24: =SUM(F17:F19) -> 62496 | G24: =SUM(F24,G17:G19)-SUM(G21:G23) -> 41663.667 | H24: =SUM(G24,H17:H19)-SUM(H21:H23) -> 20831.333 | I24: =SUM(H24,I17:I19)-SUM(I21:I23) -> 0 | J24: =SUM(I24,J17:J19)-SUM(J21:J23) -> 0 | K24: =SUM(J24,K17:K19)-SUM(K21:K23) -> 0 | L24: =SUM(K24,L17:L19)-SUM(L21:L23) -> 0 | M24: =SUM(L24,M17:M19)-SUM(M21:M23) -> 0 | N24: =SUM(M24,N17:N19)-SUM(N21:N23) -> 0 | ... U24: =SUM(T24,U17:U19)-SUM(U21:U23) -> 0
C25: % de avance | F25: 0 | G25: =IF(G$12<=$J$6,SUM($F$21:G23)/SUM($F$17:G19),1) -> 0.33742042 | H25: =IF(H$12<=$J$6,SUM($F$21:H23)/SUM($F$17:H19),1) -> 0.67073415 | I25: =IF(I$12<=$J$6,SUM($F$21:I23)/SUM($F$17:I19),1) -> 1 | J25: =IF(J$12<=$J$6,SUM($F$21:J23)/SUM($F$17:J19),1) -> 1 | K25: =IF(K$12<=$J$6,SUM($F$21:K23)/SUM($F$17:K19),1) -> 1 | L25: =IF(L$12<=$J$6,SUM($F$21:L23)/SUM($F$17:L19),1) -> 1 | M25: =IF(M$12<=$J$6,SUM($F$21:M23)/SUM($F$17:M19),1) -> 1 | N25: =IF(N$12<=$J$6,SUM($F$21:N23)/SUM($F$17:N19),1) -> 1 | ... U25: =IF(U$12<=$J$6,SUM($F$21:U23)/SUM($F$17:U19),1) -> 1
B27: Flujo de caja [MUSD] | E27: Periodo | F27: 0 | G27: 1 | H27: 2 | I27: 3 | J27: 4 | K27: 5 | L27: 6 | M27: 7 | N27: 8 | O27: 9 | P27: 10 | Q27: 11 | R27: 12 | S27: 13 | T27: 14 | U27: 15
E28: Año | F28: 2025 | G28: 2026 | H28: 2027 | I28: 2028 | J28: 2029 | K28: 2030 | L28: 2031 | M28: 2032 | N28: 2033 | O28: 2034 | P28: 2035 | Q28: 2036 | R28: 2037 | S28: 2038 | T28: 2039 | U28: 2040 | W28: VAN [MUSD] | X28: AVAN [MUSD] | Y28: VAN [USD/# Clientes] | Z28: Participación %
B30: VI [MUSD] | C30: UM 1F | F30: 0 | G30: =((-CB_SMI_Mixto_MUY_BAJA!C7)*G21)/1000000 -> -0.5210103 | H30: =((-CB_SMI_Mixto_MUY_BAJA!D7)*H21)/1000000 -> -0.5210103 | I30: =((-CB_SMI_Mixto_MUY_BAJA!E7)*I21)/1000000 -> -0.5210103 | J30: =((-CB_SMI_Mixto_MUY_BAJA!F7)*J21)/1000000 -> -0.0083445713 | K30: =((-CB_SMI_Mixto_MUY_BAJA!G7)*K21)/1000000 -> -0.0085300062 | L30: =((-CB_SMI_Mixto_MUY_BAJA!H7)*L21)/1000000 -> -0.0085300062 | M30: =((-CB_SMI_Mixto_MUY_BAJA!I7)*M21)/1000000 -> -0.0085300062 | N30: =((-CB_SMI_Mixto_MUY_BAJA!J7)*N21)/1000000 -> -0.0085300062 | ... U30: =((-CB_SMI_Mixto_MUY_BAJA!Q7)*U21)/1000000 -> -0.008900876 | W30: =NPV($D$67,G30:U30)+F30 -> -1.4529703 | X30: =PMT($D$67,15,-W30) -> -0.14960184 | Y30: =W30*1000000/7744865 -> -0.18760435 | Z30: =W30/$W$36 -> 0.033728833
C31: UM 3F Directa | F31: 0 | G31: =((-CB_SMI_Mixto_MUY_BAJA!C8)*G22)/1000000 -> 0 | H31: =((-CB_SMI_Mixto_MUY_BAJA!D8)*H22)/1000000 -> 0 | I31: =((-CB_SMI_Mixto_MUY_BAJA!E8)*I22)/1000000 -> 0 | J31: =((-CB_SMI_Mixto_MUY_BAJA!F8)*J22)/1000000 -> 0 | K31: =((-CB_SMI_Mixto_MUY_BAJA!G8)*K22)/1000000 -> 0 | L31: =((-CB_SMI_Mixto_MUY_BAJA!H8)*L22)/1000000 -> 0 | M31: =((-CB_SMI_Mixto_MUY_BAJA!I8)*M22)/1000000 -> 0 | N31: =((-CB_SMI_Mixto_MUY_BAJA!J8)*N22)/1000000 -> 0 | ... U31: =((-CB_SMI_Mixto_MUY_BAJA!Q8)*U22)/1000000 -> 0 | W31: =NPV($D$67,G31:U31)+F31 -> 0 | X31: =PMT($D$67,15,-W31) -> 0 | Y31: =W31*1000000/7744865 -> 0 | Z31: =W31/$W$36 -> 0
C32: UM 3F Indirecta | F32: 0 | G32: =((-CB_SMI_Mixto_MUY_BAJA!C9)*G23)/1000000 -> -14.355162 | H32: =((-CB_SMI_Mixto_MUY_BAJA!D9)*H23)/1000000 -> -14.355162 | I32: =((-CB_SMI_Mixto_MUY_BAJA!E9)*I23)/1000000 -> -14.355162 | J32: =((-CB_SMI_Mixto_MUY_BAJA!F9)*J23)/1000000 -> -0.26748749 | K32: =((-CB_SMI_Mixto_MUY_BAJA!G9)*K23)/1000000 -> -0.27294642 | L32: =((-CB_SMI_Mixto_MUY_BAJA!H9)*L23)/1000000 -> -0.27294642 | M32: =((-CB_SMI_Mixto_MUY_BAJA!I9)*M23)/1000000 -> -0.27528596 | N32: =((-CB_SMI_Mixto_MUY_BAJA!J9)*N23)/1000000 -> -0.27528596 | ... U32: =((-CB_SMI_Mixto_MUY_BAJA!Q9)*U23)/1000000 -> -0.28620382 | W32: =NPV($D$67,G32:U32)+F32 -> -40.316045 | X32: =PMT($D$67,15,-W32) -> -4.1510514 | Y32: =W32*1000000/7744865 -> -5.2055194 | Z32: =W32/$W$36 -> 0.93588498
C33: DCU | F33: =((-CB_SMI_Mixto_MUY_BAJA!B10)*CB_SMI_Mixto_MUY_BAJA!B6)/1000000 -> 0 | G33: =((-CB_SMI_Mixto_MUY_BAJA!C10)*CB_SMI_Mixto_MUY_BAJA!C6)/1000000 -> 0 | H33: =((-CB_SMI_Mixto_MUY_BAJA!D10)*CB_SMI_Mixto_MUY_BAJA!D6)/1000000 -> 0 | I33: =((-CB_SMI_Mixto_MUY_BAJA!E10)*CB_SMI_Mixto_MUY_BAJA!E6)/1000000 -> 0 | J33: =((-CB_SMI_Mixto_MUY_BAJA!F10)*CB_SMI_Mixto_MUY_BAJA!F6)/1000000 -> 0 | K33: =((-CB_SMI_Mixto_MUY_BAJA!G10)*CB_SMI_Mixto_MUY_BAJA!G6)/1000000 -> 0 | L33: =((-CB_SMI_Mixto_MUY_BAJA!H10)*CB_SMI_Mixto_MUY_BAJA!H6)/1000000 -> 0 | M33: =((-CB_SMI_Mixto_MUY_BAJA!I10)*CB_SMI_Mixto_MUY_BAJA!I6)/1000000 -> 0 | ... U33: =((-CB_SMI_Mixto_MUY_BAJA!Q10)*CB_SMI_Mixto_MUY_BAJA!Q6)/1000000 -> 0 | W33: =NPV($D$67,G33:U33)+F33 -> 0 | X33: =PMT($D$67,15,-W33) -> 0 | Y33: =W33*1000000/7744865 -> 0 | Z33: =W33/$W$36 -> 0
C34: HES | F34: =(-CB_SMI_Mixto_MUY_BAJA!B11)/1000000 -> -1.1468641 | G34: =(-CB_SMI_Mixto_MUY_BAJA!C11)/1000000 -> -0.007065135 | H34: =(-CB_SMI_Mixto_MUY_BAJA!D11)/1000000 -> -0.007065135 | I34: =(-CB_SMI_Mixto_MUY_BAJA!E11)/1000000 -> -0.007083486 | J34: =(-CB_SMI_Mixto_MUY_BAJA!F11)/1000000 -> -0.007120188 | K34: =(-CB_SMI_Mixto_MUY_BAJA!G11)/1000000 -> -0.007266996 | L34: =(-CB_SMI_Mixto_MUY_BAJA!H11)/1000000 -> -0.007266996 | M34: =(-CB_SMI_Mixto_MUY_BAJA!I11)/1000000 -> -0.007322049 | ... U34: =(-CB_SMI_Mixto_MUY_BAJA!Q11)/1000000 -> -0.007615665 | W34: =NPV($D$67,G34:U34)+F34 -> -1.2174901 | X34: =PMT($D$67,15,-W34) -> -0.12535615 | Y34: =W34*1000000/7744865 -> -0.15719966 | Z34: =W34/$W$36 -> 0.028262463
C35: MDMS | F35: =(-CB_SMI_Mixto_MUY_BAJA!B12)/1000000 -> -0.086178695 | G35: =(-CB_SMI_Mixto_MUY_BAJA!C12)/1000000 -> -0.00053089474 | H35: =(-CB_SMI_Mixto_MUY_BAJA!D12)/1000000 -> -0.00053089474 | I35: =(-CB_SMI_Mixto_MUY_BAJA!E12)/1000000 -> -0.00053227368 | J35: =(-CB_SMI_Mixto_MUY_BAJA!F12)/1000000 -> -0.00053503158 | K35: =(-CB_SMI_Mixto_MUY_BAJA!G12)/1000000 -> -0.00054606316 | L35: =(-CB_SMI_Mixto_MUY_BAJA!H12)/1000000 -> -0.00054606316 | M35: =(-CB_SMI_Mixto_MUY_BAJA!I12)/1000000 -> -0.0005502 | ... U35: =(-CB_SMI_Mixto_MUY_BAJA!Q12)/1000000 -> -0.00057226316 | W35: =NPV($D$67,G35:U35)+F35 -> -0.091485739 | X35: =PMT($D$67,15,-W35) -> -0.0094196246 | Y35: =W35*1000000/7744865 -> -0.011812438 | Z35: =W35/$W$36 -> 0.0021237234
C36: VI Total: | F36: =SUM(F30:F35) -> -1.2330428 | G36: =SUM(G30:G35) -> -14.883768 | H36: =SUM(H30:H35) -> -14.883768 | I36: =SUM(I30:I35) -> -14.883788 | J36: =SUM(J30:J35) -> -0.28348728 | K36: =SUM(K30:K35) -> -0.28928949 | L36: =SUM(L30:L35) -> -0.28928949 | M36: =SUM(M30:M35) -> -0.29168822 | ... U36: =SUM(U30:U35) -> -0.30329262 | W36: =NPV($D$67,G36:U36)+F36 -> -43.077991 | X36: =PMT($D$67,15,-W36) -> -4.435429 | Y36: =W36*1000000/7744865 -> -5.5621358 | Z36: =W36/$W$36 -> 1
B38: COMA [MUSD] | C38: Operación Comunicaciones UM - SGO | F38: 0 | G38: =(-CB_SMI_Mixto_MUY_BAJA!C13/1000000)*G$25 -> 0 | H38: =(-CB_SMI_Mixto_MUY_BAJA!D13/1000000)*H$25 -> 0 | I38: =(-CB_SMI_Mixto_MUY_BAJA!E13/1000000)*I$25 -> 0 | J38: =(-CB_SMI_Mixto_MUY_BAJA!F13/1000000)*J$25 -> 0 | K38: =(-CB_SMI_Mixto_MUY_BAJA!G13/1000000)*K$25 -> 0 | L38: =(-CB_SMI_Mixto_MUY_BAJA!H13/1000000)*L$25 -> 0 | M38: =(-CB_SMI_Mixto_MUY_BAJA!I13/1000000)*M$25 -> 0 | N38: =(-CB_SMI_Mixto_MUY_BAJA!J13/1000000)*N$25 -> 0 | ... U38: =(-CB_SMI_Mixto_MUY_BAJA!Q13/1000000)*U$25 -> 0 | W38: =NPV($D$67,G38:U38)+F38 -> 0 | X38: =PMT($D$67,15,-W38) -> 0 | Y38: =W38*1000000/7744865 -> 0 | Z38: =W38/$W$43 -> 0
C39: Operación Comunicaciones DCU - SGO | F39: 0 | G39: =(-CB_SMI_Mixto_MUY_BAJA!C14/1000000)*G$25 -> -0.3545051 | H39: =(-CB_SMI_Mixto_MUY_BAJA!D14/1000000)*H$25 -> -0.70469558 | I39: =(-CB_SMI_Mixto_MUY_BAJA!E14/1000000)*I$25 -> -1.0506332 | J39: =(-CB_SMI_Mixto_MUY_BAJA!F14/1000000)*J$25 -> -1.0506332 | K39: =(-CB_SMI_Mixto_MUY_BAJA!G14/1000000)*K$25 -> -1.0506332 | L39: =(-CB_SMI_Mixto_MUY_BAJA!H14/1000000)*L$25 -> -1.0506332 | M39: =(-CB_SMI_Mixto_MUY_BAJA!I14/1000000)*M$25 -> -1.0506332 | N39: =(-CB_SMI_Mixto_MUY_BAJA!J14/1000000)*N$25 -> -1.0506332 | ... U39: =(-CB_SMI_Mixto_MUY_BAJA!Q14/1000000)*U$25 -> -1.0506332 | W39: =NPV($D$67,G39:U39)+F39 -> -9.2394035 | X39: =PMT($D$67,15,-W39) -> -0.95131453 | Y39: =W39*1000000/7744865 -> -1.1929715 | Z39: =W39/$W$43 -> 0.60775601
C40: Operación HES | F40: 0 | G40: =(-CB_SMI_Mixto_MUY_BAJA!C15/1000000)*G$25 -> -0.16942727 | H40: =(-CB_SMI_Mixto_MUY_BAJA!D15/1000000)*H$25 -> -0.33885454 | I40: =(-CB_SMI_Mixto_MUY_BAJA!E15/1000000)*I$25 -> -0.50828181 | J40: =(-CB_SMI_Mixto_MUY_BAJA!F15/1000000)*J$25 -> -0.51138012 | K40: =(-CB_SMI_Mixto_MUY_BAJA!G15/1000000)*K$25 -> -0.51454231 | L40: =(-CB_SMI_Mixto_MUY_BAJA!H15/1000000)*L$25 -> -0.5177045 | M40: =(-CB_SMI_Mixto_MUY_BAJA!I15/1000000)*M$25 -> -0.52089064 | N40: =(-CB_SMI_Mixto_MUY_BAJA!J15/1000000)*N$25 -> -0.52407678 | ... U40: =(-CB_SMI_Mixto_MUY_BAJA!Q15/1000000)*U$25 -> -0.54678704 | W40: =NPV($D$67,G40:U40)+F40 -> -4.5959556 | X40: =PMT($D$67,15,-W40) -> -0.47321229 | Y40: =W40*1000000/7744865 -> -0.59341972 | Z40: =W40/$W$43 -> 0.30231601
C41: Operación MDMS | F41: 0 | G41: =(-CB_SMI_Mixto_MUY_BAJA!C16/1000000)*G$25 -> -0.024046497 | H41: =(-CB_SMI_Mixto_MUY_BAJA!D16/1000000)*H$25 -> -0.048092994 | I41: =(-CB_SMI_Mixto_MUY_BAJA!E16/1000000)*I$25 -> -0.072139492 | J41: =(-CB_SMI_Mixto_MUY_BAJA!F16/1000000)*J$25 -> -0.072579228 | K41: =(-CB_SMI_Mixto_MUY_BAJA!G16/1000000)*K$25 -> -0.073028032 | L41: =(-CB_SMI_Mixto_MUY_BAJA!H16/1000000)*L$25 -> -0.073476835 | M41: =(-CB_SMI_Mixto_MUY_BAJA!I16/1000000)*M$25 -> -0.073929039 | N41: =(-CB_SMI_Mixto_MUY_BAJA!J16/1000000)*N$25 -> -0.074381242 | ... U41: =(-CB_SMI_Mixto_MUY_BAJA!Q16/1000000)*U$25 -> -0.077604467 | W41: =NPV($D$67,G41:U41)+F41 -> -0.65229542 | X41: =PMT($D$67,15,-W41) -> -0.06716214 | Y41: =W41*1000000/7744865 -> -0.084222956 | Z41: =W41/$W$43 -> 0.042907149
C42: SyM Equipos | F42: 0 | G42: =(-CB_SMI_Mixto_MUY_BAJA!C17/1000000)*G$25 -> -0.026351928 | H42: =(-CB_SMI_Mixto_MUY_BAJA!D17/1000000)*H$25 -> -0.052703856 | I42: =(-CB_SMI_Mixto_MUY_BAJA!E17/1000000)*I$25 -> -0.079055784 | J42: =(-CB_SMI_Mixto_MUY_BAJA!F17/1000000)*J$25 -> -0.07953768 | K42: =(-CB_SMI_Mixto_MUY_BAJA!G17/1000000)*K$25 -> -0.080029512 | L42: =(-CB_SMI_Mixto_MUY_BAJA!H17/1000000)*L$25 -> -0.080521344 | M42: =(-CB_SMI_Mixto_MUY_BAJA!I17/1000000)*M$25 -> -0.081016902 | N42: =(-CB_SMI_Mixto_MUY_BAJA!J17/1000000)*N$25 -> -0.08151246 | ... U42: =(-CB_SMI_Mixto_MUY_BAJA!Q17/1000000)*U$25 -> -0.085044708 | W42: =NPV($D$67,G42:U42)+F42 -> -0.71483351 | X42: =PMT($D$67,15,-W42) -> -0.073601234 | Y42: =W42*1000000/7744865 -> -0.092297737 | Z42: =W42/$W$43 -> 0.047020824
C43: COMA Total: | F43: =SUM(F38:F42) -> 0 | G43: =SUM(G38:G42) -> -0.5743308 | H43: =SUM(H38:H42) -> -1.144347 | I43: =SUM(I38:I42) -> -1.7101103 | J43: =SUM(J38:J42) -> -1.7141303 | K43: =SUM(K38:K42) -> -1.7182331 | L43: =SUM(L38:L42) -> -1.7223359 | M43: =SUM(M38:M42) -> -1.7264698 | ... U43: =SUM(U38:U42) -> -1.7600694 | W43: =NPV($D$67,G43:U43)+F43 -> -15.202488 | X43: =PMT($D$67,15,-W43) -> -1.5652902 | Y43: =W43*1000000/7744865 -> -1.962912 | Z43: =W43/$W$43 -> 1
B45: Costos Totales (VI + COMA) | F45: =F36+F43 -> -1.2330428 | G45: =G36+G43 -> -15.458099 | H45: =H36+H43 -> -16.028115 | I45: =I36+I43 -> -16.593898 | J45: =J36+J43 -> -1.9976175 | K45: =K36+K43 -> -2.0075226 | L45: =L36+L43 -> -2.0116254 | M45: =M36+M43 -> -2.018158 | ... U45: =U36+U43 -> -2.0633621 | W45: =NPV($D$67,G45:U45)+F45 -> -58.280479 | X45: =PMT($D$67,15,-W45) -> -6.0007192 | Y45: =W45*1000000/7744865 -> -7.5250478
B47: Beneficios [MUSD] | C47: Ahorro de lectura pedestre | F47: 0 | G47: =(CB_SMI_Mixto_MUY_BAJA!C18/1000000)*G$25 -> 0 | H47: =(CB_SMI_Mixto_MUY_BAJA!D18/1000000)*H$25 -> 0 | I47: =(CB_SMI_Mixto_MUY_BAJA!E18/1000000)*I$25 -> 0 | J47: =(CB_SMI_Mixto_MUY_BAJA!F18/1000000)*J$25 -> 0 | K47: =(CB_SMI_Mixto_MUY_BAJA!G18/1000000)*K$25 -> 0 | L47: =(CB_SMI_Mixto_MUY_BAJA!H18/1000000)*L$25 -> 0 | M47: =(CB_SMI_Mixto_MUY_BAJA!I18/1000000)*M$25 -> 0 | N47: =(CB_SMI_Mixto_MUY_BAJA!J18/1000000)*N$25 -> 0 | ... U47: =(CB_SMI_Mixto_MUY_BAJA!Q18/1000000)*U$25 -> 0 | V47: =U47/$U$56 -> 0 | W47: =NPV($D$67,G47:U47)+F47 -> 0 | X47: =PMT($D$67,15,-W47) -> 0 | Y47: =W47*1000000/7744865 -> 0 | Z47: =W47/$W$56 -> 0
C48: Corte y Reposición remoto | F48: 0 | G48: =(CB_SMI_Mixto_MUY_BAJA!C19/1000000)*G$25 -> 0 | H48: =(CB_SMI_Mixto_MUY_BAJA!D19/1000000)*H$25 -> 0 | I48: =(CB_SMI_Mixto_MUY_BAJA!E19/1000000)*I$25 -> 0 | J48: =(CB_SMI_Mixto_MUY_BAJA!F19/1000000)*J$25 -> 0 | K48: =(CB_SMI_Mixto_MUY_BAJA!G19/1000000)*K$25 -> 0 | L48: =(CB_SMI_Mixto_MUY_BAJA!H19/1000000)*L$25 -> 0 | M48: =(CB_SMI_Mixto_MUY_BAJA!I19/1000000)*M$25 -> 0 | N48: =(CB_SMI_Mixto_MUY_BAJA!J19/1000000)*N$25 -> 0 | ... U48: =(CB_SMI_Mixto_MUY_BAJA!Q19/1000000)*U$25 -> 0 | V48: =U48/$U$56 -> 0 | W48: =NPV($D$67,G48:U48)+F48 -> 0 | X48: =PMT($D$67,15,-W48) -> 0 | Y48: =W48*1000000/7744865 -> 0 | Z48: =W48/$W$56 -> 0
C49: Reducción de Pérdidas No Técnicas | F49: 0 | G49: =(CB_SMI_Mixto_MUY_BAJA!C20/1000000)*G$25 -> 0 | H49: =(CB_SMI_Mixto_MUY_BAJA!D20/1000000)*H$25 -> 0 | I49: =(CB_SMI_Mixto_MUY_BAJA!E20/1000000)*I$25 -> 0 | J49: =(CB_SMI_Mixto_MUY_BAJA!F20/1000000)*J$25 -> 0 | K49: =(CB_SMI_Mixto_MUY_BAJA!G20/1000000)*K$25 -> 0 | L49: =(CB_SMI_Mixto_MUY_BAJA!H20/1000000)*L$25 -> 0 | M49: =(CB_SMI_Mixto_MUY_BAJA!I20/1000000)*M$25 -> 0 | N49: =(CB_SMI_Mixto_MUY_BAJA!J20/1000000)*N$25 -> 0 | ... U49: =(CB_SMI_Mixto_MUY_BAJA!Q20/1000000)*U$25 -> 0 | V49: =U49/$U$56 -> 0 | W49: =NPV($D$67,G49:U49)+F49 -> 0 | X49: =PMT($D$67,15,-W49) -> 0 | Y49: =W49*1000000/7744865 -> 0 | Z49: =W49/$W$56 -> 0
C50: Reducción del tiempo de respuesta ante Fallas | F50: 0 | G50: =(CB_SMI_Mixto_MUY_BAJA!C21/1000000)*G$25 -> 0.11867139 | H50: =(CB_SMI_Mixto_MUY_BAJA!D21/1000000)*H$25 -> 0.23589845 | I50: =(CB_SMI_Mixto_MUY_BAJA!E21/1000000)*I$25 -> 0.35170186 | J50: =(CB_SMI_Mixto_MUY_BAJA!F21/1000000)*J$25 -> 0.35170186 | K50: =(CB_SMI_Mixto_MUY_BAJA!G21/1000000)*K$25 -> 0.35170186 | L50: =(CB_SMI_Mixto_MUY_BAJA!H21/1000000)*L$25 -> 0.35170186 | M50: =(CB_SMI_Mixto_MUY_BAJA!I21/1000000)*M$25 -> 0.35170186 | N50: =(CB_SMI_Mixto_MUY_BAJA!J21/1000000)*N$25 -> 0.35170186 | ... U50: =(CB_SMI_Mixto_MUY_BAJA!Q21/1000000)*U$25 -> 0.35170186 | V50: =U50/$U$56 -> 0.068628782 | W50: =NPV($D$67,G50:U50)+F50 -> 3.0929114 | X50: =PMT($D$67,15,-W50) -> 0.3184547 | Y50: =W50*1000000/7744865 -> 0.39934994 | Z50: =W50/$W$56 -> 0.069944684
C51: Reducción del costo de la energía en horas de Sol | F51: 0 | G51: =(CB_SMI_Mixto_MUY_BAJA!C22/1000000)*G$25 -> 0 | H51: =(CB_SMI_Mixto_MUY_BAJA!D22/1000000)*H$25 -> 0 | I51: =(CB_SMI_Mixto_MUY_BAJA!E22/1000000)*I$25 -> 0 | J51: =(CB_SMI_Mixto_MUY_BAJA!F22/1000000)*J$25 -> 0 | K51: =(CB_SMI_Mixto_MUY_BAJA!G22/1000000)*K$25 -> 0 | L51: =(CB_SMI_Mixto_MUY_BAJA!H22/1000000)*L$25 -> 0 | M51: =(CB_SMI_Mixto_MUY_BAJA!I22/1000000)*M$25 -> 0 | N51: =(CB_SMI_Mixto_MUY_BAJA!J22/1000000)*N$25 -> 0 | ... U51: =(CB_SMI_Mixto_MUY_BAJA!Q22/1000000)*U$25 -> 0 | V51: =U51/$U$56 -> 0 | W51: =NPV($D$67,G51:U51)+F51 -> 0 | X51: =PMT($D$67,15,-W51) -> 0 | Y51: =W51*1000000/7744865 -> 0 | Z51: =W51/$W$56 -> 0
C52: Reducción del consumo de Clientes Finales | F52: 0 | G52: =(CB_SMI_Mixto_MUY_BAJA!C23/1000000)*G$25 -> 0 | H52: =(CB_SMI_Mixto_MUY_BAJA!D23/1000000)*H$25 -> 0 | I52: =(CB_SMI_Mixto_MUY_BAJA!E23/1000000)*I$25 -> 0 | J52: =(CB_SMI_Mixto_MUY_BAJA!F23/1000000)*J$25 -> 0 | K52: =(CB_SMI_Mixto_MUY_BAJA!G23/1000000)*K$25 -> 0 | L52: =(CB_SMI_Mixto_MUY_BAJA!H23/1000000)*L$25 -> 0 | M52: =(CB_SMI_Mixto_MUY_BAJA!I23/1000000)*M$25 -> 0 | N52: =(CB_SMI_Mixto_MUY_BAJA!J23/1000000)*N$25 -> 0 | ... U52: =(CB_SMI_Mixto_MUY_BAJA!Q23/1000000)*U$25 -> 0 | V52: =U52/$U$56 -> 0 | W52: =NPV($D$67,G52:U52)+F52 -> 0 | X52: =PMT($D$67,15,-W52) -> 0 | Y52: =W52*1000000/7744865 -> 0 | Z52: =W52/$W$56 -> 0
C53: Reducción de emisiones de CO2 | F53: 0 | G53: =(CB_SMI_Mixto_MUY_BAJA!C24/1000000)*G$25 -> 0 | H53: =(CB_SMI_Mixto_MUY_BAJA!D24/1000000)*H$25 -> 0 | I53: =(CB_SMI_Mixto_MUY_BAJA!E24/1000000)*I$25 -> 0 | J53: =(CB_SMI_Mixto_MUY_BAJA!F24/1000000)*J$25 -> 0 | K53: =(CB_SMI_Mixto_MUY_BAJA!G24/1000000)*K$25 -> 0 | L53: =(CB_SMI_Mixto_MUY_BAJA!H24/1000000)*L$25 -> 0 | M53: =(CB_SMI_Mixto_MUY_BAJA!I24/1000000)*M$25 -> 0 | N53: =(CB_SMI_Mixto_MUY_BAJA!J24/1000000)*N$25 -> 0 | ... U53: =(CB_SMI_Mixto_MUY_BAJA!Q24/1000000)*U$25 -> 0 | V53: =U53/$U$56 -> 0 | W53: =NPV($D$67,G53:U53)+F53 -> 0 | X53: =PMT($D$67,15,-W53) -> 0 | Y53: =W53*1000000/7744865 -> 0 | Z53: =W53/$W$56 -> 0
C54: Reducción servicio Atención al Cliente | F54: 0 | G54: =(CB_SMI_Mixto_MUY_BAJA!C25/1000000)*G$25 -> 0 | H54: =(CB_SMI_Mixto_MUY_BAJA!D25/1000000)*H$25 -> 0 | I54: =(CB_SMI_Mixto_MUY_BAJA!E25/1000000)*I$25 -> 0 | J54: =(CB_SMI_Mixto_MUY_BAJA!F25/1000000)*J$25 -> 0 | K54: =(CB_SMI_Mixto_MUY_BAJA!G25/1000000)*K$25 -> 0 | L54: =(CB_SMI_Mixto_MUY_BAJA!H25/1000000)*L$25 -> 0 | M54: =(CB_SMI_Mixto_MUY_BAJA!I25/1000000)*M$25 -> 0 | N54: =(CB_SMI_Mixto_MUY_BAJA!J25/1000000)*N$25 -> 0 | ... U54: =(CB_SMI_Mixto_MUY_BAJA!Q25/1000000)*U$25 -> 0 | V54: =U54/$U$56 -> 0 | W54: =NPV($D$67,G54:U54)+F54 -> 0 | X54: =PMT($D$67,15,-W54) -> 0 | Y54: =W54*1000000/7744865 -> 0 | Z54: =W54/$W$56 -> 0
C55: Reducción en Inversión de infraestructura de red | F55: 0 | G55: =(CB_SMI_Mixto_MUY_BAJA!C26/1000000)*G$25 -> 1.5438995 | H55: =(CB_SMI_Mixto_MUY_BAJA!D26/1000000)*H$25 -> 3.0713301 | I55: =(CB_SMI_Mixto_MUY_BAJA!E26/1000000)*I$25 -> 4.6295228 | J55: =(CB_SMI_Mixto_MUY_BAJA!F26/1000000)*J$25 -> 4.6403802 | K55: =(CB_SMI_Mixto_MUY_BAJA!G26/1000000)*K$25 -> 4.6474472 | L55: =(CB_SMI_Mixto_MUY_BAJA!H26/1000000)*L$25 -> 4.6525352 | M55: =(CB_SMI_Mixto_MUY_BAJA!I26/1000000)*M$25 -> 4.6575005 | N55: =(CB_SMI_Mixto_MUY_BAJA!J26/1000000)*N$25 -> 4.6959971 | ... U55: =(CB_SMI_Mixto_MUY_BAJA!Q26/1000000)*U$25 -> 4.7729973 | V55: =U55/$U$56 -> 0.93137122 | W55: =NPV($D$67,G55:U55)+F55 -> 41.12648 | X55: =PMT($D$67,15,-W55) -> 4.2344961 | Y55: =W55*1000000/7744865 -> 5.310161 | Z55: =W55/$W$56 -> 0.93005532
C56: Beneficios Total: | F56: =SUM(F47:F55) -> 0 | G56: =SUM(G47:G55) -> 1.6625709 | H56: =SUM(H47:H55) -> 3.3072286 | I56: =SUM(I47:I55) -> 4.9812247 | J56: =SUM(J47:J55) -> 4.9920821 | K56: =SUM(K47:K55) -> 4.999149 | L56: =SUM(L47:L55) -> 5.004237 | M56: =SUM(M47:M55) -> 5.0092024 | ... U56: =SUM(U47:U55) -> 5.1246992 | W56: =NPV($D$67,G56:U56)+F56 -> 44.219391 | X56: =PMT($D$67,15,-W56) -> 4.5529508 | Y56: =W56*1000000/7744865 -> 5.7095109 | Z56: =W56/$W$56 -> 1
B58: Flujo | F58: =F45+F56 -> -1.2330428 | G58: =G45+G56 -> -13.795528 | H58: =H45+H56 -> -12.720887 | I58: =I45+I56 -> -11.612674 | J58: =J45+J56 -> 2.9944646 | K58: =K45+K56 -> 2.9916265 | L58: =L45+L56 -> 2.9926116 | M58: =M45+M56 -> 2.9910444 | ... U58: =U45+U56 -> 3.0613371
B60: Flujo del periodo anterior | F60: 0 | G60: =F61 -> -1.2330428 | H60: =G61 -> -15.028571 | I60: =H61 -> -27.749458 | J60: =I61 -> -39.362132 | K60: =J61 -> -36.367667 | L60: =K61 -> -33.376041 | M60: =L61 -> -30.383429 | N60: =M61 -> -27.392385 | ... U60: =T61 -> -6.1276769
B61: Flujo Acumulado | F61: =F58+F60 -> -1.2330428 | G61: =G58+G60 -> -15.028571 | H61: =H58+H60 -> -27.749458 | I61: =I58+I60 -> -39.362132 | J61: =J58+J60 -> -36.367667 | K61: =K58+K60 -> -33.376041 | L61: =L58+L60 -> -30.383429 | M61: =M58+M60 -> -27.392385 | ... U61: =U58+U60 -> -3.0663398
B63: Flujo descontado (6%) | F63: =F58/(1+0.06)^F27 -> -1.2330428 | G63: =G58/(1+0.06)^G27 -> -13.014649 | H63: =H58/(1+0.06)^H27 -> -11.321544 | I63: =I58/(1+0.06)^I27 -> -9.7502248 | J63: =J58/(1+0.06)^J27 -> 2.3718964 | K63: =K58/(1+0.06)^K27 -> 2.2355173 | L63: =L58/(1+0.06)^L27 -> 2.1096731 | M63: =M58/(1+0.06)^M27 -> 1.9892153 | ... U63: =U58/(1+0.06)^U27 -> 1.277389
B64: Flujo Acumulado descontado (6%) | F64: =F63 -> -1.2330428 | G64: =F64+G63 -> -14.247692 | H64: =G64+H63 -> -25.569236 | I64: =H64+I63 -> -35.319461 | J64: =I64+J63 -> -32.947565 | K64: =J64+K63 -> -30.712047 | L64: =K64+L63 -> -28.602374 | M64: =L64+M63 -> -26.613159 | N64: =M64+N63 -> -24.714981 | ... U64: =T64+U63 -> -14.061088
B67: Tasa | D67: =J4 -> 0.06 | H67: Monto [MUSD] | J67: Monto [USD/cliente] | L67: Monto [$/cliente]
F68: VAN (Costos) | H68: =NPV(D67,G45:U45)+F45 -> -58.280479 | J68: =H68*1000000/$D$76 -> -45.243866 | L68: =J68*$S$4 -> -43405.155
B69: VAN | D69: =NPV(D67,G58:U58)+F58 -> -14.061088 | F69: Anualidad (Costos) | H69: =PMT(D67,15,-H68) -> -6.0007192 | J69: =H69*1000000/$D$76 -> -4.6584335 | L69: =J69*$S$4 -> -4469.1148
B70: TIR | D70: =IRR(F58:U58) -> -0.010472874 | F70: Mensualidad (Costos) | H70: =H69/12 -> -0.50005993 | J70: =J69/12 -> -0.38820279 | L70: =L69/12 -> -372.42623
B71: B/C | D71: =NPV(D67,G56:U56)/-(F36+NPV(D67,G36:U36)+NPV(D67,G43:U43)) -> 0.75873418
F72: VAN (Beneficios) | H72: =NPV(D67,G56:U56)+F56 -> 44.219391 | J72: =H72*1000000/$D$76 -> 34.328068 | L72: =J72*$S$4 -> 32932.975
B73: # Clientes Alta | D73: 2527114 | F73: Anualidad (Beneficios) | H73: =PMT(D67,15,-H72) -> 4.5529508 | J73: =H73*1000000/$D$76 -> 3.5345127 | L73: =J73*$S$4 -> 3390.8701
B74: # Clientes Media | D74: 2158536 | F74: Mensualidad (Beneficios) | H74: =H73/12 -> 0.37941256 | J74: =J73/12 -> 0.29454273 | L74: =L73/12 -> 282.57251
B75: # Clientes Baja | D75: 1173397
B76: # Clientes Muy Baja | D76: 1288141 | F76: VAN (Neto) | H76: =H72+H68 -> -14.061088 | J76: =H76*1000000/$D$76 -> -10.915798 | L76: =J76*$S$4 -> -10472.18
B77: # Clientes Ext. Baja | D77: 593823 | F77: Anualidad (Neto) | H77: =PMT(D67,15,-H76) -> -1.4477684 | J77: =H77*1000000/$D$76 -> -1.1239208 | L77: =J77*$S$4 -> -1078.2446
F78: Mensualidad (Neto) | H78: =H77/12 -> -0.12064737 | J78: =J77/12 -> -0.093660065 | L78: =L77/12 -> -89.85372
B79: # Clientes Regulados | D79: =SUM(D73:D77) -> 7741011

Sheet CB_SMI_Mixto_EXT_BAJA
A1: Concepto | B1: Periodo 0 | C1: Periodo 1 | D1: Periodo 2 | E1: Periodo 3 | F1: Periodo 4 | G1: Periodo 5 | H1: Periodo 6 | I1: Periodo 7 | J1: Periodo 8 | K1: Periodo 9 | L1: Periodo 10 | M1: Periodo 11 | N1: Periodo 12 | O1: Periodo 13 | P1: Periodo 14 | Q1: Periodo 15
A2: Energía facturada anual [MWh/año] | B2: 1856961.4 | C2: 1913041.6 | D2: 1970815.5 | E2: 2030334.1 | F2: 2091650.2 | G2: 2154818 | H2: 2219893.5 | I2: 2286934.3 | J2: 2355999.7 | K2: 2427150.9 | L2: 2500450.9 | M2: 2575964.5 | N2: 2653758.6 | O2: 2733902.1 | P2: 2816466 | Q2: 2901523.3
A3: Cantidad UM 1F | B3: 6777 | C3: 0 | D3: 0 | E3: 0 | F3: 0 | G3: 0 | H3: 0 | I3: 0 | J3: 0 | K3: 0 | L3: 0 | M3: 0 | N3: 0 | O3: 0 | P3: 0 | Q3: 0
A4: Cantidad UM 3F Directa | B4: 0 | C4: 0 | D4: 0 | E4: 0 | F4: 0 | G4: 0 | H4: 0 | I4: 0 | J4: 0 | K4: 0 | L4: 0 | M4: 0 | N4: 0 | O4: 0 | P4: 0 | Q4: 0
A5: Cantidad UM 3F Indirecta | B5: 40181 | C5: 0 | D5: 0 | E5: 0 | F5: 0 | G5: 0 | H5: 0 | I5: 0 | J5: 0 | K5: 0 | L5: 0 | M5: 0 | N5: 0 | O5: 0 | P5: 0 | Q5: 0
A6: Cantidad DCU | B6: 0 | C6: 0 | D6: 0 | E6: 0 | F6: 0 | G6: 0 | H6: 0 | I6: 0 | J6: 0 | K6: 0 | L6: 0 | M6: 0 | N6: 0 | O6: 0 | P6: 0 | Q6: 0
A7: Inversión UM 1F [USD/equipo] | B7: 216.60825 | C7: 0 | D7: 0 | E7: 0 | F7: 0 | G7: 0 | H7: 0 | I7: 0 | J7: 0 | K7: 0 | L7: 0 | M7: 0 | N7: 0 | O7: 0 | P7: 0 | Q7: 0
A8: Inversión UM 3F Directa [USD/equipo] | B8: 0 | C8: 0 | D8: 0 | E8: 0 | F8: 0 | G8: 0 | H8: 0 | I8: 0 | J8: 0 | K8: 0 | L8: 0 | M8: 0 | N8: 0 | O8: 0 | P8: 0 | Q8: 0
A9: Inversión UM 3F Indirecta [USD/equipo] | B9: 966.86692 | C9: 0 | D9: 0 | E9: 0 | F9: 0 | G9: 0 | H9: 0 | I9: 0 | J9: 0 | K9: 0 | L9: 0 | M9: 0 | N9: 0 | O9: 0 | P9: 0 | Q9: 0
A10: Inversión DCU [USD/equipo] | B10: 0 | C10: 0 | D10: 0 | E10: 0 | F10: 0 | G10: 0 | H10: 0 | I10: 0 | J10: 0 | K10: 0 | L10: 0 | M10: 0 | N10: 0 | O10: 0 | P10: 0 | Q10: 0
A11: Inversión SGO [USD] | B11: 861726.26 | C11: 0 | D11: 0 | E11: 0 | F11: 0 | G11: 0 | H11: 0 | I11: 0 | J11: 0 | K11: 0 | L11: 0 | M11: 0 | N11: 0 | O11: 0 | P11: 0 | Q11: 0
A12: Inversión MDMS [USD] | B12: 64752.611 | C12: 0 | D12: 0 | E12: 0 | F12: 0 | G12: 0 | H12: 0 | I12: 0 | J12: 0 | K12: 0 | L12: 0 | M12: 0 | N12: 0 | O12: 0 | P12: 0 | Q12: 0
A13: Operación Comunicaciones [USD/año] | B13: 0 | C13: 0 | D13: 0 | E13: 0 | F13: 0 | G13: 0 | H13: 0 | I13: 0 | J13: 0 | K13: 0 | L13: 0 | M13: 0 | N13: 0 | O13: 0 | P13: 0 | Q13: 0
... A26: Ahorro por inversión evitada [USD/año] | B26: 4843846.1 | C26: 4847413.7 | D26: 4851080.5 | E26: 4904544 | F26: 4916046.4 | G26: 4923533.1 | H26: 4928923.4 | I26: 4934183.7 | J26: 4974967.3 | K26: 4985506.3 | L26: 4993852 | M26: 5002217.8 | N26: 5012138 | O26: 5026895.7 | P26: 5041696.9 | Q26: 5056541.7

Sheet Flujo SMI_Mixto_EXT_BAJA
B2: Escenario de implementación | G2: Supuestos y Consideraciones
B4: Densidad de clientes | D4: Tecnología | G4: Tasa de descuento | J4: 0.06 | K4: % | R4: Dólar | S4: 959.36 | T4: USD/$ | U4: 45946
B5: Alta | D5: Mixto_EXT_BAJA | G5: Vida útil del proyecto | J5: 15 | K5: años | R5: UF | S5: 39521.26 | T5: UF/$ | U5: 45946
B6: Media | D6: Mixto_EXT_BAJA | G6: Meta de despligue | J6: 3 | K6: años
B7: Baja | D7: Mixto_EXT_BAJA | G7: Objetivo de despligue UM 1F | J7: =(SUMIF($F$12:$U$12,"<="&$J$6,$F$17:$U$17)) / ($J$6) -> 2259 | K7: UM/año | L7: ="Razonable para chile en torno a 1M y 1,5M por año." -> Razonable para chile en torno a 1M y 1,5M por año.
B8: Muy Baja | D8: Mixto_EXT_BAJA | G8: Objetivo de despligue UM 3F Directa | J8: =(SUMIF($F$12:$U$12,"<="&$J$6,$F$18:$U$18)) / ($J$6) -> 0 | K8: UM/año | L8: ="Razonable para chile en torno a 1M y 1,5M por año." -> Razonable para chile en torno a 1M y 1,5M por año.
B9: Extremadamente Baja | D9: Mixto_EXT_BAJA | G9: Objetivo de despligue UM 3F Indirecta | J9: =(SUMIF($F$12:$U$12,"<="&$J$6,$F$19:$U$19)) / ($J$6) -> 13393.667 | K9: UM/año | L9: ="Razonable para chile en torno a 1M y 1,5M por año." -> Razonable para chile en torno a 1M y 1,5M por año.
B12: Despligue SMI Chile | E12: Periodo | F12: 0 | G12: 1 | H12: 2 | I12: 3 | J12: 4 | K12: 5 | L12: 6 | M12: 7 | N12: 8 | O12: 9 | P12: 10 | Q12: 11 | R12: 12 | S12: 13 | T12: 14 | U12: 15
E13: Año | F13: 2025 | G13: 2026 | H13: 2027 | I13: 2028 | J13: 2029 | K13: 2030 | L13: 2031 | M13: 2032 | N13: 2033 | O13: 2034 | P13: 2035 | Q13: 2036 | R13: 2037 | S13: 2038 | T13: 2039 | U13: 2040
B15: Datos de despliegue | C15: Energía Facturada anual [GWh] | F15: =CB_SMI_Mixto_EXT_BAJA!B2/1000 -> 1856.9614 | G15: =CB_SMI_Mixto_EXT_BAJA!C2/1000 -> 1913.0416 | H15: =CB_SMI_Mixto_EXT_BAJA!D2/1000 -> 1970.8155 | I15: =CB_SMI_Mixto_EXT_BAJA!E2/1000 -> 2030.3341 | J15: =CB_SMI_Mixto_EXT_BAJA!F2/1000 -> 2091.6502 | K15: =CB_SMI_Mixto_EXT_BAJA!G2/1000 -> 2154.818 | L15: =CB_SMI_Mixto_EXT_BAJA!H2/1000 -> 2219.8935 | M15: =CB_SMI_Mixto_EXT_BAJA!I2/1000 -> 2286.9343 | ... U15: =CB_SMI_Mixto_EXT_BAJA!Q2/1000 -> 2901.5233
C17: UM 1F [N° Equipos] | F17: =CB_SMI_Mixto_EXT_BAJA!B3 -> 6777 | G17: =CB_SMI_Mixto_EXT_BAJA!C3 -> 0 | H17: =CB_SMI_Mixto_EXT_BAJA!D3 -> 0 | I17: =CB_SMI_Mixto_EXT_BAJA!E3 -> 0 | J17: =CB_SMI_Mixto_EXT_BAJA!F3 -> 0 | K17: =CB_SMI_Mixto_EXT_BAJA!G3 -> 0 | L17: =CB_SMI_Mixto_EXT_BAJA!H3 -> 0 | M17: =CB_SMI_Mixto_EXT_BAJA!I3 -> 0 | ... U17: =CB_SMI_Mixto_EXT_BAJA!Q3 -> 0
C18: UM 3F Directa [N° Equipos] | F18: =CB_SMI_Mixto_EXT_BAJA!B4 -> 0 | G18: =CB_SMI_Mixto_EXT_BAJA!C4 -> 0 | H18: =CB_SMI_Mixto_EXT_BAJA!D4 -> 0 | I18: =CB_SMI_Mixto_EXT_BAJA!E4 -> 0 | J18: =CB_SMI_Mixto_EXT_BAJA!F4 -> 0 | K18: =CB_SMI_Mixto_EXT_BAJA!G4 -> 0 | L18: =CB_SMI_Mixto_EXT_BAJA!H4 -> 0 | M18: =CB_SMI_Mixto_EXT_BAJA!I4 -> 0 | ... U18: =CB_SMI_Mixto_EXT_BAJA!Q4 -> 0
C19: UM 3F Indirecta [N° Equipos] | F19: =CB_SMI_Mixto_EXT_BAJA!B5 -> 40181 | G19: =CB_SMI_Mixto_EXT_BAJA!C5 -> 0 | H19: =CB_SMI_Mixto_EXT_BAJA!D5 -> 0 | I19: =CB_SMI_Mixto_EXT_BAJA!E5 -> 0 | J19: =CB_SMI_Mixto_EXT_BAJA!F5 -> 0 | K19: =CB_SMI_Mixto_EXT_BAJA!G5 -> 0 | L19: =CB_SMI_Mixto_EXT_BAJA!H5 -> 0 | M19: =CB_SMI_Mixto_EXT_BAJA!I5 -> 0 | ... U19: =CB_SMI_Mixto_EXT_BAJA!Q5 -> 0
B21: Despliegue | C21: UM 1F instalados | F21: 0 | G21: =IF(G$12<=$J$6,$J7,G17) -> 2259 | H21: =IF(H$12<=$J$6,$J7,H17) -> 2259 | I21: =IF(I$12<=$J$6,$J7,I17) -> 2259 | J21: =IF(J$12<=$J$6,$J7,J17) -> 0 | K21: =IF(K$12<=$J$6,$J7,K17) -> 0 | L21: =IF(L$12<=$J$6,$J7,L17) -> 0 | M21: =IF(M$12<=$J$6,$J7,M17) -> 0 | N21: =IF(N$12<=$J$6,$J7,N17) -> 0 | ... U21: =IF(U$12<=$J$6,$J7,U17) -> 0
C22: UM 3F Directa instalados | F22: 0 | G22: =IF(G$12<=$J$6,$J8,G18) -> 0 | H22: =IF(H$12<=$J$6,$J8,H18) -> 0 | I22: =IF(I$12<=$J$6,$J8,I18) -> 0 | J22: =IF(J$12<=$J$6,$J8,J18) -> 0 | K22: =IF(K$12<=$J$6,$J8,K18) -> 0 | L22: =IF(L$12<=$J$6,$J8,L18) -> 0 | M22: =IF(M$12<=$J$6,$J8,M18) -> 0 | N22: =IF(N$12<=$J$6,$J8,N18) -> 0 | ... U22: =IF(U$12<=$J$6,$J8,U18) -> 0
C23: UM 3F Indirecta instalados | F23: 0 | G23: =IF(G$12<=$J$6,$J9,G19) -> 13393.667 | H23: =IF(H$12<=$J$6,$J9,H19) -> 13393.667 | I23: =IF(I$12<=$J$6,$J9,I19) -> 13393.667 | J23: =IF(J$12<=$J$6,$J9,J19) -> 0 | K23: =IF(K$12<=$J$6,$J9,K19) -> 0 | L23: =IF(L$12<=$J$6,$J9,L19) -> 0 | M23: =IF(M$12<=$J$6,$J9,M19) -> 0 | N23: =IF(N$12<=$J$6,$J9,N19) -> 0 | ... U23: =IF(U$12<=$J$6,$J9,U19) -> 0
C24: UM faltantes por instalar | F24: =SUM(F17:F19) -> 46958 | G24: =SUM(F24,G17:G19)-SUM(G21:G23) -> 31305.333 | H24: =SUM(G24,H17:H19)-SUM(H21:H23) -> 15652.667 | I24: =SUM(H24,I17:I19)-SUM(I21:I23) -> 0 | J24: =SUM(I24,J17:J19)-SUM(J21:J23) -> 0 | K24: =SUM(J24,K17:K19)-SUM(K21:K23) -> 0 | L24: =SUM(K24,L17:L19)-SUM(L21:L23) -> 0 | M24: =SUM(L24,M17:M19)-SUM(M21:M23) -> 0 | N24: =SUM(M24,N17:N19)-SUM(N21:N23) -> 0 | ... U24: =SUM(T24,U17:U19)-SUM(U21:U23) -> 0
C25: % de avance | F25: 0 | G25: =IF(G$12<=$J$6,SUM($F$21:G23)/SUM($F$17:G19),1) -> 0.33333333 | H25: =IF(H$12<=$J$6,SUM($F$21:H23)/SUM($F$17:H19),1) -> 0.66666667 | I25: =IF(I$12<=$J$6,SUM($F$21:I23)/SUM($F$17:I19),1) -> 1 | J25: =IF(J$12<=$J$6,SUM($F$21:J23)/SUM($F$17:J19),1) -> 1 | K25: =IF(K$12<=$J$6,SUM($F$21:K23)/SUM($F$17:K19),1) -> 1 | L25: =IF(L$12<=$J$6,SUM($F$21:L23)/SUM($F$17:L19),1) -> 1 | M25: =IF(M$12<=$J$6,SUM($F$21:M23)/SUM($F$17:M19),1) -> 1 | N25: =IF(N$12<=$J$6,SUM($F$21:N23)/SUM($F$17:N19),1) -> 1 | ... U25: =IF(U$12<=$J$6,SUM($F$21:U23)/SUM($F$17:U19),1) -> 1
B27: Flujo de caja [MUSD] | E27: Periodo | F27: 0 | G27: 1 | H27: 2 | I27: 3 | J27: 4 | K27: 5 | L27: 6 | M27: 7 | N27: 8 | O27: 9 | P27: 10 | Q27: 11 | R27: 12 | S27: 13 | T27: 14 | U27: 15
E28: Año | F28: 2025 | G28: 2026 | H28: 2027 | I28: 2028 | J28: 2029 | K28: 2030 | L28: 2031 | M28: 2032 | N28: 2033 | O28: 2034 | P28: 2035 | Q28: 2036 | R28: 2037 | S28: 2038 | T28: 2039 | U28: 2040 | W28: VAN [MUSD] | X28: AVAN [MUSD] | Y28: VAN [USD/# Clientes] | Z28: Participación %
B30: VI [MUSD] | C30: UM 1F | F30: 0 | G30: =((-CB_SMI_Mixto_EXT_BAJA!$B$7)*G21)/1000000 -> -0.48931804 | H30: =((-CB_SMI_Mixto_EXT_BAJA!$B$7)*H21)/1000000 -> -0.48931804 | I30: =((-CB_SMI_Mixto_EXT_BAJA!$B$7)*I21)/1000000 -> -0.48931804 | J30: =((-CB_SMI_Mixto_EXT_BAJA!$B$7)*J21)/1000000 -> 0 | K30: =((-CB_SMI_Mixto_EXT_BAJA!$B$7)*K21)/1000000 -> 0 | L30: =((-CB_SMI_Mixto_EXT_BAJA!$B$7)*L21)/1000000 -> 0 | M30: =((-CB_SMI_Mixto_EXT_BAJA!$B$7)*M21)/1000000 -> 0 | N30: =((-CB_SMI_Mixto_EXT_BAJA!$B$7)*N21)/1000000 -> 0 | ... U30: =((-CB_SMI_Mixto_EXT_BAJA!$B$7)*U21)/1000000 -> 0 | W30: =NPV($D$67,G30:U30)+F30 -> -1.307953 | X30: =PMT($D$67,15,-W30) -> -0.13467045 | Y30: =W30*1000000/7744865 -> -0.16888002 | Z30: =W30/$W$36 -> 0.035494311
C31: UM 3F Directa | F31: 0 | G31: =((-CB_SMI_Mixto_EXT_BAJA!$B$8)*G22)/1000000 -> 0 | H31: =((-CB_SMI_Mixto_EXT_BAJA!$B$8)*H22)/1000000 -> 0 | I31: =((-CB_SMI_Mixto_EXT_BAJA!$B$8)*I22)/1000000 -> 0 | J31: =((-CB_SMI_Mixto_EXT_BAJA!$B$8)*J22)/1000000 -> 0 | K31: =((-CB_SMI_Mixto_EXT_BAJA!$B$8)*K22)/1000000 -> 0 | L31: =((-CB_SMI_Mixto_EXT_BAJA!$B$8)*L22)/1000000 -> 0 | M31: =((-CB_SMI_Mixto_EXT_BAJA!$B$8)*M22)/1000000 -> 0 | N31: =((-CB_SMI_Mixto_EXT_BAJA!$B$8)*N22)/1000000 -> 0 | ... U31: =((-CB_SMI_Mixto_EXT_BAJA!$B$8)*U22)/1000000 -> 0 | W31: =NPV($D$67,G31:U31)+F31 -> 0 | X31: =PMT($D$67,15,-W31) -> 0 | Y31: =W31*1000000/7744865 -> 0 | Z31: =W31/$W$36 -> 0
C32: UM 3F Indirecta | F32: 0 | G32: =((-CB_SMI_Mixto_EXT_BAJA!$B$9)*G23)/1000000 -> -12.949893 | H32: =((-CB_SMI_Mixto_EXT_BAJA!$B$9)*H23)/1000000 -> -12.949893 | I32: =((-CB_SMI_Mixto_EXT_BAJA!$B$9)*I23)/1000000 -> -12.949893 | J32: =((-CB_SMI_Mixto_EXT_BAJA!$B$9)*J23)/1000000 -> 0 | K32: =((-CB_SMI_Mixto_EXT_BAJA!$B$9)*K23)/1000000 -> 0 | L32: =((-CB_SMI_Mixto_EXT_BAJA!$B$9)*L23)/1000000 -> 0 | M32: =((-CB_SMI_Mixto_EXT_BAJA!$B$9)*M23)/1000000 -> 0 | N32: =((-CB_SMI_Mixto_EXT_BAJA!$B$9)*N23)/1000000 -> 0 | ... U32: =((-CB_SMI_Mixto_EXT_BAJA!$B$9)*U23)/1000000 -> 0 | W32: =NPV($D$67,G32:U32)+F32 -> -34.615219 | X32: =PMT($D$67,15,-W32) -> -3.5640786 | Y32: =W32*1000000/7744865 -> -4.4694413 | Z32: =W32/$W$36 -> 0.93936356
C33: DCU | F33: =((-CB_SMI_Mixto_EXT_BAJA!B10)*CB_SMI_Mixto_EXT_BAJA!B6)/1000000 -> 0 | G33: =((-CB_SMI_Mixto_EXT_BAJA!C10)*CB_SMI_Mixto_EXT_BAJA!C6)/1000000 -> 0 | H33: =((-CB_SMI_Mixto_EXT_BAJA!D10)*CB_SMI_Mixto_EXT_BAJA!D6)/1000000 -> 0 | I33: =((-CB_SMI_Mixto_EXT_BAJA!E10)*CB_SMI_Mixto_EXT_BAJA!E6)/1000000 -> 0 | J33: =((-CB_SMI_Mixto_EXT_BAJA!F10)*CB_SMI_Mixto_EXT_BAJA!F6)/1000000 -> 0 | K33: =((-CB_SMI_Mixto_EXT_BAJA!G10)*CB_SMI_Mixto_EXT_BAJA!G6)/1000000 -> 0 | L33: =((-CB_SMI_Mixto_EXT_BAJA!H10)*CB_SMI_Mixto_EXT_BAJA!H6)/1000000 -> 0 | M33: =((-CB_SMI_Mixto_EXT_BAJA!I10)*CB_SMI_Mixto_EXT_BAJA!I6)/1000000 -> 0 | ... U33: =((-CB_SMI_Mixto_EXT_BAJA!Q10)*CB_SMI_Mixto_EXT_BAJA!Q6)/1000000 -> 0 | W33: =NPV($D$67,G33:U33)+F33 -> 0 | X33: =PMT($D$67,15,-W33) -> 0 | Y33: =W33*1000000/7744865 -> 0 | Z33: =W33/$W$36 -> 0
C34: HES | F34: =(-CB_SMI_Mixto_EXT_BAJA!B11)/1000000 -> -0.86172626 | G34: =(-CB_SMI_Mixto_EXT_BAJA!C11)/1000000 -> 0 | H34: =(-CB_SMI_Mixto_EXT_BAJA!D11)/1000000 -> 0 | I34: =(-CB_SMI_Mixto_EXT_BAJA!E11)/1000000 -> 0 | J34: =(-CB_SMI_Mixto_EXT_BAJA!F11)/1000000 -> 0 | K34: =(-CB_SMI_Mixto_EXT_BAJA!G11)/1000000 -> 0 | L34: =(-CB_SMI_Mixto_EXT_BAJA!H11)/1000000 -> 0 | M34: =(-CB_SMI_Mixto_EXT_BAJA!I11)/1000000 -> 0 | ... U34: =(-CB_SMI_Mixto_EXT_BAJA!Q11)/1000000 -> 0 | W34: =NPV($D$67,G34:U34)+F34 -> -0.86172626 | X34: =PMT($D$67,15,-W34) -> -0.088725717 | Y34: =W34*1000000/7744865 -> -0.11126421 | Z34: =W34/$W$36 -> 0.023384923
C35: MDMS | F35: =(-CB_SMI_Mixto_EXT_BAJA!B12)/1000000 -> -0.064752611 | G35: =(-CB_SMI_Mixto_EXT_BAJA!C12)/1000000 -> 0 | H35: =(-CB_SMI_Mixto_EXT_BAJA!D12)/1000000 -> 0 | I35: =(-CB_SMI_Mixto_EXT_BAJA!E12)/1000000 -> 0 | J35: =(-CB_SMI_Mixto_EXT_BAJA!F12)/1000000 -> 0 | K35: =(-CB_SMI_Mixto_EXT_BAJA!G12)/1000000 -> 0 | L35: =(-CB_SMI_Mixto_EXT_BAJA!H12)/1000000 -> 0 | M35: =(-CB_SMI_Mixto_EXT_BAJA!I12)/1000000 -> 0 | ... U35: =(-CB_SMI_Mixto_EXT_BAJA!Q12)/1000000 -> 0 | W35: =NPV($D$67,G35:U35)+F35 -> -0.064752611 | X35: =PMT($D$67,15,-W35) -> -0.0066671078 | Y35: =W35*1000000/7744865 -> -0.0083607152 | Z35: =W35/$W$36 -> 0.001757211
C36: VI Total: | F36: =SUM(F30:F35) -> -0.92647887 | G36: =SUM(G30:G35) -> -13.439211 | H36: =SUM(H30:H35) -> -13.439211 | I36: =SUM(I30:I35) -> -13.439211 | J36: =SUM(J30:J35) -> 0 | K36: =SUM(K30:K35) -> 0 | L36: =SUM(L30:L35) -> 0 | M36: =SUM(M30:M35) -> 0 | ... U36: =SUM(U30:U35) -> 0 | W36: =NPV($D$67,G36:U36)+F36 -> -36.849651 | X36: =PMT($D$67,15,-W36) -> -3.7941419 | Y36: =W36*1000000/7744865 -> -4.7579462 | Z36: =W36/$W$36 -> 1
B38: COMA [MUSD] | C38: Operación Comunicaciones UM - SGO | F38: 0 | G38: =(-CB_SMI_Mixto_EXT_BAJA!C13/1000000)*G$25 -> 0 | H38: =(-CB_SMI_Mixto_EXT_BAJA!D13/1000000)*H$25 -> 0 | I38: =(-CB_SMI_Mixto_EXT_BAJA!E13/1000000)*I$25 -> 0 | J38: =(-CB_SMI_Mixto_EXT_BAJA!F13/1000000)*J$25 -> 0 | K38: =(-CB_SMI_Mixto_EXT_BAJA!G13/1000000)*K$25 -> 0 | L38: =(-CB_SMI_Mixto_EXT_BAJA!H13/1000000)*L$25 -> 0 | M38: =(-CB_SMI_Mixto_EXT_BAJA!I13/1000000)*M$25 -> 0 | N38: =(-CB_SMI_Mixto_EXT_BAJA!J13/1000000)*N$25 -> 0 | ... U38: =(-CB_SMI_Mixto_EXT_BAJA!Q13/1000000)*U$25 -> 0 | W38: =NPV($D$67,G38:U38)+F38 -> 0 | X38: =PMT($D$67,15,-W38) -> 0 | Y38: =W38*1000000/7744865 -> 0 | Z38: =W38/$W$43 -> 0
C39: Operación Comunicaciones DCU - SGO | F39: 0 | G39: =(-CB_SMI_Mixto_EXT_BAJA!C14/1000000)*G$25 -> -0.26314023 | H39: =(-CB_SMI_Mixto_EXT_BAJA!D14/1000000)*H$25 -> -0.52628045 | I39: =(-CB_SMI_Mixto_EXT_BAJA!E14/1000000)*I$25 -> -0.78942068 | J39: =(-CB_SMI_Mixto_EXT_BAJA!F14/1000000)*J$25 -> -0.78942068 | K39: =(-CB_SMI_Mixto_EXT_BAJA!G14/1000000)*K$25 -> -0.78942068 | L39: =(-CB_SMI_Mixto_EXT_BAJA!H14/1000000)*L$25 -> -0.78942068 | M39: =(-CB_SMI_Mixto_EXT_BAJA!I14/1000000)*M$25 -> -0.78942068 | N39: =(-CB_SMI_Mixto_EXT_BAJA!J14/1000000)*N$25 -> -0.78942068 | ... U39: =(-CB_SMI_Mixto_EXT_BAJA!Q14/1000000)*U$25 -> -0.78942068 | W39: =NPV($D$67,G39:U39)+F39 -> -6.9363653 | X39: =PMT($D$67,15,-W39) -> -0.71418735 | Y39: =W39*1000000/7744865 -> -0.8956083 | Z39: =W39/$W$43 -> 0.61869888
C40: Operación HES | F40: 0 | G40: =(-CB_SMI_Mixto_EXT_BAJA!C15/1000000)*G$25 -> -0.12499161 | H40: =(-CB_SMI_Mixto_EXT_BAJA!D15/1000000)*H$25 -> -0.24998322 | I40: =(-CB_SMI_Mixto_EXT_BAJA!E15/1000000)*I$25 -> -0.37497482 | J40: =(-CB_SMI_Mixto_EXT_BAJA!F15/1000000)*J$25 -> -0.37497482 | K40: =(-CB_SMI_Mixto_EXT_BAJA!G15/1000000)*K$25 -> -0.37497482 | L40: =(-CB_SMI_Mixto_EXT_BAJA!H15/1000000)*L$25 -> -0.37497482 | M40: =(-CB_SMI_Mixto_EXT_BAJA!I15/1000000)*M$25 -> -0.37497482 | N40: =(-CB_SMI_Mixto_EXT_BAJA!J15/1000000)*N$25 -> -0.37497482 | ... U40: =(-CB_SMI_Mixto_EXT_BAJA!Q15/1000000)*U$25 -> -0.37497482 | W40: =NPV($D$67,G40:U40)+F40 -> -3.2947735 | X40: =PMT($D$67,15,-W40) -> -0.33923899 | Y40: =W40*1000000/7744865 -> -0.42541394 | Z40: =W40/$W$43 -> 0.29388197
C41: Operación MDMS | F41: 0 | G41: =(-CB_SMI_Mixto_EXT_BAJA!C16/1000000)*G$25 -> -0.017739826 | H41: =(-CB_SMI_Mixto_EXT_BAJA!D16/1000000)*H$25 -> -0.035479652 | I41: =(-CB_SMI_Mixto_EXT_BAJA!E16/1000000)*I$25 -> -0.053219479 | J41: =(-CB_SMI_Mixto_EXT_BAJA!F16/1000000)*J$25 -> -0.053219479 | K41: =(-CB_SMI_Mixto_EXT_BAJA!G16/1000000)*K$25 -> -0.053219479 | L41: =(-CB_SMI_Mixto_EXT_BAJA!H16/1000000)*L$25 -> -0.053219479 | M41: =(-CB_SMI_Mixto_EXT_BAJA!I16/1000000)*M$25 -> -0.053219479 | N41: =(-CB_SMI_Mixto_EXT_BAJA!J16/1000000)*N$25 -> -0.053219479 | ... U41: =(-CB_SMI_Mixto_EXT_BAJA!Q16/1000000)*U$25 -> -0.053219479 | W41: =NPV($D$67,G41:U41)+F41 -> -0.46762107 | X41: =PMT($D$67,15,-W41) -> -0.048147558 | Y41: =W41*1000000/7744865 -> -0.060378209 | Z41: =W41/$W$43 -> 0.041710121
C42: SyM Equipos | F42: 0 | G42: =(-CB_SMI_Mixto_EXT_BAJA!C17/1000000)*G$25 -> -0.019440612 | H42: =(-CB_SMI_Mixto_EXT_BAJA!D17/1000000)*H$25 -> -0.038881224 | I42: =(-CB_SMI_Mixto_EXT_BAJA!E17/1000000)*I$25 -> -0.058321836 | J42: =(-CB_SMI_Mixto_EXT_BAJA!F17/1000000)*J$25 -> -0.058321836 | K42: =(-CB_SMI_Mixto_EXT_BAJA!G17/1000000)*K$25 -> -0.058321836 | L42: =(-CB_SMI_Mixto_EXT_BAJA!H17/1000000)*L$25 -> -0.058321836 | M42: =(-CB_SMI_Mixto_EXT_BAJA!I17/1000000)*M$25 -> -0.058321836 | N42: =(-CB_SMI_Mixto_EXT_BAJA!J17/1000000)*N$25 -> -0.058321836 | ... U42: =(-CB_SMI_Mixto_EXT_BAJA!Q17/1000000)*U$25 -> -0.058321836 | W42: =NPV($D$67,G42:U42)+F42 -> -0.51245372 | X42: =PMT($D$67,15,-W42) -> -0.052763651 | Y42: =W42*1000000/7744865 -> -0.066166901 | Z42: =W42/$W$43 -> 0.045709031
C43: COMA Total: | F43: =SUM(F38:F42) -> 0 | G43: =SUM(G38:G42) -> -0.42531227 | H43: =SUM(H38:H42) -> -0.85062455 | I43: =SUM(I38:I42) -> -1.2759368 | J43: =SUM(J38:J42) -> -1.2759368 | K43: =SUM(K38:K42) -> -1.2759368 | L43: =SUM(L38:L42) -> -1.2759368 | M43: =SUM(M38:M42) -> -1.2759368 | ... U43: =SUM(U38:U42) -> -1.2759368 | W43: =NPV($D$67,G43:U43)+F43 -> -11.211214 | X43: =PMT($D$67,15,-W43) -> -1.1543375 | Y43: =W43*1000000/7744865 -> -1.4475673 | Z43: =W43/$W$43 -> 1
B45: Costos Totales (VI + COMA) | F45: =F36+F43 -> -0.92647887 | G45: =G36+G43 -> -13.864524 | H45: =H36+H43 -> -14.289836 | I45: =I36+I43 -> -14.715148 | J45: =J36+J43 -> -1.2759368 | K45: =K36+K43 -> -1.2759368 | L45: =L36+L43 -> -1.2759368 | M45: =M36+M43 -> -1.2759368 | ... U45: =U36+U43 -> -1.2759368 | W45: =NPV($D$67,G45:U45)+F45 -> -48.060865 | X45: =PMT($D$67,15,-W45) -> -4.9484795 | Y45: =W45*1000000/7744865 -> -6.2055136
B47: Beneficios [MUSD] | C47: Ahorro de lectura pedestre | F47: 0 | G47: =(CB_SMI_Mixto_EXT_BAJA!C18/1000000)*G$25 -> 0 | H47: =(CB_SMI_Mixto_EXT_BAJA!D18/1000000)*H$25 -> 0 | I47: =(CB_SMI_Mixto_EXT_BAJA!E18/1000000)*I$25 -> 0 | J47: =(CB_SMI_Mixto_EXT_BAJA!F18/1000000)*J$25 -> 0 | K47: =(CB_SMI_Mixto_EXT_BAJA!G18/1000000)*K$25 -> 0 | L47: =(CB_SMI_Mixto_EXT_BAJA!H18/1000000)*L$25 -> 0 | M47: =(CB_SMI_Mixto_EXT_BAJA!I18/1000000)*M$25 -> 0 | N47: =(CB_SMI_Mixto_EXT_BAJA!J18/1000000)*N$25 -> 0 | ... U47: =(CB_SMI_Mixto_EXT_BAJA!Q18/1000000)*U$25 -> 0 | V47: =U47/$U$56 -> 0 | W47: =NPV($D$67,G47:U47)+F47 -> 0 | X47: =PMT($D$67,15,-W47) -> 0 | Y47: =W47*1000000/7744865 -> 0 | Z47: =W47/$W$56 -> 0
C48: Corte y Reposición remoto | F48: 0 | G48: =(CB_SMI_Mixto_EXT_BAJA!C19/1000000)*G$25 -> 0 | H48: =(CB_SMI_Mixto_EXT_BAJA!D19/1000000)*H$25 -> 0 | I48: =(CB_SMI_Mixto_EXT_BAJA!E19/1000000)*I$25 -> 0 | J48: =(CB_SMI_Mixto_EXT_BAJA!F19/1000000)*J$25 -> 0 | K48: =(CB_SMI_Mixto_EXT_BAJA!G19/1000000)*K$25 -> 0 | L48: =(CB_SMI_Mixto_EXT_BAJA!H19/1000000)*L$25 -> 0 | M48: =(CB_SMI_Mixto_EXT_BAJA!I19/1000000)*M$25 -> 0 | N48: =(CB_SMI_Mixto_EXT_BAJA!J19/1000000)*N$25 -> 0 | ... U48: =(CB_SMI_Mixto_EXT_BAJA!Q19/1000000)*U$25 -> 0 | V48: =U48/$U$56 -> 0 | W48: =NPV($D$67,G48:U48)+F48 -> 0 | X48: =PMT($D$67,15,-W48) -> 0 | Y48: =W48*1000000/7744865 -> 0 | Z48: =W48/$W$56 -> 0
C49: Reducción de Pérdidas No Técnicas | F49: 0 | G49: =(CB_SMI_Mixto_EXT_BAJA!C20/1000000)*G$25 -> 0 | H49: =(CB_SMI_Mixto_EXT_BAJA!D20/1000000)*H$25 -> 0 | I49: =(CB_SMI_Mixto_EXT_BAJA!E20/1000000)*I$25 -> 0 | J49: =(CB_SMI_Mixto_EXT_BAJA!F20/1000000)*J$25 -> 0 | K49: =(CB_SMI_Mixto_EXT_BAJA!G20/1000000)*K$25 -> 0 | L49: =(CB_SMI_Mixto_EXT_BAJA!H20/1000000)*L$25 -> 0 | M49: =(CB_SMI_Mixto_EXT_BAJA!I20/1000000)*M$25 -> 0 | N49: =(CB_SMI_Mixto_EXT_BAJA!J20/1000000)*N$25 -> 0 | ... U49: =(CB_SMI_Mixto_EXT_BAJA!Q20/1000000)*U$25 -> 0 | V49: =U49/$U$56 -> 0 | W49: =NPV($D$67,G49:U49)+F49 -> 0 | X49: =PMT($D$67,15,-W49) -> 0 | Y49: =W49*1000000/7744865 -> 0 | Z49: =W49/$W$56 -> 0
C50: Reducción del tiempo de respuesta ante Fallas | F50: 0 | G50: =(CB_SMI_Mixto_EXT_BAJA!C21/1000000)*G$25 -> 0.056656597 | H50: =(CB_SMI_Mixto_EXT_BAJA!D21/1000000)*H$25 -> 0.11331319 | I50: =(CB_SMI_Mixto_EXT_BAJA!E21/1000000)*I$25 -> 0.16996979 | J50: =(CB_SMI_Mixto_EXT_BAJA!F21/1000000)*J$25 -> 0.16996979 | K50: =(CB_SMI_Mixto_EXT_BAJA!G21/1000000)*K$25 -> 0.16996979 | L50: =(CB_SMI_Mixto_EXT_BAJA!H21/1000000)*L$25 -> 0.16996979 | M50: =(CB_SMI_Mixto_EXT_BAJA!I21/1000000)*M$25 -> 0.16996979 | N50: =(CB_SMI_Mixto_EXT_BAJA!J21/1000000)*N$25 -> 0.16996979 | ... U50: =(CB_SMI_Mixto_EXT_BAJA!Q21/1000000)*U$25 -> 0.16996979 | V50: =U50/$U$56 -> 0.032520696 | W50: =NPV($D$67,G50:U50)+F50 -> 1.4934655 | X50: =PMT($D$67,15,-W50) -> 0.15377134 | Y50: =W50*1000000/7744865 -> 0.192833 | Z50: =W50/$W$56 -> 0.033168331
C51: Reducción del costo de la energía en horas de Sol | F51: 0 | G51: =(CB_SMI_Mixto_EXT_BAJA!C22/1000000)*G$25 -> 0 | H51: =(CB_SMI_Mixto_EXT_BAJA!D22/1000000)*H$25 -> 0 | I51: =(CB_SMI_Mixto_EXT_BAJA!E22/1000000)*I$25 -> 0 | J51: =(CB_SMI_Mixto_EXT_BAJA!F22/1000000)*J$25 -> 0 | K51: =(CB_SMI_Mixto_EXT_BAJA!G22/1000000)*K$25 -> 0 | L51: =(CB_SMI_Mixto_EXT_BAJA!H22/1000000)*L$25 -> 0 | M51: =(CB_SMI_Mixto_EXT_BAJA!I22/1000000)*M$25 -> 0 | N51: =(CB_SMI_Mixto_EXT_BAJA!J22/1000000)*N$25 -> 0 | ... U51: =(CB_SMI_Mixto_EXT_BAJA!Q22/1000000)*U$25 -> 0 | V51: =U51/$U$56 -> 0 | W51: =NPV($D$67,G51:U51)+F51 -> 0 | X51: =PMT($D$67,15,-W51) -> 0 | Y51: =W51*1000000/7744865 -> 0 | Z51: =W51/$W$56 -> 0
C52: Reducción del consumo de Clientes Finales | F52: 0 | G52: =(CB_SMI_Mixto_EXT_BAJA!C23/1000000)*G$25 -> 0 | H52: =(CB_SMI_Mixto_EXT_BAJA!D23/1000000)*H$25 -> 0 | I52: =(CB_SMI_Mixto_EXT_BAJA!E23/1000000)*I$25 -> 0 | J52: =(CB_SMI_Mixto_EXT_BAJA!F23/1000000)*J$25 -> 0 | K52: =(CB_SMI_Mixto_EXT_BAJA!G23/1000000)*K$25 -> 0 | L52: =(CB_SMI_Mixto_EXT_BAJA!H23/1000000)*L$25 -> 0 | M52: =(CB_SMI_Mixto_EXT_BAJA!I23/1000000)*M$25 -> 0 | N52: =(CB_SMI_Mixto_EXT_BAJA!J23/1000000)*N$25 -> 0 | ... U52: =(CB_SMI_Mixto_EXT_BAJA!Q23/1000000)*U$25 -> 0 | V52: =U52/$U$56 -> 0 | W52: =NPV($D$67,G52:U52)+F52 -> 0 | X52: =PMT($D$67,15,-W52) -> 0 | Y52: =W52*1000000/7744865 -> 0 | Z52: =W52/$W$56 -> 0
C53: Reducción de emisiones de CO2 | F53: 0 | G53: =(CB_SMI_Mixto_EXT_BAJA!C24/1000000)*G$25 -> 0 | H53: =(CB_SMI_Mixto_EXT_BAJA!D24/1000000)*H$25 -> 0 | I53: =(CB_SMI_Mixto_EXT_BAJA!E24/1000000)*I$25 -> 0 | J53: =(CB_SMI_Mixto_EXT_BAJA!F24/1000000)*J$25 -> 0 | K53: =(CB_SMI_Mixto_EXT_BAJA!G24/1000000)*K$25 -> 0 | L53: =(CB_SMI_Mixto_EXT_BAJA!H24/1000000)*L$25 -> 0 | M53: =(CB_SMI_Mixto_EXT_BAJA!I24/1000000)*M$25 -> 0 | N53: =(CB_SMI_Mixto_EXT_BAJA!J24/1000000)*N$25 -> 0 | ... U53: =(CB_SMI_Mixto_EXT_BAJA!Q24/1000000)*U$25 -> 0 | V53: =U53/$U$56 -> 0 | W53: =NPV($D$67,G53:U53)+F53 -> 0 | X53: =PMT($D$67,15,-W53) -> 0 | Y53: =W53*1000000/7744865 -> 0 | Z53: =W53/$W$56 -> 0
C54: Reducción servicio Atención al Cliente | F54: 0 | G54: =(CB_SMI_Mixto_EXT_BAJA!C25/1000000)*G$25 -> 0 | H54: =(CB_SMI_Mixto_EXT_BAJA!D25/1000000)*H$25 -> 0 | I54: =(CB_SMI_Mixto_EXT_BAJA!E25/1000000)*I$25 -> 0 | J54: =(CB_SMI_Mixto_EXT_BAJA!F25/1000000)*J$25 -> 0 | K54: =(CB_SMI_Mixto_EXT_BAJA!G25/1000000)*K$25 -> 0 | L54: =(CB_SMI_Mixto_EXT_BAJA!H25/1000000)*L$25 -> 0 | M54: =(CB_SMI_Mixto_EXT_BAJA!I25/1000000)*M$25 -> 0 | N54: =(CB_SMI_Mixto_EXT_BAJA!J25/1000000)*N$25 -> 0 | ... U54: =(CB_SMI_Mixto_EXT_BAJA!Q25/1000000)*U$25 -> 0 | V54: =U54/$U$56 -> 0 | W54: =NPV($D$67,G54:U54)+F54 -> 0 | X54: =PMT($D$67,15,-W54) -> 0 | Y54: =W54*1000000/7744865 -> 0 | Z54: =W54/$W$56 -> 0
C55: Reducción en Inversión de infraestructura de red | F55: 0 | G55: =(CB_SMI_Mixto_EXT_BAJA!C26/1000000)*G$25 -> 1.6158046 | H55: =(CB_SMI_Mixto_EXT_BAJA!D26/1000000)*H$25 -> 3.2340537 | I55: =(CB_SMI_Mixto_EXT_BAJA!E26/1000000)*I$25 -> 4.904544 | J55: =(CB_SMI_Mixto_EXT_BAJA!F26/1000000)*J$25 -> 4.9160464 | K55: =(CB_SMI_Mixto_EXT_BAJA!G26/1000000)*K$25 -> 4.9235331 | L55: =(CB_SMI_Mixto_EXT_BAJA!H26/1000000)*L$25 -> 4.9289234 | M55: =(CB_SMI_Mixto_EXT_BAJA!I26/1000000)*M$25 -> 4.9341837 | N55: =(CB_SMI_Mixto_EXT_BAJA!J26/1000000)*N$25 -> 4.9749673 | ... U55: =(CB_SMI_Mixto_EXT_BAJA!Q26/1000000)*U$25 -> 5.0565417 | V55: =U55/$U$56 -> 0.9674793 | W55: =NPV($D$67,G55:U55)+F55 -> 43.533386 | X55: =PMT($D$67,15,-W55) -> 4.4823177 | Y55: =W55*1000000/7744865 -> 5.6209354 | Z55: =W55/$W$56 -> 0.96683167
C56: Beneficios Total: | F56: =SUM(F47:F55) -> 0 | G56: =SUM(G47:G55) -> 1.6724612 | H56: =SUM(H47:H55) -> 3.3473669 | I56: =SUM(I47:I55) -> 5.0745138 | J56: =SUM(J47:J55) -> 5.0860162 | K56: =SUM(K47:K55) -> 5.0935029 | L56: =SUM(L47:L55) -> 5.0988932 | M56: =SUM(M47:M55) -> 5.1041535 | ... U56: =SUM(U47:U55) -> 5.2265115 | W56: =NPV($D$67,G56:U56)+F56 -> 45.026851 | X56: =PMT($D$67,15,-W56) -> 4.6360891 | Y56: =W56*1000000/7744865 -> 5.8137684 | Z56: =W56/$W$56 -> 1
B58: Flujo | F58: =F45+F56 -> -0.92647887 | G58: =G45+G56 -> -12.192062 | H58: =H45+H56 -> -10.942469 | I58: =I45+I56 -> -9.6406343 | J58: =J45+J56 -> 3.8100794 | K58: =K45+K56 -> 3.8175661 | L58: =L45+L56 -> 3.8229564 | M58: =M45+M56 -> 3.8282167 | ... U58: =U45+U56 -> 3.9505747
B60: Flujo del periodo anterior | F60: 0 | G60: =F61 -> -0.92647887 | H60: =G61 -> -13.118541 | I60: =H61 -> -24.06101 | J60: =I61 -> -33.701644 | K60: =J61 -> -29.891565 | L60: =K61 -> -26.073999 | M60: =L61 -> -22.251043 | N60: =M61 -> -18.422826 | ... U60: =T61 -> 8.872679
B61: Flujo Acumulado | F61: =F58+F60 -> -0.92647887 | G61: =G58+G60 -> -13.118541 | H61: =H58+H60 -> -24.06101 | I61: =I58+I60 -> -33.701644 | J61: =J58+J60 -> -29.891565 | K61: =K58+K60 -> -26.073999 | L61: =L58+L60 -> -22.251043 | M61: =M58+M60 -> -18.422826 | ... U61: =U58+U60 -> 12.823254
B63: Flujo descontado (6%) | F63: =F58/(1+0.06)^F27 -> -0.92647887 | G63: =G58/(1+0.06)^G27 -> -11.501946 | H63: =H58/(1+0.06)^H27 -> -9.7387584 | I63: =I58/(1+0.06)^I27 -> -8.0944624 | J63: =J58/(1+0.06)^J27 -> 3.0179397 | K63: =K58/(1+0.06)^K27 -> 2.8527075 | L63: =L58/(1+0.06)^L27 -> 2.6950334 | M63: =M58/(1+0.06)^M27 -> 2.5459827 | ... U63: =U58/(1+0.06)^U27 -> 1.6484368
B64: Flujo Acumulado descontado (6%) | F64: =F63 -> -0.92647887 | G64: =F64+G63 -> -12.428424 | H64: =G64+H63 -> -22.167183 | I64: =H64+I63 -> -30.261645 | J64: =I64+J63 -> -27.243706 | K64: =J64+K63 -> -24.390998 | L64: =K64+L63 -> -21.695965 | M64: =L64+M63 -> -19.149982 | N64: =M64+N63 -> -16.722523 | ... U64: =T64+U63 -> -3.0340134
B67: Tasa | D67: =J4 -> 0.06 | H67: Monto [MUSD] | J67: Monto [USD/cliente] | L67: Monto [$/cliente]
F68: VAN (Costos) | H68: =NPV(D67,G45:U45)+F45 -> -48.060865 | J68: =H68*1000000/$D$77 -> -80.934664 | L68: =J68*$S$4 -> -77645.479
B69: VAN | D69: =NPV(D67,G58:U58)+F58 -> -3.0340134 | F69: Anualidad (Costos) | H69: =PMT(D67,15,-H68) -> -4.9484795 | J69: =H69*1000000/$D$77 -> -8.3332567 | L69: =J69*$S$4 -> -7994.5931
B70: TIR | D70: =IRR(F58:U58) -> 0.044357624 | F70: Mensualidad (Costos) | H70: =H69/12 -> -0.41237329 | J70: =J69/12 -> -0.69443806 | L70: =L69/12 -> -666.21609
B71: B/C | D71: =NPV(D67,G56:U56)/-(F36+NPV(D67,G36:U36)+NPV(D67,G43:U43)) -> 0.93687143
F72: VAN (Beneficios) | H72: =NPV(D67,G56:U56)+F56 -> 45.026851 | J72: =H72*1000000/$D$77 -> 75.825374 | L72: =J72*$S$4 -> 72743.831
B73: # Clientes Alta | D73: 2527114 | F73: Anualidad (Beneficios) | H73: =PMT(D67,15,-H72) -> 4.6360891 | J73: =H73*1000000/$D$77 -> 7.8071901 | L73: =J73*$S$4 -> 7489.9059
B74: # Clientes Media | D74: 2158536 | F74: Mensualidad (Beneficios) | H74: =H73/12 -> 0.38634076 | J74: =J73/12 -> 0.65059918 | L74: =L73/12 -> 624.15883
B75: # Clientes Baja | D75: 1173397
B76: # Clientes Muy Baja | D76: 1288141 | F76: VAN (Neto) | H76: =H72+H68 -> -3.0340134 | J76: =H76*1000000/$D$77 -> -5.1092892 | L76: =J76*$S$4 -> -4901.6477
B77: # Clientes Ext. Baja | D77: 593823 | F77: Anualidad (Neto) | H77: =PMT(D67,15,-H76) -> -0.31239041 | J77: =H77*1000000/$D$77 -> -0.52606654 | L77: =J77*$S$4 -> -504.68719
F78: Mensualidad (Neto) | H78: =H77/12 -> -0.026032534 | J78: =J77/12 -> -0.043838878 | L78: =L77/12 -> -42.057266
B79: # Clientes Regulados | D79: =SUM(D73:D77) -> 7741011
